Workbook
Name AF_butter: #REF!
Name Area: [1]Resumen!$B$17:$B$26
Name Cost_Exp: #REF!
Name Dolar_Cprador_BNA: #REF!
Name Dolar_Cprador_Div: #REF!
Name Dolar_Prom_BNA: #REF!
Name Dolar_Vdor_BNA: #REF!
Name EX_CN: [2]NUMBEO!#REF!
Name EX_EU: #REF!
Name FOB_Maní: #REF!
Name GBPtoUSD: #REF!
Name PPP: '[3]Valuation factors'!$B$14
Name PPP_CI: #REF!
Name PPP_CM: #REF!
Name PPP_ID: #REF!
Name PPP_IN: #REF!
Name Pr_Flete: #REF!
Name Pr_Ind: #REF!
Name Pr_Proc_Exp: #REF!
Name Pr_Proc_Ind: #REF!
Name Pr_Prom_Alq: #REF!
Name Pr_Prom_Cosecha: #REF!

Sheet Intro
B2: Title | C2: Living Wage Global Dataset 2023/2024
B3: Author | C3: Samuel Vionnet - Valuing Impact Edgar Sacayon - Valuing Impact
B4: Citation | C4: Vionnet & Sacayon (2024) Living Wage Global Dataset. Valuing Impact
B5: Version | C5: v1.0
B6: Contact | C6: sv@valuingimpact.com
B7: Related publication | C7: Vionnet Samuel (2020) A worldwide living wage dataset for benchmarking compensation practices in global value chain - Technical paper (previous version of this dataset, published in 2020)
B8: Data reference year | C8: 2023
B9: Living wage methodology | C9: Anker & Anker 2017 The detailed methodology adaptations is provided below.
B10: Living wage type | C10: Typical family: Accounts for 1 + country employment rate working parents and uses the national fertility rate for the number of children. Standard family: Accounts for 2 adults, 2 children families. Considers 1.8 working adults. Individual person: cost of living for one single adult Single working parent typical family: accounts for 2 adults and uses the national fertility rate for the number of children. Considers only one working parent.
C11: The Numbeo data was adjusted to reflect a urban and rural living wage. Rural living wage: accounts for 20% lower food costs, 75% of rent for a 3 bedroom apartment outside the City Centre, 75% of electricity costs. Urban living wage: considers 75% of the rent for a 3 bedroom apartment in the City Centre + the total costs of food, electricity, mobile phones and internet.
B12: Coverage | C12: 218 Countries and 360 Cities
B13: Note | C13: The cost of living data was extracted from Numbeo, however it was not collected for the purpose of creating a living wage specifically. Uncertainties are high. All countries that were not covered by Numbeo were covered using a linear regresion model considering the existing living wage estimates and the purchasing power parity (PPP). This linear regresion model was re-calculated for each type of living wage. R2 is around 0.6, whcih shows an unperfect correlation. For countries: Data derived from Numbeo is indicated as "a" in the source column, and as "b" for the linear regression model (LRM). Some countries have the indication a/b wich indicates we chose the lower PPP value for the region and income level as we observed some inconsistencies. For cities: data derived from Numbeo is indicated as "a". If one of the cost data (food or housing) is missing and is replaced by an regional average, the letter "b" is indicated. If both food and housing data are missing and are replaced by regional averages, the letter "c" is used. Data is far from being perfect, specially when estimated with the linear regression model. Some effect at the edge of the distribution (such as very low income countries) makes the estimates a bit too variable on the PPP value. We recommend to use those values with care and when possible recalculate a living wages with primary data or access other datasets such as the WageIndicator Foundation, Global Living Wage Coalition or Fair Wage.
B15: Numbeo model
B16: Data source | C16: https://www.numbeo.com/cost-of-living/
B17: Food costs | C17: The food costs were estimed based on a diet combinging Numbeo prices per country leading to 2,300 kcal per day per person (for children, we assumed 70% of an adult diet). We adjusted the rate of fat, proteins, carbohydrates and other food types to follow the recommendations from the WHO. The ratio between food items are constant across countries, despite the fact that some variations might occur depending on local preferences, food availability, culture and religions. The food prices per day were then multiplied by 365 days, accounting for the number of adults and kids in the household. Most of the diet impact is based on the following food items: Loaf of Fresh White Bread Eggs Local Cheese Apples Oranges Potato Lettuce Rice Tomato Banana Onion Beef Round Chicken Breasts Milk
B18: Housing costs | C18: Housing costs consideres: housing + electricity, water and waste + internet services + mobile phone. The housing costs were provided directly by Numbeo, although for rural and urban housing/apartment costs we considered only 75% of the numbeo value as some adaptations were needed given that most of the prices communicated are average market prices which correspond to standards above basic but decent living conditions. For families we considered a 3 bedroom apartment/house, although we considered a single bedroom apartament for single individual living wage estimate. For rural utilities we used 75% of the averge utility cost of Numbeo and 75% of an internet plan (Numbeo considers 60Mo/s speed minimum with unlimited data, which is not necessary for the purpose of a basic but decent life quality).
B19: NFNH | C19: The Non Food Non Housing costs were estimated separately for adults and children. We considered the following compoenents: - Transport (monthly public transport plan for adults, to go to work and other activities) - Clothes (we considered a cost equivalent for each individual to a pair of jeans or dress, 2-3 t-shirts and some underwear) - Education (we considered the cost of education for kids only, considering 10% of the cost of a private school, given that this was the only data available in Numbeo. We considered that kids are going to public school, although there are still costs associated to public education). - Health (we considered health for all members of the family as 10% additional to the total costs of diet and housing. This is a standard estimate for households across the world, although this value can vary greatly depending on socio-economic context and personal situations).
B20: Unexpected events | C20: We considered a 5% cost over all the previous costs planned for unexpected events, according to the Anker&Anker methodology.
B21: Household data | C21: We used World Bank data to translate the cost of living into a net living wage. We considered the natality rate for 2021 and unemployment rate (to calculate the level of employment for the typical living wages). Those living wages based on typical family (statistical household composition) are not excelent at reflecting the real situation of households, as you cannot split a children in a fraction and most of the time, you either have a job or not. For this reason we tend to prefer the definition of the standard family or the single working parent typical family (as a higher bounardy for the living wage).
B22: Taxation rates | C22: We developed our own dataset of personal income tax rates for low incomes, pulling from PwC and KPMG websites on the topic. Not all countries were covered and when no information was available we assumed a 10% tax rates, which reflects an average taxation rates for low income households. Applying the taxation rates allows us to calculate a gross living wage estimates (what is currently considered a living wage).
B23: Data gaps | C23: The data from Numbeo was sorted based on the World Bank's regions and income levels. Initially, a complete dataset was created by removing any country or city that didn't have complete data. In cases where data was missing, we used the average income level and region data from the complete country-level dataset provided by the World Bank. Currency exchange rates were sourced from the World Bank and FAO.
B24: World Bank Data | C24: Price level ratio of PPP conversion factor (GDP) to market exchange rate Unemployment, total (% of total labor force) (modeled ILO estimate)
B25: World Health Organization | C25: Total fertility rate (live births per woman) 2023

Sheet LW2023
A1: No | B1: Numbeo Country name | C1: Country WB | D1: Country_Code | E1: City | F1: Region | G1: World Bank Income Level | H1: RURAL LW for a Typical family [USD/year] | I1: URBAN LW for a Typical family [USD/year] | J1: LW for a Typical familiy average [USD/year] | K1: RURAL LW for a Standard family [USD/year] | L1: URBAN LW for a Standard Family [USD/year] | M1: LW for a Standard Family average [USD/year] | N1: RURAL LW for a Single Individual [USD/year] | O1: URBAN LW for a Single Individual [USD/year] | P1: LW for a Single Individual average [USD/year] | Q1: RURAL LW for a Single working parent [USD/year] | R1: URBAN LW for a Single working parent [USD/year] | S1: LW for a Single Working Parent average [USD/year] | T1: Source
A2: 1 | B2: Aruba | C2: Aruba | D2: ABW | E2: Country | F2: Latin America & Caribbean | G2: High income | H2: 12377.365 | I2: 18885.814 | J2: 15631.589 | K2: 12750.086 | L2: 19314.95 | M2: 16032.518 | N2: 10661.764 | O2: 14060.621 | P2: 12361.193 | Q2: 24124.49 | R2: 36812.998 | S2: 30468.744 | T2: b
A3: 2 | B3: Afghanistan | C3: Afghanistan | D3: AFG | E3: Country | F3: South Asia | G3: Low income | H3: 4336.4169 | I3: 7145.9235 | J3: 5741.1702 | K3: 3979.4757 | L3: 6718.4609 | M3: 5348.9683 | N3: 2603.8651 | O3: 4462.6134 | P3: 3533.2392 | Q3: 8233.79 | R3: 13610.045 | S3: 10921.917 | T3: b
A4: 3 | B4: Angola | C4: Angola | D4: AGO | E4: Country | F4: Sub-Saharan Africa | G4: Lower middle income | H4: 8053.4072 | I4: 12572.778 | J4: 10313.093 | K4: 8033.7582 | L4: 12541.285 | M4: 10287.522 | N4: 6328.6913 | O4: 8899.3665 | P4: 7614.0289 | Q4: 15579.389 | R4: 24335.789 | S4: 19957.589 | T4: b
A5: 4 | B5: Albania | C5: Albania | D5: ALB | E5: Country | F5: Europe & Central Asia | G5: Upper middle income | H5: 6041.0066 | I5: 9992.4517 | J5: 8016.7291 | K5: 6512.7174 | L5: 10550.028 | M5: 8531.3729 | N5: 4546.4966 | O5: 7103.8613 | P5: 5825.179 | Q5: 11379.505 | R5: 18822.881 | S5: 15101.193 | T5: a
A6: 5 | B6: Andorra | C6: Andorra | D6: AND | E6: Country | F6: Europe & Central Asia | G6: High income | H6: 10174.827 | I6: 15670.079 | J6: 12922.453 | K6: 10347.682 | L6: 15864.58 | M6: 13106.131 | N6: 8454.5828 | O6: 11431.58 | P6: 9943.0815 | Q6: 19771.785 | R6: 30457.355 | S6: 25114.57 | T6: b
A7: 6 | B7: United Arab Emirates | C7: United Arab Emirates | D7: ARE | E7: Country | F7: Middle East & North Africa | G7: High income | H7: 15662.135 | I7: 27653.762 | J7: 21657.949 | K7: 16643.997 | L7: 28775.286 | M7: 22709.642 | N7: 16530.131 | O7: 24144.531 | P7: 20337.331 | Q7: 30858.948 | R7: 54485.931 | S7: 42672.44 | T7: a
A8: 7 | B8: Argentina | C8: Argentina | D8: ARG | E8: Country | F8: Latin America & Caribbean | G8: Upper middle income | H8: 6414.4503 | I8: 9467.7961 | J8: 7941.1232 | K8: 6197.1359 | L8: 9221.46 | M8: 7709.298 | N8: 3985.2828 | O8: 5753.4137 | P8: 4869.3482 | Q8: 12392.397 | R8: 18291.309 | S8: 15341.853 | T8: a
A9: 8 | B9: Armenia | C9: Armenia | D9: ARM | E9: Country | F9: Europe & Central Asia | G9: Upper middle income | H9: 12744.212 | I9: 21740.377 | J9: 17242.295 | K9: 13090.862 | L9: 22149.388 | M9: 17620.125 | N9: 11591.321 | O9: 17274.238 | P9: 14432.779 | Q9: 24393.951 | R9: 41613.691 | S9: 33003.821 | T9: a
A10: 9 | B10: American Samoa | C10: American Samoa | D10: ASM | E10: Country | F10: East Asia & Pacific | G10: High income | H10: 8909.6044 | I10: 13822.838 | J10: 11366.221 | K10: 8967.6496 | L10: 13882.555 | M10: 11425.102 | N10: 7186.6934 | O10: 9921.3587 | P10: 8554.0261 | Q10: 17271.425 | R10: 26806.431 | S10: 22038.928 | T10: b
A11: 10 | B11: Antigua and Barbuda | C11: Antigua and Barbuda | D11: ATG | E11: Country | F11: Latin America & Caribbean | G11: High income | H11: 13615.404 | I11: 20693.367 | J11: 17154.386 | K11: 14100.47 | L11: 21254.392 | M11: 17677.431 | N11: 11902.414 | O11: 15538.396 | P11: 13720.405 | Q11: 26571.131 | R11: 40385.484 | S11: 33478.307 | T11: b
A12: 11 | B12: Australia | C12: Australia | D12: AUS | E12: Country | F12: East Asia & Pacific | G12: High income | H12: 18345.299 | I12: 29073.34 | J12: 23709.319 | K12: 18816.406 | L12: 29619.759 | M12: 24218.083 | N12: 16618.971 | O12: 22645.877 | P12: 19632.424 | Q12: 36011.822 | R12: 57070.966 | S12: 46541.394 | T12: a
A13: 12 | B13: Austria | C13: Austria | D13: AUT | E13: Country | F13: Europe & Central Asia | G13: High income | H13: 14282.266 | I13: 21220.164 | J13: 17751.215 | K13: 15246.28 | L13: 22328.396 | M13: 18787.338 | N13: 11730.331 | O13: 15244.249 | P13: 13487.29 | Q13: 27851.847 | R13: 41381.441 | S13: 34616.644 | T13: a
... A219: 218 | B219: Zimbabwe | C219: Zimbabwe | D219: ZWE | E219: Country | F219: Sub-Saharan Africa | G219: Lower middle income | H219: 6722.2189 | I219: 9839.0002 | J219: 8280.6095 | K219: 5693.6016 | L219: 8593.7325 | M219: 7143.667 | N219: 4233.7053 | O219: 5756.2851 | P219: 4994.9952 | Q219: 12822.229 | R219: 18767.303 | S219: 15794.766 | T219: a
A220: 219 | B220: Alexandria, Egypt | C220: Egypt | D220: EGY | E220: Rural | F220: Middle East & North Africa | G220: Lower middle income | H220: 0 | I220: 4860.4074 | K220: 0 | L220: 4255.3229 | N220: 0 | O220: 2684.1964 | Q220: 0 | R220: 9409.8946 | T220: a
A221: 220 | B221: Rawalpindi, Pakistan | C221: Pakistan | D221: PAK | E221: Rawalpindi | F221: South Asia | G221: Lower middle income | H221: 0 | I221: 5737.6917 | K221: 0 | L221: 4881.4786 | N221: 0 | O221: 2793.4257 | Q221: 0 | R221: 11154.36 | T221: b
A222: 221 | B222: Bhopal, India | C222: India | D222: IND | E222: Bhopal | F222: South Asia | G222: Lower middle income | H222: 0 | I222: 4309.6407 | K222: 0 | L222: 4228.9445 | N222: 0 | O222: 2362.4724 | Q222: 0 | R222: 8411.4705 | T222: c
A223: 222 | B223: Karachi, Pakistan | C223: Pakistan | D223: PAK | E223: Karachi | F223: South Asia | G223: Lower middle income | H223: 0 | I223: 4509.607 | K223: 0 | L223: 3921.4634 | N223: 0 | O223: 2493.2695 | Q223: 0 | R223: 8766.9015 | T223: a
A224: 223 | B224: Bhubaneswar, India | C224: India | D224: IND | E224: Bhubaneswar | F224: South Asia | G224: Lower middle income | H224: 0 | I224: 4309.6407 | K224: 0 | L224: 4228.9445 | N224: 0 | O224: 2362.4724 | Q224: 0 | R224: 8411.4705 | T224: c
A225: 224 | B225: Indore, India | C225: India | D225: IND | E225: Indore | F225: South Asia | G225: Lower middle income | H225: 0 | I225: 4188.2981 | K225: 0 | L225: 4107.6019 | N225: 0 | O225: 2241.1298 | Q225: 0 | R225: 8174.6365 | T225: b
A226: 225 | B226: Nagpur, India | C226: India | D226: IND | E226: Nagpur | F226: South Asia | G226: Lower middle income | H226: 0 | I226: 4309.6407 | K226: 0 | L226: 4228.9445 | N226: 0 | O226: 2362.4724 | Q226: 0 | R226: 8411.4705 | T226: c
A227: 226 | B227: Coimbatore, India | C227: India | D227: IND | E227: Coimbatore | F227: South Asia | G227: Lower middle income | H227: 0 | I227: 4309.6407 | K227: 0 | L227: 4228.9445 | N227: 0 | O227: 2362.4724 | Q227: 0 | R227: 8411.4705 | T227: c
A228: 227 | B228: Dhaka, Bangladesh | C228: Bangladesh | D228: BGD | E228: Dhaka | F228: South Asia | G228: Lower middle income | H228: 0 | I228: 6051.0819 | K228: 0 | L228: 6120.4577 | N228: 0 | O228: 3684.6516 | Q228: 0 | R228: 11843.722 | T228: a
A229: 228 | B229: Lahore, Pakistan | C229: Pakistan | D229: PAK | E229: Lahore | F229: South Asia | G229: Lower middle income | H229: 0 | I229: 4988.7419 | K229: 0 | L229: 4368.5882 | N229: 0 | O229: 2864.5656 | Q229: 0 | R229: 9698.3637 | T229: a
A230: 229 | B230: Lucknow (Lakhnau), India | C230: India | D230: IND | E230: Lucknow (Lakhnau) | F230: South Asia | G230: Lower middle income | H230: 0 | I230: 4309.6407 | K230: 0 | L230: 4228.9445 | N230: 0 | O230: 2362.4724 | Q230: 0 | R230: 8411.4705 | T230: c
A231: 230 | B231: Kolkata, India | C231: India | D231: IND | E231: Kolkata | F231: South Asia | G231: Lower middle income | H231: 0 | I231: 3805.822 | K231: 0 | L231: 3746.6561 | N231: 0 | O231: 2381.3655 | Q231: 0 | R231: 7428.1272 | T231: a
... A579: 578 | B579: Brooklyn, NY, United States | C579: United States | D579: USA | E579: Brooklyn | F579: North America | G579: High income | H579: 0 | I579: 14402.341 | K579: 0 | L579: 14816.584 | N579: 0 | O579: 9568.5059 | Q579: 0 | R579: 28278.997 | T579: c

Sheet PIVOT
C3: Average of Cost of Diet [$/person per day] | D3: Column Labels
C4: Row Labels | D4: High income | E4: Low income | F4: Lower middle income | G4: Upper middle income | H4: Grand Total
C5: East Asia & Pacific | D5: 7.2223381 | F5: 4.3957042 | G5: 4.2210333 | H5: 5.6682211
C6: Europe & Central Asia | D6: 5.7419345 | F6: 2.8562444 | G6: 3.1798567 | H6: 4.7400571
C7: Latin America & Caribbean | D7: 4.4976967 | F7: 3.4570333 | G7: 3.3711133 | H7: 3.7125696
C8: Middle East & North Africa | D8: 4.4382729 | F8: 2.6191024 | G8: 3.0066583 | H8: 3.5207775
C9: North America | D9: 5.3047944 | H9: 5.3047944
C10: South Asia | F10: 2.5483533 | H10: 2.5483533
C11: Sub-Saharan Africa | E11: 0 | F11: 3.1846917 | G11: 2.2040778 | H11: 2.1433653
C12: Grand Total | D12: 5.5957984 | E12: 0 | F12: 3.0833056 | G12: 3.2623137 | H12: 4.1823227
C16: Average of NFNH Cost Adult | D16: Column Labels
C17: Row Labels | D17: High income | E17: Low income | F17: Lower middle income | G17: Upper middle income | H17: Grand Total
C18: East Asia & Pacific | D18: 255.91084 | F18: 59.773075 | G18: 155.89405 | H18: 176.93629
C19: Europe & Central Asia | D19: 238.94906 | F19: 111.1928 | G19: 167.03321 | H19: 207.84254
C20: Latin America & Caribbean | D20: 88.42624 | F20: 0 | G20: 97.75033 | H20: 83.507912
C21: Middle East & North Africa | D21: 140.66904 | F21: 102.07824 | G21: 69.5958 | H21: 116.41715
C22: North America | D22: 156.2097 | H22: 156.2097
C23: South Asia | F23: 67.63112 | H23: 67.63112
C24: Sub-Saharan Africa | E24: 0 | F24: 94.705517 | G24: 51.610333 | H24: 60.255342
C25: Grand Total | D25: 206.8656 | E25: 0 | F25: 81.244707 | G25: 129.42942 | H25: 149.57947
C29: Average of NFNH Cost Kid | D29: Column Labels
C30: Row Labels | D30: High income | E30: Low income | F30: Lower middle income | G30: Upper middle income | H30: Grand Total
C31: East Asia & Pacific | D31: 2058.5796 | F31: 558.38858 | G31: 1293.3011 | H31: 1454.4544
C32: Europe & Central Asia | D32: 1108.8325 | F32: 605.40547 | G32: 576.80456 | H32: 906.90271
C33: Latin America & Caribbean | D33: 342.94964 | F33: 0 | G33: 400.88113 | H33: 336.67997
C34: Middle East & North Africa | D34: 748.14866 | F34: 268.4611 | G34: 221.5193 | H34: 488.67386
C35: North America | D35: 1294.917 | H35: 1294.917
C36: South Asia | F36: 155.09532 | H36: 155.09532
C37: Sub-Saharan Africa | E37: 0 | F37: 266.67395 | G37: 173.93433 | H37: 176.82056
C38: Grand Total | D38: 1118.2863 | E38: 0 | F38: 307.57477 | G38: 552.90957 | H38: 734.95114
C42: Average of Housing Family URBAN (apt. 3bed.) [$/year] | D42: Column Labels
C43: Row Labels | D43: High income | E43: Low income | F43: Lower middle income | G43: Upper middle income | H43: Grand Total
C44: East Asia & Pacific | D44: 19093.618 | F44: 6308.958 | G44: 7175.793 | H44: 12506.289
C45: Europe & Central Asia | D45: 12032.908 | F45: 5267.516 | G45: 5988.7816 | H45: 9672.098
C46: Latin America & Caribbean | D46: 10234.452 | F46: 3304.68 | G46: 6214.5384 | H46: 7054.5296
C47: Middle East & North Africa | D47: 12891.3 | F47: 4410.2263 | G47: 3990.018 | H47: 8351.8835
C48: North America | D48: 12148.744 | H48: 12148.744
C49: South Asia | F49: 2894.6448 | H49: 2894.6448
C50: Sub-Saharan Africa | E50: 0 | F50: 7207.872 | G50: 3879.512 | H50: 4573.814
C51: Grand Total | D51: 12949.203 | E51: 0 | F51: 5045.9178 | G51: 5891.1427 | H51: 8706.0102
C54: Average of Housing Family RURAL (apt. 3bed.) ($/year) | D54: Column Labels
C55: Row Labels | D55: High income | E55: Low income | F55: Lower middle income | G55: Upper middle income | H55: Grand Total
C56: East Asia & Pacific | D56: 18689.181 | F56: 5656.479 | G56: 6111.489 | H56: 11859.743
C57: Europe & Central Asia | D57: 13610.783 | F57: 5199.264 | G57: 6285.4648 | H57: 10736.01
C58: Latin America & Caribbean | D58: 10460.158 | F58: 3693.597 | G58: 6098.988 | H58: 7098.6978
C59: Middle East & North Africa | D59: 13547.71 | F59: 3822.6274 | G59: 3877.317 | H59: 8405.5708
C60: North America | D60: 14278.814 | H60: 14278.814
C61: South Asia | F61: 2343.438 | H61: 2343.438
C62: Sub-Saharan Africa | E62: 0 | F62: 5194.457 | G62: 4359.604 | H62: 3687.1295
C63: Grand Total | D63: 14020.306 | E63: 0 | F63: 4268.638 | G63: 5898.5663 | H63: 9007.417
C66: Average of Housing Single URBAN (apt. 1bed.) [$/year] | D66: Column Labels
C67: Row Labels | D67: High income | E67: Low income | F67: Lower middle income | G67: Upper middle income | H67: Grand Total
C68: East Asia & Pacific | D68: 10183.353 | F68: 3245.673 | G68: 3298.698 | H68: 6497.3968
C69: Europe & Central Asia | D69: 7790.4095 | F69: 3178.676 | G69: 3695.1936 | H69: 6189.0597
C70: Latin America & Caribbean | D70: 6239.136 | F70: 2153.28 | G70: 3478.6104 | H70: 4134.6085
C71: Middle East & North Africa | D71: 7660.1775 | F71: 2655.6291 | G71: 2883.828 | H71: 5037.5576
C72: North America | D72: 7780.984 | H72: 7780.984
C73: South Asia | F73: 1401.1728 | H73: 1401.1728
C74: Sub-Saharan Africa | E74: 0 | F74: 2721.918 | G74: 2437.912 | H74: 1970.437
C75: Grand Total | D75: 7942.7961 | E75: 0 | F75: 2546.3724 | G75: 3426.1821 | H75: 5157.4797
C78: Average of Housing Single RURAL (apt. 1bed.) [$/year] | D78: Column Labels
C79: Row Labels | D79: High income | E79: Low income | F79: Lower middle income | G79: Upper middle income | H79: Grand Total
C80: East Asia & Pacific | D80: 10741.269 | F80: 2998.8015 | G80: 2904.3615 | H80: 6586.7688
C81: Europe & Central Asia | D81: 8797.6858 | F81: 3143.304 | G81: 3726.3452 | H81: 6818.2549
C82: Latin America & Caribbean | D82: 5921.1336 | F82: 2030.712 | G82: 3371.322 | H82: 3963.5478
C83: Middle East & North Africa | D83: 7774.626 | F83: 2324.4231 | G83: 2724.777 | H83: 4936.3249
C84: North America | D84: 9099.704 | H84: 9099.704
C85: South Asia | F85: 1237.644 | H85: 1237.644
C86: Sub-Saharan Africa | E86: 0 | F86: 2510.897 | G86: 2508.754 | H86: 1882.637
C87: Grand Total | D87: 8642.7607 | E87: 0 | F87: 2333.7447 | G87: 3358.8724 | H87: 5402.0373

Sheet PPP_WB
A1: Data Source | B1: World Development Indicators
A2: Last Updated Date | B2: 45343
B3: 1 | C3: 2 | D3: 3 | E3: 4 | F3: 5 | G3: 6 | H3: 7 | I3: 8 | J3: 9 | K3: 10 | L3: 11 | M3: 12 | N3: 13 | O3: 14 | P3: 15 | Q3: 16 | R3: 17 | S3: 18 | T3: 19 | U3: 20 | V3: 21 | W3: 22 | X3: 23 | Y3: 24 | Z3: 25 | AA3: 26 | AB3: 27 | AC3: 28 | AD3: 29 | AE3: 30 | AF3: 31 | AG3: 32 | AH3: 33 | AI3: 34 | AJ3: 35 | AK3: 36 | AL3: 37 | AM3: 38 | AN3: 39 | AO3: 40 | AP3: 41 | AQ3: 42 | AR3: 43 | AS3: 44 | AT3: 45 | AU3: 46 | AV3: 47 | AW3: 48 | AX3: 49 | AY3: 50 | AZ3: 51 | BA3: 52 | BB3: 53 | BC3: 54 | BD3: 55 | BE3: 56 | BF3: 57 | BG3: 58 | BH3: 59 | BI3: 60 | BJ3: 61 | BK3: 62 | BL3: 63 | BM3: 64 | BN3: 65 | BO3: 66
A4: Country Name | B4: Country Code | C4: Indicator Name | D4: Indicator Code | E4: 1960 | F4: 1961 | G4: 1962 | H4: 1963 | I4: 1964 | J4: 1965 | K4: 1966 | L4: 1967 | M4: 1968 | N4: 1969 | O4: 1970 | P4: 1971 | Q4: 1972 | R4: 1973 | S4: 1974 | T4: 1975 | U4: 1976 | V4: 1977 | W4: 1978 | X4: 1979 | Y4: 1980 | Z4: 1981 | AA4: 1982 | AB4: 1983 | AC4: 1984 | AD4: 1985 | AE4: 1986 | AF4: 1987 | AG4: 1988 | AH4: 1989 | AI4: 1990 | AJ4: 1991 | AK4: 1992 | AL4: 1993 | AM4: 1994 | AN4: 1995 | AO4: 1996 | AP4: 1997 | AQ4: 1998 | AR4: 1999 | AS4: 2000 | AT4: 2001 | AU4: 2002 | AV4: 2003 | AW4: 2004 | AX4: 2005 | AY4: 2006 | AZ4: 2007 | BA4: 2008 | BB4: 2009 | BC4: 2010 | BD4: 2011 | BE4: 2012 | BF4: 2013 | BG4: 2014 | BH4: 2015 | BI4: 2016 | BJ4: 2017 | BK4: 2018 | BL4: 2019 | BM4: 2020 | BN4: 2021 | BO4: 2022 | BP4: Region | BQ4: Income group
A5: Aruba | B5: ABW | C5: Price level ratio of PPP conversion factor (GDP) to market exchange rate | D5: PA.NUS.PPPC.RF | AI5: 0.51589712 | AJ5: 0.52704076 | AK5: 0.53499399 | AL5: 0.55030622 | AM5: 0.57268019 | AN5: 0.57985398 | AO5: 0.58798837 | AP5: 0.59943206 | AQ5: 0.63184074 | AR5: 0.63670577 | AS5: 0.62905123 | AT5: 0.64982074 | AU5: 0.66822379 | AV5: 0.67527109 | AW5: 0.67609641 | AX5: 0.68875931 | AY5: 0.69142361 | AZ5: 0.70801446 | BA5: 0.72430159 | BB5: 0.73194703 | BC5: 0.71440666 | BD5: 0.72789978 | BE5: 0.73620188 | BF5: 0.71795586 | BG5: 0.73119708 | BH5: 0.76107146 | BI5: 0.75700816 | BJ5: 0.75457522 | BK5: 0.76248533 | BL5: 0.79469648 | BM5: 0.77762476 | BN5: 0.70705353 | BO5: 0.6830897 | BP5: =_xlfn.XLOOKUP(B5,Countries_WB!$C$2:$C$219,Countries_WB!$D$2:$D$219,"No Data",0) -> Latin America & Caribbean | BQ5: =_xlfn.XLOOKUP(B5,Countries_WB!$C$2:$C$219,Countries_WB!$E$2:$E$219,"No Data",0) -> High income
A6: Africa Eastern and Southern | B6: AFE | C6: Price level ratio of PPP conversion factor (GDP) to market exchange rate | D6: PA.NUS.PPPC.RF | BO6: =BN6 -> 0 | BP6: =_xlfn.XLOOKUP(B6,Countries_WB!$C$2:$C$219,Countries_WB!$D$2:$D$219,"No Data",0) -> No Data | BQ6: =_xlfn.XLOOKUP(B6,Countries_WB!$C$2:$C$219,Countries_WB!$E$2:$E$219,"No Data",0) -> No Data
A7: Afghanistan | B7: AFG | C7: Price level ratio of PPP conversion factor (GDP) to market exchange rate | D7: PA.NUS.PPPC.RF | AU7: 0.1931618 | AV7: 0.20568097 | AW7: 0.22826509 | AX7: 0.23623876 | AY7: 0.24446166 | AZ7: 0.29238498 | BA7: 0.28628263 | BB7: 0.28780712 | BC7: 0.31758122 | BD7: 0.3478633 | BE7: 0.33364052 | BF7: 0.30975502 | BG7: 0.29680887 | BH7: 0.26637575 | BI7: 0.25844651 | BJ7: 0.25101022 | BK7: 0.23319185 | BL7: 0.22957137 | BM7: 0.24634673 | BN7: 0.21264027 | BO7: =BN7 -> 0.21264027 | BP7: =_xlfn.XLOOKUP(B7,Countries_WB!$C$2:$C$219,Countries_WB!$D$2:$D$219,"No Data",0) -> South Asia | BQ7: =_xlfn.XLOOKUP(B7,Countries_WB!$C$2:$C$219,Countries_WB!$E$2:$E$219,"No Data",0) -> Low income
A8: Africa Western and Central | B8: AFW | C8: Price level ratio of PPP conversion factor (GDP) to market exchange rate | D8: PA.NUS.PPPC.RF | BO8: =BN8 -> 0 | BP8: =_xlfn.XLOOKUP(B8,Countries_WB!$C$2:$C$219,Countries_WB!$D$2:$D$219,"No Data",0) -> No Data | BQ8: =_xlfn.XLOOKUP(B8,Countries_WB!$C$2:$C$219,Countries_WB!$E$2:$E$219,"No Data",0) -> No Data
A9: Angola | B9: AGO | C9: Price level ratio of PPP conversion factor (GDP) to market exchange rate | D9: PA.NUS.PPPC.RF | AI9: 0.35436814 | AJ9: 0.3141862 | AK9: 0.26057401 | AL9: 0.24524466 | AM9: 0.17283246 | AN9: 0.18369947 | AO9: 0.18746716 | AP9: 0.20175839 | AQ9: 0.16154689 | AR9: 0.14743169 | AS9: 0.20756973 | AT9: 0.19067377 | AU9: 0.2306853 | AV9: 0.25596743 | AW9: 0.29706528 | AX9: 0.39306322 | AY9: 0.48429374 | AZ9: 0.51534795 | BA9: 0.61702896 | BB9: 0.4827015 | BC9: 0.54455056 | BD9: 0.68777264 | BE9: 0.68799704 | BF9: 0.66214036 | BG9: 0.61700785 | BH9: 0.44230124 | BI9: 0.25753118 | BJ9: 0.33804791 | BK9: 0.3606651 | BL9: 0.31840437 | BM9: 0.22786327 | BN9: 0.2954679 | BO9: 0.43010915 | BP9: =_xlfn.XLOOKUP(B9,Countries_WB!$C$2:$C$219,Countries_WB!$D$2:$D$219,"No Data",0) -> Sub-Saharan Africa | BQ9: =_xlfn.XLOOKUP(B9,Countries_WB!$C$2:$C$219,Countries_WB!$E$2:$E$219,"No Data",0) -> Lower middle income
A10: Albania | B10: ALB | C10: Price level ratio of PPP conversion factor (GDP) to market exchange rate | D10: PA.NUS.PPPC.RF | AI10: 0.29221517 | AJ10: 0.21279983 | AK10: 0.13296045 | AL10: 0.2154609 | AM10: 0.30909759 | AN10: 0.33944503 | AO10: 0.33887086 | AP10: 0.26396736 | AQ10: 0.26936148 | AR10: 0.29762319 | AS10: 0.29178611 | AT10: 0.29804499 | AU10: 0.30572862 | AV10: 0.36920219 | AW10: 0.43730345 | AX10: 0.45586615 | AY10: 0.45277494 | AZ10: 0.49354409 | BA10: 0.53115875 | BB10: 0.46680062 | BC10: 0.42522762 | BD10: 0.43468464 | BE10: 0.40353091 | BF10: 0.41747294 | BG10: 0.40665332 | BH10: 0.33903701 | BI10: 0.34143205 | BJ10: 0.35478921 | BK10: 0.39172937 | BL10: 0.37454545 | BM10: 0.37951951 | BN10: 0.41220218 | BO10: 0.36606802 | BP10: =_xlfn.XLOOKUP(B10,Countries_WB!$C$2:$C$219,Countries_WB!$D$2:$D$219,"No Data",0) -> Europe & Central Asia | BQ10: =_xlfn.XLOOKUP(B10,Countries_WB!$C$2:$C$219,Countries_WB!$E$2:$E$219,"No Data",0) -> Upper middle income
A11: Andorra | B11: AND | C11: Price level ratio of PPP conversion factor (GDP) to market exchange rate | D11: PA.NUS.PPPC.RF | BO11: =BN11 -> 0 | BP11: =_xlfn.XLOOKUP(B11,Countries_WB!$C$2:$C$219,Countries_WB!$D$2:$D$219,"No Data",0) -> Europe & Central Asia | BQ11: =_xlfn.XLOOKUP(B11,Countries_WB!$C$2:$C$219,Countries_WB!$E$2:$E$219,"No Data",0) -> High income
A12: Arab World | B12: ARB | C12: Price level ratio of PPP conversion factor (GDP) to market exchange rate | D12: PA.NUS.PPPC.RF | BO12: =BN12 -> 0 | BP12: =_xlfn.XLOOKUP(B12,Countries_WB!$C$2:$C$219,Countries_WB!$D$2:$D$219,"No Data",0) -> No Data | BQ12: =_xlfn.XLOOKUP(B12,Countries_WB!$C$2:$C$219,Countries_WB!$E$2:$E$219,"No Data",0) -> No Data
A13: United Arab Emirates | B13: ARE | C13: Price level ratio of PPP conversion factor (GDP) to market exchange rate | D13: PA.NUS.PPPC.RF | AI13: 0.30721963 | AJ13: 0.29957965 | AK13: 0.29819689 | AL13: 0.2950151 | AM13: 0.28808884 | AN13: 0.29319779 | AO13: 0.30454805 | AP13: 0.2965343 | AQ13: 0.28064371 | AR13: 0.30011027 | AS13: 0.32709111 | AT13: 0.3123692 | AU13: 0.31917372 | AV13: 0.32574291 | AW13: 0.34419606 | AX13: 0.38888424 | AY13: 0.42237056 | AZ13: 0.46280294 | BA13: 0.53825252 | BB13: 0.45362224 | BC13: 0.52231922 | BD13: 0.57906287 | BE13: 0.59298151 | BF13: 0.60267283 | BG13: 0.5943001 | BH13: 0.59572081 | BI13: 0.59625653 | BJ13: 0.6049808 | BK13: 0.63766672 | BL13: 0.60641831 | BM13: 0.52658678 | BN13: 0.57371062 | BO13: 0.60694538 | BP13: =_xlfn.XLOOKUP(B13,Countries_WB!$C$2:$C$219,Countries_WB!$D$2:$D$219,"No Data",0) -> Middle East & North Africa | BQ13: =_xlfn.XLOOKUP(B13,Countries_WB!$C$2:$C$219,Countries_WB!$E$2:$E$219,"No Data",0) -> High income
A14: Argentina | B14: ARG | C14: Price level ratio of PPP conversion factor (GDP) to market exchange rate | D14: PA.NUS.PPPC.RF | AI14: 0.60289798 | AJ14: 0.71722015 | AK14: 0.78342566 | AL14: 0.73185857 | AM14: 0.73623721 | AN14: 0.74394034 | AO14: 0.73018131 | AP14: 0.7144733 | AQ14: 0.69447301 | AR14: 0.67224511 | AS14: 0.66417111 | AT14: 0.64241992 | AU14: 0.25818847 | AV14: 0.30372284 | AW14: 0.35011035 | AX14: 0.37640609 | AY14: 0.39545434 | AZ14: 0.43672924 | BA14: 0.51782555 | BB14: 0.50366313 | BC14: 0.57495647 | BD14: 0.66497196 | BE14: 0.66607756 | BF14: 0.64973487 | BG14: 0.62664811 | BH14: 0.68584551 | BI14: 0.6298181 | BJ14: 0.61927206 | BK14: 0.50635841 | BL14: 0.43305567 | BM14: 0.40873882 | BN14: 0.44686788 | BO14: 0.5145284 | BP14: =_xlfn.XLOOKUP(B14,Countries_WB!$C$2:$C$219,Countries_WB!$D$2:$D$219,"No Data",0) -> Latin America & Caribbean | BQ14: =_xlfn.XLOOKUP(B14,Countries_WB!$C$2:$C$219,Countries_WB!$E$2:$E$219,"No Data",0) -> Upper middle income
A15: Armenia | B15: ARM | C15: Price level ratio of PPP conversion factor (GDP) to market exchange rate | D15: PA.NUS.PPPC.RF | AI15: 0.2302015 | AJ15: 0.23128173 | AK15: 0.23892492 | AL15: 0.24153291 | AM15: 0.24562995 | AN15: 0.25126551 | AO15: 0.25349854 | AP15: 0.24761344 | AQ15: 0.26358548 | AR15: 0.24520893 | AS15: 0.2345254 | AT15: 0.23191914 | AU15: 0.22628697 | AV15: 0.2299382 | AW15: 0.25820504 | AX15: 0.30115974 | AY15: 0.33623157 | AZ15: 0.41520106 | BA15: 0.48274692 | BB15: 0.41408507 | BC15: 0.42870874 | BD15: 0.43932784 | BE15: 0.39317571 | BF15: 0.39022474 | BG15: 0.39715806 | BH15: 0.36182653 | BI15: 0.33555225 | BJ15: 0.32311043 | BK15: 0.3241386 | BL15: 0.32352275 | BM15: 0.31943117 | BN15: 0.31721607 | BO15: 0.37003861 | BP15: =_xlfn.XLOOKUP(B15,Countries_WB!$C$2:$C$219,Countries_WB!$D$2:$D$219,"No Data",0) -> Europe & Central Asia | BQ15: =_xlfn.XLOOKUP(B15,Countries_WB!$C$2:$C$219,Countries_WB!$E$2:$E$219,"No Data",0) -> Upper middle income
A16: American Samoa | B16: ASM | C16: Price level ratio of PPP conversion factor (GDP) to market exchange rate | D16: PA.NUS.PPPC.RF | BO16: =BN16 -> 0 | BP16: =_xlfn.XLOOKUP(B16,Countries_WB!$C$2:$C$219,Countries_WB!$D$2:$D$219,"No Data",0) -> East Asia & Pacific | BQ16: =_xlfn.XLOOKUP(B16,Countries_WB!$C$2:$C$219,Countries_WB!$E$2:$E$219,"No Data",0) -> High income
A17: Antigua and Barbuda | B17: ATG | C17: Price level ratio of PPP conversion factor (GDP) to market exchange rate | D17: PA.NUS.PPPC.RF | AI17: 0.6520796 | AJ17: 0.64718903 | AK17: 0.64834313 | AL17: 0.64481481 | AM17: 0.65181733 | AN17: 0.65377388 | AO17: 0.6611328 | AP17: 0.6618013 | AQ17: 0.66824339 | AR17: 0.66886928 | AS17: 0.64623768 | AT17: 0.64136898 | AU17: 0.63595851 | AV17: 0.61825632 | AW17: 0.61136301 | AX17: 0.61922212 | AY17: 0.60313627 | AZ17: 0.60919452 | BA17: 0.62391504 | BB17: 0.63132942 | BC17: 0.63302354 | BD17: 0.62643581 | BE17: 0.67724864 | BF17: 0.68682026 | BG17: 0.70915372 | BH17: 0.75538565 | BI17: 0.76297892 | BJ17: 0.77537077 | BK17: 0.76822486 | BL17: 0.76010837 | BM17: 0.75632045 | BN17: 0.75936743 | BO17: 0.75552332 | BP17: =_xlfn.XLOOKUP(B17,Countries_WB!$C$2:$C$219,Countries_WB!$D$2:$D$219,"No Data",0) -> Latin America & Caribbean | BQ17: =_xlfn.XLOOKUP(B17,Countries_WB!$C$2:$C$219,Countries_WB!$E$2:$E$219,"No Data",0) -> High income
A18: Australia | B18: AUS | C18: Price level ratio of PPP conversion factor (GDP) to market exchange rate | D18: PA.NUS.PPPC.RF | AI18: 1.0499433 | AJ18: 1.0574168 | AK18: 1.0202815 | AL18: 0.92108628 | AM18: 0.89880664 | AN18: 0.9719305 | AO18: 0.99501138 | AP18: 1.0225583 | AQ18: 0.88107712 | AR18: 0.81272716 | AS18: 0.82400316 | AT18: 0.71243028 | AU18: 0.6992801 | AV18: 0.78740711 | AW18: 0.97081448 | AX18: 1.0436844 | AY18: 1.050191 | AZ18: 1.1199812 | BA18: 1.3242023 | BB18: 1.0621192 | BC18: 1.3243821 | BD18: 1.4898029 | BE18: 1.5881371 | BF18: 1.4846383 | BG18: 1.3334554 | BH18: 1.2261028 | BI18: 1.0556047 | BJ18: 1.1143362 | BK18: 1.1397413 | BL18: 1.0584112 | BM18: 0.97466534 | BN18: 1.0803877 | BO18: 1.0297977 | BP18: =_xlfn.XLOOKUP(B18,Countries_WB!$C$2:$C$219,Countries_WB!$D$2:$D$219,"No Data",0) -> East Asia & Pacific | BQ18: =_xlfn.XLOOKUP(B18,Countries_WB!$C$2:$C$219,Countries_WB!$E$2:$E$219,"No Data",0) -> High income
A19: Austria | B19: AUT | C19: Price level ratio of PPP conversion factor (GDP) to market exchange rate | D19: PA.NUS.PPPC.RF | AI19: 1.1133825 | AJ19: 1.0869806 | AK19: 1.1684523 | AL19: 1.1080693 | AM19: 1.1326623 | AN19: 1.2796738 | AO19: 1.2136938 | AP19: 1.0502943 | AQ19: 1.0257248 | AR19: 0.98467725 | AS19: 0.83812759 | AT19: 0.82665799 | AU19: 0.8508244 | AV19: 1.0046096 | AW19: 1.092237 | AX19: 1.0972117 | AY19: 1.0799154 | AZ19: 1.1896695 | BA19: 1.2566488 | BB19: 1.17681 | BC19: 1.1165623 | BD19: 1.1572354 | BE19: 1.0453657 | BF19: 1.0586177 | BG19: 1.0612024 | BH19: 0.88629332 | BI19: 0.85998734 | BJ19: 0.87551308 | BK19: 0.90390612 | BL19: 0.8386409 | BM19: 0.85243352 | BN19: 0.89451596 | BO19: 0.76736286 | BP19: =_xlfn.XLOOKUP(B19,Countries_WB!$C$2:$C$219,Countries_WB!$D$2:$D$219,"No Data",0) -> Europe & Central Asia | BQ19: =_xlfn.XLOOKUP(B19,Countries_WB!$C$2:$C$219,Countries_WB!$E$2:$E$219,"No Data",0) -> High income
A20: Azerbaijan | B20: AZE | C20: Price level ratio of PPP conversion factor (GDP) to market exchange rate | D20: PA.NUS.PPPC.RF | AI20: 0.23570657 | AJ20: 0.1381004 | AK20: 0.014515373 | AL20: 0.06511922 | AM20: 0.060325485 | AN20: 0.1357263 | AO20: 0.17289738 | AP20: 0.20039266 | AQ20: 0.20215271 | AR20: 0.19123887 | AS20: 0.19372026 | AT20: 0.18660795 | AU20: 0.18344226 | AV20: 0.19045943 | AW20: 0.20252754 | AX20: 0.2341644 | AY20: 0.2675348 | AZ20: 0.32825213 | BA20: 0.42982358 | BB20: 0.3542935 | BC20: 0.39809414 | BD20: 0.48564845 | BE20: 0.46973288 | BF20: 0.45816338 | BG20: 0.45235584 | BH20: 0.36821234 | BI20: 0.27003542 | BJ20: 0.29368165 | BK20: 0.32573219 | BL20: 0.31922279 | BM20: 0.29180538 | BN20: 0.33954756 | BO20: 0.43537183 | BP20: =_xlfn.XLOOKUP(B20,Countries_WB!$C$2:$C$219,Countries_WB!$D$2:$D$219,"No Data",0) -> Europe & Central Asia | BQ20: =_xlfn.XLOOKUP(B20,Countries_WB!$C$2:$C$219,Countries_WB!$E$2:$E$219,"No Data",0) -> Upper middle income
A21: Burundi | B21: BDI | C21: Price level ratio of PPP conversion factor (GDP) to market exchange rate | D21: PA.NUS.PPPC.RF | AI21: 0.41590998 | AJ21: 0.39510548 | AK21: 0.3548028 | AL21: 0.3203667 | AM21: 0.321434 | AN21: 0.36978037 | AO21: 0.34286791 | AP21: 0.38343538 | AQ21: 0.33253466 | AR21: 0.29949863 | AS21: 0.25919966 | AT21: 0.25018251 | AU21: 0.22202927 | AV21: 0.20954953 | AW21: 0.22706293 | AX21: 0.26631734 | AY21: 0.27935936 | AZ21: 0.28003391 | BA21: 0.31141557 | BB21: 0.32943442 | BC21: 0.35322867 | BD21: 0.36596533 | BE21: 0.36537326 | BF21: 0.3468036 | BG21: 0.35372362 | BH21: 0.36303819 | BI21: 0.31638869 | BJ21: 0.32518573 | BK21: 0.30604802 | BL21: 0.28526399 | BM21: 0.28864105 | BN21: 0.28067749 | BO21: 0.30966647 | BP21: =_xlfn.XLOOKUP(B21,Countries_WB!$C$2:$C$219,Countries_WB!$D$2:$D$219,"No Data",0) -> Sub-Saharan Africa | BQ21: =_xlfn.XLOOKUP(B21,Countries_WB!$C$2:$C$219,Countries_WB!$E$2:$E$219,"No Data",0) -> Low income
A22: Belgium | B22: BEL | C22: Price level ratio of PPP conversion factor (GDP) to market exchange rate | D22: PA.NUS.PPPC.RF | AI22: 1.1022936 | AJ22: 1.0734542 | AK22: 1.1528946 | AL22: 1.088413 | AM22: 1.1249674 | AN22: 1.2657923 | AO22: 1.2086137 | AP22: 1.0458751 | AQ22: 1.0397611 | AR22: 0.99260876 | AS22: 0.83119588 | AT22: 0.79931174 | AU22: 0.82576953 | AV22: 0.99097342 | AW22: 1.1049845 | AX22: 1.1094648 | AY22: 1.0978014 | AZ22: 1.2044611 | BA22: 1.2750567 | BB22: 1.1857059 | BC22: 1.1091144 | BD22: 1.1579829 | BE22: 1.0562723 | BF22: 1.0706836 | BG22: 1.0630849 | BH22: 0.88760809 | BI22: 0.86450351 | BJ22: 0.87621913 | BK22: 0.9050918 | BL22: 0.83580079 | BM22: 0.83412069 | BN22: 0.87130823 | BO22: 0.76249251 | BP22: =_xlfn.XLOOKUP(B22,Countries_WB!$C$2:$C$219,Countries_WB!$D$2:$D$219,"No Data",0) -> Europe & Central Asia | BQ22: =_xlfn.XLOOKUP(B22,Countries_WB!$C$2:$C$219,Countries_WB!$E$2:$E$219,"No Data",0) -> High income
A23: Benin | B23: BEN | C23: Price level ratio of PPP conversion factor (GDP) to market exchange rate | D23: PA.NUS.PPPC.RF | AI23: 0.43251856 | AJ23: 0.40682925 | AK23: 0.32971804 | AL23: 0.40830152 | AM23: 0.27219587 | AN23: 0.34132307 | AO23: 0.3496493 | AP23: 0.31230095 | AQ23: 0.3215208 | AR23: 0.32986915 | AS23: 0.29166968 | AT23: 0.282051 | AU23: 0.30363092 | AV23: 0.36709998 | AW23: 0.39616121 | AX23: 0.40066919 | AY23: 0.40048716 | AZ23: 0.42728708 | BA23: 0.47887102 | BB23: 0.46270246 | BC23: 0.43839616 | BD23: 0.46776493 | BE23: 0.45833178 | BF23: 0.4686726 | BG23: 0.45577903 | BH23: 0.37300327 | BI23: 0.3618492 | BJ23: 0.37332487 | BK23: 0.38366221 | BL23: 0.35585919 | BM23: 0.36872009 | BN23: 0.37130683 | BO23: 0.32110081 | BP23: =_xlfn.XLOOKUP(B23,Countries_WB!$C$2:$C$219,Countries_WB!$D$2:$D$219,"No Data",0) -> Sub-Saharan Africa | BQ23: =_xlfn.XLOOKUP(B23,Countries_WB!$C$2:$C$219,Countries_WB!$E$2:$E$219,"No Data",0) -> Lower middle income
A24: Burkina Faso | B24: BFA | C24: Price level ratio of PPP conversion factor (GDP) to market exchange rate | D24: PA.NUS.PPPC.RF | AI24: 0.59728072 | AJ24: 0.53546278 | AK24: 0.55924411 | AL24: 0.50329717 | AM24: 0.28811314 | AN24: 0.33513627 | AO24: 0.32224997 | AP24: 0.28196636 | AQ24: 0.29776288 | AR24: 0.33039576 | AS24: 0.27768596 | AT24: 0.27377224 | AU24: 0.29330362 | AV24: 0.34918788 | AW24: 0.37429175 | AX24: 0.37653903 | AY24: 0.36620382 | AZ24: 0.39889112 | BA24: 0.4584953 | BB24: 0.44243496 | BC24: 0.43123853 | BD24: 0.47345669 | BE24: 0.46807499 | BF24: 0.46786684 | BG24: 0.46850125 | BH24: 0.38127785 | BI24: 0.36313643 | BJ24: 0.35951912 | BK24: 0.37095515 | BL24: 0.34856747 | BM24: 0.37322027 | BN24: 0.37013605 | BO24: 0.32551306 | BP24: =_xlfn.XLOOKUP(B24,Countries_WB!$C$2:$C$219,Countries_WB!$D$2:$D$219,"No Data",0) -> Sub-Saharan Africa | BQ24: =_xlfn.XLOOKUP(B24,Countries_WB!$C$2:$C$219,Countries_WB!$E$2:$E$219,"No Data",0) -> Low income
A25: Bangladesh | B25: BGD | C25: Price level ratio of PPP conversion factor (GDP) to market exchange rate | D25: PA.NUS.PPPC.RF | AI25: 0.41206133 | AJ25: 0.37734705 | AK25: 0.3583881 | AL25: 0.34970663 | AM25: 0.33555764 | AN25: 0.35127283 | AO25: 0.35341008 | AP25: 0.34541995 | AQ25: 0.33647708 | AR25: 0.32515272 | AS25: 0.31432915 | AT25: 0.2959567 | AU25: 0.28446617 | AV25: 0.29278829 | AW25: 0.29322985 | AX25: 0.28463782 | AY25: 0.26770493 | AZ25: 0.26989308 | BA25: 0.28750447 | BB25: 0.30414446 | BC25: 0.32023192 | BD25: 0.32881233 | BE25: 0.3006226 | BF25: 0.31233805 | BG25: 0.33220161 | BH25: 0.35113227 | BI25: 0.36414154 | BJ25: 0.37584234 | BK25: 0.37414762 | BL25: 0.37235468 | BM25: 0.37823362 | BN25: 0.3768345 | BO25: 0.36340505 | BP25: =_xlfn.XLOOKUP(B25,Countries_WB!$C$2:$C$219,Countries_WB!$D$2:$D$219,"No Data",0) -> South Asia | BQ25: =_xlfn.XLOOKUP(B25,Countries_WB!$C$2:$C$219,Countries_WB!$E$2:$E$219,"No Data",0) -> Lower middle income
A26: Bulgaria | B26: BGR | C26: Price level ratio of PPP conversion factor (GDP) to market exchange rate | D26: PA.NUS.PPPC.RF | AI26: 0.31340214 | AJ26: 0.17562752 | AK26: 0.1751464 | AL26: 0.18174099 | AM26: 0.15645762 | AN26: 0.29176416 | AO26: 0.21465819 | AP26: 0.23674578 | AQ26: 0.29466916 | AR26: 0.28577447 | AS26: 0.25242166 | AT26: 0.25443762 | AU26: 0.26879814 | AV26: 0.32308065 | AW26: 0.36838159 | AX26: 0.3789394 | AY26: 0.39654265 | AZ26: 0.45931616 | BA26: 0.506823 | BB26: 0.49276043 | BC26: 0.45885427 | BD26: 0.49895036 | BE26: 0.45511599 | BF26: 0.46174528 | BG26: 0.44914286 | BH26: 0.38501126 | BI26: 0.37731128 | BJ26: 0.39061712 | BK26: 0.41065907 | BL26: 0.39247851 | BM26: 0.40436952 | BN26: 0.43679234 | BO26: 0.4128885 | BP26: =_xlfn.XLOOKUP(B26,Countries_WB!$C$2:$C$219,Countries_WB!$D$2:$D$219,"No Data",0) -> Europe & Central Asia | BQ26: =_xlfn.XLOOKUP(B26,Countries_WB!$C$2:$C$219,Countries_WB!$E$2:$E$219,"No Data",0) -> Upper middle income
A27: Bahrain | B27: BHR | C27: Price level ratio of PPP conversion factor (GDP) to market exchange rate | D27: PA.NUS.PPPC.RF | AI27: 0.31770024 | AJ27: 0.30152267 | AK27: 0.28438994 | AL27: 0.26939915 | AM27: 0.28310384 | AN27: 0.28031367 | AO27: 0.27581502 | AP27: 0.27366566 | AQ27: 0.251521 | AR27: 0.25461437 | AS27: 0.32364416 | AT27: 0.30586631 | AU27: 0.31145552 | AV27: 0.33170226 | AW27: 0.35853538 | AX27: 0.39538163 | AY27: 0.41746187 | AZ27: 0.44076561 | BA27: 0.48162184 | BB27: 0.41637143 | BC27: 0.44204173 | BD27: 0.47520877 | BE27: 0.46678006 | BF27: 0.48052393 | BG27: 0.48901117 | BH27: 0.49662527 | BI27: 0.50500273 | BJ27: 0.49765349 | BK27: 0.50715908 | BL27: 0.49863617 | BM27: 0.46235026 | BN27: 0.48905763 | BO27: 0.49220932 | BP27: =_xlfn.XLOOKUP(B27,Countries_WB!$C$2:$C$219,Countries_WB!$D$2:$D$219,"No Data",0) -> Middle East & North Africa | BQ27: =_xlfn.XLOOKUP(B27,Countries_WB!$C$2:$C$219,Countries_WB!$E$2:$E$219,"No Data",0) -> High income
A28: Bahamas, The | B28: BHS | C28: Price level ratio of PPP conversion factor (GDP) to market exchange rate | D28: PA.NUS.PPPC.RF | AI28: 0.98157575 | AJ28: 0.97374055 | AK28: 0.98922702 | AL28: 0.95808901 | AM28: 0.95853874 | AN28: 0.94638563 | AO28: 0.93851643 | AP28: 0.94039157 | AQ28: 0.95828023 | AR28: 0.99174806 | AS28: 0.9787255 | AT28: 0.96054134 | AU28: 0.98325893 | AV28: 0.97536459 | AW28: 0.96121718 | AX28: 0.97911314 | AY28: 0.95767233 | AZ28: 0.95996098 | BA28: 0.95591721 | BB28: 0.93998539 | BC28: 0.92517664 | BD28: 0.89856344 | BE28: 0.91523546 | BF28: 0.90308458 | BG28: 0.90426666 | BH28: 0.93631327 | BI28: 0.92412019 | BJ28: 0.90140676 | BK28: 0.88321199 | BL28: 0.9021332 | BM28: 0.86962946 | BN28: 0.8407155 | BO28: 0.768348 | BP28: =_xlfn.XLOOKUP(B28,Countries_WB!$C$2:$C$219,Countries_WB!$D$2:$D$219,"No Data",0) -> Latin America & Caribbean | BQ28: =_xlfn.XLOOKUP(B28,Countries_WB!$C$2:$C$219,Countries_WB!$E$2:$E$219,"No Data",0) -> High income
A29: Bosnia and Herzegovina | B29: BIH | C29: Price level ratio of PPP conversion factor (GDP) to market exchange rate | D29: PA.NUS.PPPC.RF | AM29: 0.40714414 | AN29: 0.4906732 | AO29: 0.38061961 | AP29: 0.36694766 | AQ29: 0.35192534 | AR29: 0.36043875 | AS29: 0.32275364 | AT29: 0.32227641 | AU29: 0.34440548 | AV29: 0.41358777 | AW29: 0.45352474 | AX29: 0.45998804 | AY29: 0.46089358 | AZ29: 0.51154826 | BA29: 0.56385694 | BB29: 0.52217013 | BC29: 0.49586183 | BD29: 0.51044364 | BE29: 0.46376489 | BF29: 0.4658091 | BG29: 0.46616337 | BH29: 0.39358852 | BI29: 0.38208179 | BJ29: 0.39223145 | BK29: 0.40702398 | BL29: 0.37811971 | BM29: 0.38402565 | BN29: 0.41351095 | BO29: 0.37861383 | BP29: =_xlfn.XLOOKUP(B29,Countries_WB!$C$2:$C$219,Countries_WB!$D$2:$D$219,"No Data",0) -> Europe & Central Asia | BQ29: =_xlfn.XLOOKUP(B29,Countries_WB!$C$2:$C$219,Countries_WB!$E$2:$E$219,"No Data",0) -> Upper middle income
A30: Belarus | B30: BLR | C30: Price level ratio of PPP conversion factor (GDP) to market exchange rate | D30: PA.NUS.PPPC.RF | AK30: 0.18293846 | AL30: 0.34510882 | AM30: 0.34852683 | AN30: 0.35597793 | AO30: 0.35919806 | AP30: 0.30352195 | AQ30: 0.2982587 | AR30: 0.22682853 | AS30: 0.21998166 | AT30: 0.19926717 | AU30: 0.22065185 | AV30: 0.246888 | AW30: 0.28007142 | AX30: 0.32404193 | AY30: 0.3496333 | AZ30: 0.38398378 | BA30: 0.45875069 | BB30: 0.38094451 | BC30: 0.39283589 | BD30: 0.39410614 | BE30: 0.3840434 | BF30: 0.42108035 | BG30: 0.43883056 | BH30: 0.32975057 | BI30: 0.28335723 | BJ30: 0.31518376 | BK30: 0.32731629 | BL30: 0.34008479 | BM30: 0.32203523 | BN30: 0.34154892 | BO30: 0.3498022 | BP30: =_xlfn.XLOOKUP(B30,Countries_WB!$C$2:$C$219,Countries_WB!$D$2:$D$219,"No Data",0) -> Europe & Central Asia | BQ30: =_xlfn.XLOOKUP(B30,Countries_WB!$C$2:$C$219,Countries_WB!$E$2:$E$219,"No Data",0) -> Upper middle income
A31: Belize | B31: BLZ | C31: Price level ratio of PPP conversion factor (GDP) to market exchange rate | D31: PA.NUS.PPPC.RF | AI31: 0.66998017 | AJ31: 0.63214262 | AK31: 0.63913283 | AL31: 0.63605378 | AM31: 0.63918286 | AN31: 0.65933441 | AO31: 0.66527493 | AP31: 0.64418684 | AQ31: 0.65235645 | AR31: 0.63253314 | AS31: 0.62726675 | AT31: 0.60145256 | AU31: 0.59648606 | AV31: 0.56062537 | AW31: 0.55739561 | AX31: 0.5567275 | AY31: 0.55760112 | AZ31: 0.56375555 | BA31: 0.57260384 | BB31: 0.55488506 | BC31: 0.56013156 | BD31: 0.57561415 | BE31: 0.61951077 | BF31: 0.63214421 | BG31: 0.65624201 | BH31: 0.65926254 | BI31: 0.67113715 | BJ31: 0.68753254 | BK31: 0.67203545 | BL31: 0.65932945 | BM31: 0.64725923 | BN31: 0.62227147 | BO31: 0.62415566 | BP31: =_xlfn.XLOOKUP(B31,Countries_WB!$C$2:$C$219,Countries_WB!$D$2:$D$219,"No Data",0) -> Latin America & Caribbean | BQ31: =_xlfn.XLOOKUP(B31,Countries_WB!$C$2:$C$219,Countries_WB!$E$2:$E$219,"No Data",0) -> Upper middle income
A32: Bermuda | B32: BMU | C32: Price level ratio of PPP conversion factor (GDP) to market exchange rate | D32: PA.NUS.PPPC.RF | AI32: 0.87348347 | AJ32: 0.89924336 | AK32: 0.90394686 | AL32: 0.92890059 | AM32: 0.92730122 | AN32: 0.94620714 | AO32: 1.2020489 | AP32: 1.2292211 | AQ32: 1.2488644 | AR32: 1.26491 | AS32: 1.1844887 | AT32: 1.1425301 | AU32: 1.2215264 | AV32: 1.2317221 | AW32: 1.2558053 | AX32: 1.299963 | AY32: 1.3288615 | AZ32: 1.3789658 | BA32: 1.4221403 | BB32: 1.4278297 | BC32: 1.4424243 | BD32: 1.3967968 | BE32: 1.4592482 | BF32: 1.4417595 | BG32: 1.4317273 | BH32: 1.4192437 | BI32: 1.3997251 | BJ32: 1.3664159 | BK32: 1.3558353 | BL32: 1.3641656 | BM32: 1.3410046 | BN32: 1.289223 | BO32: 1.2389309 | BP32: =_xlfn.XLOOKUP(B32,Countries_WB!$C$2:$C$219,Countries_WB!$D$2:$D$219,"No Data",0) -> North America | BQ32: =_xlfn.XLOOKUP(B32,Countries_WB!$C$2:$C$219,Countries_WB!$E$2:$E$219,"No Data",0) -> High income
A33: Bolivia | B33: BOL | C33: Price level ratio of PPP conversion factor (GDP) to market exchange rate | D33: PA.NUS.PPPC.RF | AI33: 0.29892102 | AJ33: 0.30151951 | AK33: 0.30634254 | AL33: 0.29161541 | AM33: 0.28451327 | AN33: 0.29888209 | AO33: 0.30979651 | AP33: 0.31091266 | AQ33: 0.31384711 | AR33: 0.30046621 | AS33: 0.29052388 | AT33: 0.27088886 | AU33: 0.25271745 | AV33: 0.24668394 | AW33: 0.25032841 | AX33: 0.25299034 | AY33: 0.28084656 | AZ33: 0.29961679 | BA33: 0.35197455 | BB33: 0.3518832 | BC33: 0.37840397 | BD33: 0.42971433 | BE33: 0.44073544 | BF33: 0.4389865 | BG33: 0.43672294 | BH33: 0.4255713 | BI33: 0.41023329 | BJ33: 0.39782107 | BK33: 0.40035477 | BL33: 0.39057368 | BM33: 0.37839323 | BN33: 0.37644982 | BO33: 0.36971056 | BP33: =_xlfn.XLOOKUP(B33,Countries_WB!$C$2:$C$219,Countries_WB!$D$2:$D$219,"No Data",0) -> Latin America & Caribbean | BQ33: =_xlfn.XLOOKUP(B33,Countries_WB!$C$2:$C$219,Countries_WB!$E$2:$E$219,"No Data",0) -> Lower middle income
A34: Brazil | B34: BRA | C34: Price level ratio of PPP conversion factor (GDP) to market exchange rate | D34: PA.NUS.PPPC.RF | AI34: 0.46317135 | AJ34: 0.39101741 | AK34: 0.36859218 | AL34: 0.38507596 | AM34: 0.44388355 | AN34: 0.58752812 | AO34: 0.62399712 | AP34: 0.6161462 | AQ34: 0.59383162 | AR34: 0.40465235 | AS34: 0.4143322 | AT34: 0.34144054 | AU34: 0.29700008 | AV34: 0.31532803 | AW34: 0.34812456 | AX34: 0.43572154 | AY34: 0.50506041 | AZ34: 0.58480194 | BA34: 0.66272936 | BB34: 0.64811807 | BC34: 0.78917368 | BD34: 0.88067365 | BE34: 0.82214424 | BF34: 0.78905662 | BG34: 0.77060691 | BH34: 0.59779727 | BI34: 0.61096833 | BJ34: 0.683576 | BK34: 0.60924372 | BL34: 0.57782585 | BM34: 0.4646746 | BN34: 0.47335413 | BO34: 0.5002162 | BP34: =_xlfn.XLOOKUP(B34,Countries_WB!$C$2:$C$219,Countries_WB!$D$2:$D$219,"No Data",0) -> Latin America & Caribbean | BQ34: =_xlfn.XLOOKUP(B34,Countries_WB!$C$2:$C$219,Countries_WB!$E$2:$E$219,"No Data",0) -> Upper middle income
A35: Barbados | B35: BRB | C35: Price level ratio of PPP conversion factor (GDP) to market exchange rate | D35: PA.NUS.PPPC.RF | AI35: 0.80562934 | AJ35: 0.81430675 | AK35: 0.81765441 | AL35: 0.83549796 | AM35: 0.83610673 | AN35: 0.82725608 | AO35: 0.83300326 | AP35: 0.82639052 | AQ35: 0.88831513 | AR35: 0.91480615 | AS35: 0.88769389 | AT35: 0.88771504 | AU35: 0.88202754 | AV35: 0.87460858 | AW35: 0.90138517 | AX35: 0.93225323 | AY35: 0.94164465 | AZ35: 0.99542274 | BA35: 0.99345542 | BB35: 0.97001342 | BC35: 0.99519849 | BD35: 1.0094435 | BE35: 1.0613686 | BF35: 1.0728049 | BG35: 1.0865591 | BH35: 1.0653898 | BI35: 1.0594341 | BJ35: 1.1015025 | BK35: 1.1107395 | BL35: 1.1374586 | BM35: 1.1416095 | BN35: 1.1439702 | BO35: 1.1114023 | BP35: =_xlfn.XLOOKUP(B35,Countries_WB!$C$2:$C$219,Countries_WB!$D$2:$D$219,"No Data",0) -> Latin America & Caribbean | BQ35: =_xlfn.XLOOKUP(B35,Countries_WB!$C$2:$C$219,Countries_WB!$E$2:$E$219,"No Data",0) -> High income
A36: Brunei Darussalam | B36: BRN | C36: Price level ratio of PPP conversion factor (GDP) to market exchange rate | D36: PA.NUS.PPPC.RF | AI36: 0.24363051 | AJ36: 0.24023856 | AK36: 0.25340236 | AL36: 0.24218793 | AM36: 0.22885689 | AN36: 0.24850399 | AO36: 0.25631621 | AP36: 0.25982569 | AQ36: 0.2013967 | AR36: 0.21883113 | AS36: 0.27142703 | AT36: 0.24112575 | AU36: 0.23846492 | AV36: 0.25501922 | AW36: 0.29665282 | AX36: 0.34691302 | AY36: 0.38793152 | AZ36: 0.40269465 | BA36: 0.47352484 | BB36: 0.35714126 | BC36: 0.43929413 | BD36: 0.56061652 | BE36: 0.54099722 | BF36: 0.53398819 | BG36: 0.51276784 | BH36: 0.4982967 | BI36: 0.48239466 | BJ36: 0.46843207 | BK36: 0.51143294 | BL36: 0.48022141 | BM36: 0.41779555 | BN36: 0.47400185 | BO36: 0.53612677 | BP36: =_xlfn.XLOOKUP(B36,Countries_WB!$C$2:$C$219,Countries_WB!$D$2:$D$219,"No Data",0) -> East Asia & Pacific | BQ36: =_xlfn.XLOOKUP(B36,Countries_WB!$C$2:$C$219,Countries_WB!$E$2:$E$219,"No Data",0) -> High income
A37: Bhutan | B37: BTN | C37: Price level ratio of PPP conversion factor (GDP) to market exchange rate | D37: PA.NUS.PPPC.RF | AI37: 0.3480108 | AJ37: 0.28224695 | AK37: 0.26375334 | AL37: 0.23763257 | AM37: 0.25404276 | AN37: 0.26068654 | AO37: 0.25328703 | AP37: 0.27431689 | AQ37: 0.26428208 | AR37: 0.26514762 | AS37: 0.26664936 | AT37: 0.26167788 | AU37: 0.26200814 | AV37: 0.27633853 | AW37: 0.28688673 | AX37: 0.30270944 | AY37: 0.30131686 | AZ37: 0.33096986 | BA37: 0.32565107 | BB37: 0.30465354 | BC37: 0.33733218 | BD37: 0.35133149 | BE37: 0.32089251 | BF37: 0.30948924 | BG37: 0.30603342 | BH37: 0.2897305 | BI37: 0.28024346 | BJ37: 0.29496125 | BK37: 0.27742974 | BL37: 0.27290695 | BM37: 0.26955216 | BN37: 0.27824149 | BO37: =BN37 -> 0.27824149 | BP37: =_xlfn.XLOOKUP(B37,Countries_WB!$C$2:$C$219,Countries_WB!$D$2:$D$219,"No Data",0) -> South Asia | BQ37: =_xlfn.XLOOKUP(B37,Countries_WB!$C$2:$C$219,Countries_WB!$E$2:$E$219,"No Data",0) -> Lower middle income
A38: Botswana | B38: BWA | C38: Price level ratio of PPP conversion factor (GDP) to market exchange rate | D38: PA.NUS.PPPC.RF | AI38: 0.46543655 | AJ38: 0.43578875 | AK38: 0.4353788 | AL38: 0.41867705 | AM38: 0.40499839 | AN38: 0.41163811 | AO38: 0.3914285 | AP38: 0.36785846 | AQ38: 0.34558099 | AR38: 0.35574153 | AS38: 0.35999162 | AT38: 0.33305639 | AU38: 0.30632155 | AV38: 0.39652798 | AW38: 0.44836128 | AX38: 0.46041079 | AY38: 0.4212564 | AZ38: 0.41304586 | BA38: 0.39858352 | BB38: 0.43496693 | BC38: 0.48745229 | BD38: 0.5344448 | BE38: 0.51878462 | BF38: 0.49123639 | BG38: 0.47731617 | BH38: 0.43737079 | BI38: 0.4196854 | BJ38: 0.45749095 | BK38: 0.45346785 | BL38: 0.42459723 | BM38: 0.41073622 | BN38: 0.44007143 | BO38: 0.4222009 | BP38: =_xlfn.XLOOKUP(B38,Countries_WB!$C$2:$C$219,Countries_WB!$D$2:$D$219,"No Data",0) -> Sub-Saharan Africa | BQ38: =_xlfn.XLOOKUP(B38,Countries_WB!$C$2:$C$219,Countries_WB!$E$2:$E$219,"No Data",0) -> Upper middle income
A39: Central African Republic | B39: CAF | C39: Price level ratio of PPP conversion factor (GDP) to market exchange rate | D39: PA.NUS.PPPC.RF | AI39: 0.80868688 | AJ39: 0.75200022 | AK39: 0.80542463 | AL39: 0.71020551 | AM39: 0.44121943 | AN39: 0.52826908 | AO39: 0.48825693 | AP39: 0.42413846 | AQ39: 0.41323285 | AR39: 0.40639869 | AS39: 0.37381961 | AT39: 0.35601697 | AU39: 0.36132349 | AV39: 0.42953919 | AW39: 0.43957956 | AX39: 0.44413305 | AY39: 0.44932191 | AZ39: 0.48630474 | BA39: 0.54830571 | BB39: 0.52034769 | BC39: 0.50928928 | BD39: 0.54485327 | BE39: 0.51341836 | BF39: 0.51497742 | BG39: 0.5892474 | BH39: 0.47956382 | BI39: 0.47257026 | BJ39: 0.4939737 | BK39: 0.49809806 | BL39: 0.47467603 | BM39: 0.48642114 | BN39: 0.49857507 | BO39: 0.43879757 | BP39: =_xlfn.XLOOKUP(B39,Countries_WB!$C$2:$C$219,Countries_WB!$D$2:$D$219,"No Data",0) -> Sub-Saharan Africa | BQ39: =_xlfn.XLOOKUP(B39,Countries_WB!$C$2:$C$219,Countries_WB!$E$2:$E$219,"No Data",0) -> Low income
A40: Canada | B40: CAN | C40: Price level ratio of PPP conversion factor (GDP) to market exchange rate | D40: PA.NUS.PPPC.RF | AI40: 1.0640692 | AJ40: 1.0802042 | AK40: 1.0157144 | AL40: 0.94154639 | AM40: 0.88356693 | AN40: 0.88052244 | AO40: 0.88552255 | AP40: 0.86708436 | AQ40: 0.79881631 | AR40: 0.80151444 | AS40: 0.82661033 | AT40: 0.7880062 | AU40: 0.78336392 | AV40: 0.87482264 | AW40: 0.94747271 | AX40: 1.0015217 | AY40: 1.0625573 | AZ40: 1.1284787 | BA40: 1.1568791 | BB40: 1.05174 | BC40: 1.1861032 | BD40: 1.2533675 | BE40: 1.2453981 | BF40: 1.1881911 | BG40: 1.113701 | BH40: 0.97595829 | BI40: 0.91055461 | BJ40: 0.93402459 | BK40: 0.93110755 | BL40: 0.93060233 | BM40: 0.91791265 | BN40: 0.98746216 | BO40: 0.94121433 | BP40: =_xlfn.XLOOKUP(B40,Countries_WB!$C$2:$C$219,Countries_WB!$D$2:$D$219,"No Data",0) -> North America | BQ40: =_xlfn.XLOOKUP(B40,Countries_WB!$C$2:$C$219,Countries_WB!$E$2:$E$219,"No Data",0) -> High income
A41: Central Europe and the Baltics | B41: CEB | C41: Price level ratio of PPP conversion factor (GDP) to market exchange rate | D41: PA.NUS.PPPC.RF | BO41: =BN41 -> 0 | BP41: =_xlfn.XLOOKUP(B41,Countries_WB!$C$2:$C$219,Countries_WB!$D$2:$D$219,"No Data",0) -> No Data | BQ41: =_xlfn.XLOOKUP(B41,Countries_WB!$C$2:$C$219,Countries_WB!$E$2:$E$219,"No Data",0) -> No Data
A42: Switzerland | B42: CHE | C42: Price level ratio of PPP conversion factor (GDP) to market exchange rate | D42: PA.NUS.PPPC.RF | AI42: 1.3904038 | AJ42: 1.3733808 | AK42: 1.3984191 | AL42: 1.3302172 | AM42: 1.4237238 | AN42: 1.6247822 | AO42: 1.5263261 | AP42: 1.2703748 | AQ42: 1.2605511 | AR42: 1.2001305 | AS42: 1.0590609 | AT42: 1.048118 | AU42: 1.0969845 | AV42: 1.2736036 | AW42: 1.3605123 | AX42: 1.3544394 | AY42: 1.2752839 | AZ42: 1.2761896 | BA42: 1.378496 | BB42: 1.351022 | BC42: 1.4058194 | BD42: 1.5736845 | BE42: 1.4440593 | BF42: 1.4159801 | BG42: 1.3990717 | BH42: 1.2840939 | BI42: 1.2197796 | BJ42: 1.2061908 | BK42: 1.2055283 | BL42: 1.1576081 | BM42: 1.2096502 | BN42: 1.2107381 | BO42: 1.1017126 | BP42: =_xlfn.XLOOKUP(B42,Countries_WB!$C$2:$C$219,Countries_WB!$D$2:$D$219,"No Data",0) -> Europe & Central Asia | BQ42: =_xlfn.XLOOKUP(B42,Countries_WB!$C$2:$C$219,Countries_WB!$E$2:$E$219,"No Data",0) -> High income
A43: Channel Islands | B43: CHI | C43: Price level ratio of PPP conversion factor (GDP) to market exchange rate | D43: PA.NUS.PPPC.RF | BO43: =BN43 -> 0 | BP43: =_xlfn.XLOOKUP(B43,Countries_WB!$C$2:$C$219,Countries_WB!$D$2:$D$219,"No Data",0) -> Europe & Central Asia | BQ43: =_xlfn.XLOOKUP(B43,Countries_WB!$C$2:$C$219,Countries_WB!$E$2:$E$219,"No Data",0) -> High income
A44: Chile | B44: CHL | C44: Price level ratio of PPP conversion factor (GDP) to market exchange rate | D44: PA.NUS.PPPC.RF | AI44: 0.55973175 | AJ44: 0.57277019 | AK44: 0.60249003 | AL44: 0.58421749 | AM44: 0.61956146 | AN44: 0.70265663 | AO44: 0.6755173 | AP44: 0.67467796 | AQ44: 0.6123755 | AR44: 0.558173 | AS44: 0.53895194 | AT44: 0.46683749 | AU44: 0.43725163 | AV44: 0.44574477 | AW44: 0.52707376 | AX44: 0.59602105 | AY44: 0.6007862 | AZ44: 0.6196379 | BA44: 0.65237187 | BB44: 0.6331009 | BC44: 0.7050421 | BD44: 0.7199891 | BE44: 0.71336613 | BF44: 0.70643223 | BG44: 0.64422825 | BH44: 0.59790517 | BI44: 0.58692623 | BJ44: 0.6124623 | BK44: 0.6188273 | BL44: 0.57158516 | BM44: 0.52819296 | BN44: 0.57312227 | BO44: 0.50831138 | BP44: =_xlfn.XLOOKUP(B44,Countries_WB!$C$2:$C$219,Countries_WB!$D$2:$D$219,"No Data",0) -> Latin America & Caribbean | BQ44: =_xlfn.XLOOKUP(B44,Countries_WB!$C$2:$C$219,Countries_WB!$E$2:$E$219,"No Data",0) -> High income
A45: China | B45: CHN | C45: Price level ratio of PPP conversion factor (GDP) to market exchange rate | D45: PA.NUS.PPPC.RF | AI45: 0.35415892 | AJ45: 0.32847875 | AK45: 0.33541671 | AL45: 0.36120229 | AM45: 0.2851753 | AN45: 0.32765177 | AO45: 0.34423158 | AP45: 0.34487696 | AQ45: 0.33841155 | AR45: 0.32952405 | AS45: 0.32885865 | AT45: 0.32825338 | AU45: 0.32516639 | AV45: 0.32717079 | AW45: 0.34077779 | AX45: 0.34677093 | AY45: 0.35928444 | AZ45: 0.39507098 | BA45: 0.45747521 | BB45: 0.46139394 | BC45: 0.49168907 | BD45: 0.54545987 | BE45: 0.56412865 | BF45: 0.59131502 | BG45: 0.61184833 | BH45: 0.62155024 | BI45: 0.60032364 | BJ45: 0.61902099 | BK45: 0.63914813 | BL45: 0.60904335 | BM45: 0.60482606 | BN45: 0.64756674 | BO45: 0.59211821 | BP45: =_xlfn.XLOOKUP(B45,Countries_WB!$C$2:$C$219,Countries_WB!$D$2:$D$219,"No Data",0) -> East Asia & Pacific | BQ45: =_xlfn.XLOOKUP(B45,Countries_WB!$C$2:$C$219,Countries_WB!$E$2:$E$219,"No Data",0) -> Upper middle income
A46: Cote d'Ivoire | B46: CIV | C46: Price level ratio of PPP conversion factor (GDP) to market exchange rate | D46: PA.NUS.PPPC.RF | AI46: 0.48913781 | AJ46: 0.45966035 | AK46: 0.47887333 | AL46: 0.46418199 | AM46: 0.33930821 | AN46: 0.4104871 | AO46: 0.41293199 | AP46: 0.36972754 | AQ46: 0.38120615 | AR46: 0.35739421 | AS46: 0.30782167 | AT46: 0.31199094 | AU46: 0.3391955 | AV46: 0.4109599 | AW46: 0.42908832 | AX46: 0.42151963 | AY46: 0.4182958 | AZ46: 0.45828325 | BA46: 0.50848816 | BB46: 0.48493774 | BC46: 0.46235703 | BD46: 0.50272949 | BE46: 0.47343527 | BF46: 0.5005908 | BG46: 0.49927225 | BH46: 0.42393993 | BI46: 0.42593391 | BJ46: 0.4369976 | BK46: 0.45361054 | BL46: 0.42818375 | BM46: 0.43684165 | BN46: 0.44547529 | BO46: 0.38015847 | BP46: =_xlfn.XLOOKUP(B46,Countries_WB!$C$2:$C$219,Countries_WB!$D$2:$D$219,"No Data",0) -> Sub-Saharan Africa | BQ46: =_xlfn.XLOOKUP(B46,Countries_WB!$C$2:$C$219,Countries_WB!$E$2:$E$219,"No Data",0) -> Lower middle income
A47: Cameroon | B47: CMR | C47: Price level ratio of PPP conversion factor (GDP) to market exchange rate | D47: PA.NUS.PPPC.RF | AI47: 0.60416296 | AJ47: 0.5841394 | AK47: 0.60092329 | AL47: 0.7671096 | AM47: 0.41990258 | AN47: 0.48030697 | AO47: 0.4621234 | AP47: 0.42270018 | AQ47: 0.41795211 | AR47: 0.39063016 | AS47: 0.33609434 | AT47: 0.32660132 | AU47: 0.34894249 | AV47: 0.41734436 | AW47: 0.44756643 | AX47: 0.43991415 | AY47: 0.44059875 | AZ47: 0.47055373 | BA47: 0.51996042 | BB47: 0.50761684 | BC47: 0.48003244 | BD47: 0.50654169 | BE47: 0.47437263 | BF47: 0.48812146 | BG47: 0.48428514 | BH47: 0.40714395 | BI47: 0.40067753 | BJ47: 0.40092773 | BK47: 0.41704946 | BL47: 0.39294068 | BM47: 0.39762293 | BN47: 0.40634618 | BO47: 0.35549603 | BP47: =_xlfn.XLOOKUP(B47,Countries_WB!$C$2:$C$219,Countries_WB!$D$2:$D$219,"No Data",0) -> Sub-Saharan Africa | BQ47: =_xlfn.XLOOKUP(B47,Countries_WB!$C$2:$C$219,Countries_WB!$E$2:$E$219,"No Data",0) -> Lower middle income
A48: Congo, Dem. Rep. | B48: COD | C48: Price level ratio of PPP conversion factor (GDP) to market exchange rate | D48: PA.NUS.PPPC.RF | AI48: 0.30566917 | AK48: 0.33457765 | AL48: 0.45956092 | AM48: 0.25308518 | AN48: 0.23867577 | AO48: 0.24218 | AP48: 0.26620186 | AQ48: 0.27316298 | AR48: 0.21320471 | AS48: 0.90738834 | AT48: 0.35321663 | AU48: 0.39642155 | AV48: 0.37705045 | AW48: 0.39635667 | AX48: 0.42070751 | AY48: 0.46805669 | AZ48: 0.4967114 | BA48: 0.54244644 | BB48: 0.4938376 | BC48: 0.52686238 | BD48: 0.57864976 | BE48: 0.6341413 | BF48: 0.60779397 | BG48: 0.57285191 | BH48: 0.54924814 | BI48: 0.48908776 | BJ48: 0.44071474 | BK48: 0.50883988 | BL48: 0.52123477 | BM48: 0.47586505 | BN48: 0.48701338 | BO48: 0.48859287 | BP48: =_xlfn.XLOOKUP(B48,Countries_WB!$C$2:$C$219,Countries_WB!$D$2:$D$219,"No Data",0) -> Sub-Saharan Africa | BQ48: =_xlfn.XLOOKUP(B48,Countries_WB!$C$2:$C$219,Countries_WB!$E$2:$E$219,"No Data",0) -> Low income
A49: Congo, Rep. | B49: COG | C49: Price level ratio of PPP conversion factor (GDP) to market exchange rate | D49: PA.NUS.PPPC.RF | AI49: 0.37361269 | AJ49: 0.3436189 | AK49: 0.35244788 | AL49: 0.31818982 | AM49: 0.21728459 | AN49: 0.24476157 | AO49: 0.27672933 | AP49: 0.25026245 | AQ49: 0.20022637 | AR49: 0.24481352 | AS49: 0.30504611 | AT49: 0.24900278 | AU49: 0.25435266 | AV49: 0.28569927 | AW49: 0.35738513 | AX49: 0.42049318 | AY49: 0.4585307 | AZ49: 0.52015904 | BA49: 0.63682284 | BB49: 0.47307246 | BC49: 0.57501257 | BD49: 0.65623786 | BE49: 0.61916059 | BF49: 0.6401137 | BG49: 0.637567 | BH49: 0.52772966 | BI49: 0.53428946 | BJ49: 0.51264764 | BK49: 0.63969407 | BL49: 0.58790236 | BM49: 0.50803434 | BN49: 0.62219326 | BO49: 0.61111682 | BP49: =_xlfn.XLOOKUP(B49,Countries_WB!$C$2:$C$219,Countries_WB!$D$2:$D$219,"No Data",0) -> Sub-Saharan Africa | BQ49: =_xlfn.XLOOKUP(B49,Countries_WB!$C$2:$C$219,Countries_WB!$E$2:$E$219,"No Data",0) -> Lower middle income
A50: Colombia | B50: COL | C50: Price level ratio of PPP conversion factor (GDP) to market exchange rate | D50: PA.NUS.PPPC.RF | AI50: 0.34717136 | AJ50: 0.34156933 | AK50: 0.37759754 | AL50: 0.39843316 | AM50: 0.45313962 | AN50: 0.47760098 | AO50: 0.48270584 | AP50: 0.50366163 | AQ50: 0.457298 | AR50: 0.41238538 | AS50: 0.37711757 | AT50: 0.35664123 | AU50: 0.34170077 | AV50: 0.31158601 | AW50: 0.35640201 | AX50: 0.40990605 | AY50: 0.41404733 | AZ50: 0.48143789 | BA50: 0.53780798 | BB50: 0.50649632 | BC50: 0.59027173 | BD50: 0.63216045 | BE50: 0.66939788 | BF50: 0.64566446 | BG50: 0.60996664 | BH50: 0.46556565 | BI50: 0.42488846 | BJ50: 0.44994834 | BK50: 0.44732509 | BL50: 0.40551814 | BM50: 0.35120593 | BN50: 0.36145608 | BO50: 0.32681776 | BP50: =_xlfn.XLOOKUP(B50,Countries_WB!$C$2:$C$219,Countries_WB!$D$2:$D$219,"No Data",0) -> Latin America & Caribbean | BQ50: =_xlfn.XLOOKUP(B50,Countries_WB!$C$2:$C$219,Countries_WB!$E$2:$E$219,"No Data",0) -> Upper middle income
A51: Comoros | B51: COM | C51: Price level ratio of PPP conversion factor (GDP) to market exchange rate | D51: PA.NUS.PPPC.RF | AI51: 0.60823045 | AJ51: 0.61390847 | AK51: 0.59644711 | AL51: 0.56005952 | AM51: 0.4080045 | AN51: 0.48149123 | AO51: 0.47612643 | AP51: 0.41401522 | AQ51: 0.41050201 | AR51: 0.41040526 | AS51: 0.35983086 | AT51: 0.37068997 | AU51: 0.40142722 | AV51: 0.49499346 | AW51: 0.54806074 | AX51: 0.5331562 | AY51: 0.53821964 | AZ51: 0.59228182 | BA51: 0.64326715 | BB51: 0.61213043 | BC51: 0.58454083 | BD51: 0.61956703 | BE51: 0.55877248 | BF51: 0.5709663 | BG51: 0.55720519 | BH51: 0.45859273 | BI51: 0.44452398 | BJ51: 0.43657669 | BK51: 0.4538586 | BL51: 0.44043862 | BM51: 0.44656018 | BN51: 0.4427933 | BO51: 0.38732231 | BP51: =_xlfn.XLOOKUP(B51,Countries_WB!$C$2:$C$219,Countries_WB!$D$2:$D$219,"No Data",0) -> Sub-Saharan Africa | BQ51: =_xlfn.XLOOKUP(B51,Countries_WB!$C$2:$C$219,Countries_WB!$E$2:$E$219,"No Data",0) -> Lower middle income
A52: Cabo Verde | B52: CPV | C52: Price level ratio of PPP conversion factor (GDP) to market exchange rate | D52: PA.NUS.PPPC.RF | AI52: 0.8025264 | AJ52: 0.79779404 | AK52: 0.78518963 | AL52: 0.968812 | AM52: 0.65982832 | AN52: 0.67798977 | AO52: 0.65526758 | AP52: 0.56657415 | AQ52: 0.52970926 | AR52: 0.53308694 | AS52: 0.44537205 | AT52: 0.44490578 | AU52: 0.45866396 | AV52: 0.5658754 | AW52: 0.56876146 | AX52: 0.54219183 | AY52: 0.55487372 | AZ52: 0.59731619 | BA52: 0.650428 | BB52: 0.62022817 | BC52: 0.5928495 | BD52: 0.62685944 | BE52: 0.59246303 | BF52: 0.6242164 | BG52: 0.6243155 | BH52: 0.50764513 | BI52: 0.49518585 | BJ52: 0.49564098 | BK52: 0.5154048 | BL52: 0.48353617 | BM52: 0.48746617 | BN52: 0.48445543 | BO52: 0.43073734 | BP52: =_xlfn.XLOOKUP(B52,Countries_WB!$C$2:$C$219,Countries_WB!$D$2:$D$219,"No Data",0) -> Sub-Saharan Africa | BQ52: =_xlfn.XLOOKUP(B52,Countries_WB!$C$2:$C$219,Countries_WB!$E$2:$E$219,"No Data",0) -> Lower middle income
A53: Costa Rica | B53: CRI | C53: Price level ratio of PPP conversion factor (GDP) to market exchange rate | D53: PA.NUS.PPPC.RF | AI53: 0.36446309 | AJ53: 0.43433335 | AK53: 0.46278687 | AL53: 0.47233001 | AM53: 0.48419545 | AN53: 0.5027427 | AO53: 0.49132471 | AP53: 0.49462756 | AQ53: 0.49516668 | AR53: 0.48807485 | AS53: 0.48394372 | AT53: 0.48663439 | AU53: 0.48081257 | AV53: 0.47088538 | AW53: 0.47318561 | AX53: 0.47515738 | AY53: 0.48679177 | AZ53: 0.51838954 | BA53: 0.55637902 | BB53: 0.5566924 | BC53: 0.63948398 | BD53: 0.68137312 | BE53: 0.70348724 | BF53: 0.71599014 | BG53: 0.67510714 | BH53: 0.6812309 | BI53: 0.62968391 | BJ53: 0.60085289 | BK53: 0.58564652 | BL53: 0.56038619 | BM53: 0.56141976 | BN53: 0.55368028 | BO53: 0.52959123 | BP53: =_xlfn.XLOOKUP(B53,Countries_WB!$C$2:$C$219,Countries_WB!$D$2:$D$219,"No Data",0) -> Latin America & Caribbean | BQ53: =_xlfn.XLOOKUP(B53,Countries_WB!$C$2:$C$219,Countries_WB!$E$2:$E$219,"No Data",0) -> Upper middle income
A54: Caribbean small states | B54: CSS | C54: Price level ratio of PPP conversion factor (GDP) to market exchange rate | D54: PA.NUS.PPPC.RF | BO54: =BN54 -> 0 | BP54: =_xlfn.XLOOKUP(B54,Countries_WB!$C$2:$C$219,Countries_WB!$D$2:$D$219,"No Data",0) -> No Data | BQ54: =_xlfn.XLOOKUP(B54,Countries_WB!$C$2:$C$219,Countries_WB!$E$2:$E$219,"No Data",0) -> No Data
A55: Cuba | B55: CUB | C55: Price level ratio of PPP conversion factor (GDP) to market exchange rate | D55: PA.NUS.PPPC.RF | BO55: =BN55 -> 0 | BP55: =_xlfn.XLOOKUP(B55,Countries_WB!$C$2:$C$219,Countries_WB!$D$2:$D$219,"No Data",0) -> Latin America & Caribbean | BQ55: =_xlfn.XLOOKUP(B55,Countries_WB!$C$2:$C$219,Countries_WB!$E$2:$E$219,"No Data",0) -> Upper middle income
A56: Curacao | B56: CUW | C56: Price level ratio of PPP conversion factor (GDP) to market exchange rate | D56: PA.NUS.PPPC.RF | BD56: 0.74001211 | BE56: 0.78651419 | BF56: 0.78942143 | BG56: 0.79821002 | BH56: 0.79518383 | BI56: 0.78825571 | BJ56: 0.76377458 | BK56: 0.76512263 | BL56: 0.77137604 | BM56: 0.77803931 | BN56: 0.77257187 | BO56: 0.75091894 | BP56: =_xlfn.XLOOKUP(B56,Countries_WB!$C$2:$C$219,Countries_WB!$D$2:$D$219,"No Data",0) -> Latin America & Caribbean | BQ56: =_xlfn.XLOOKUP(B56,Countries_WB!$C$2:$C$219,Countries_WB!$E$2:$E$219,"No Data",0) -> High income
A57: Cayman Islands | B57: CYM | C57: Price level ratio of PPP conversion factor (GDP) to market exchange rate | D57: PA.NUS.PPPC.RF | AY57: 1.1583042 | AZ57: 1.1624808 | BA57: 1.1753673 | BB57: 1.1750101 | BC57: 1.1586602 | BD57: 1.12985 | BE57: 1.1589057 | BF57: 1.1773224 | BG57: 1.1890091 | BH57: 1.1875642 | BI57: 1.177511 | BJ57: 1.1685537 | BK57: 1.1715062 | BL57: 1.1899474 | BM57: 1.176463 | BN57: 1.1553245 | BO57: 1.1820756 | BP57: =_xlfn.XLOOKUP(B57,Countries_WB!$C$2:$C$219,Countries_WB!$D$2:$D$219,"No Data",0) -> Latin America & Caribbean | BQ57: =_xlfn.XLOOKUP(B57,Countries_WB!$C$2:$C$219,Countries_WB!$E$2:$E$219,"No Data",0) -> High income
A58: Cyprus | B58: CYP | C58: Price level ratio of PPP conversion factor (GDP) to market exchange rate | D58: PA.NUS.PPPC.RF | AI58: 0.72226785 | AJ58: 0.71572407 | AK58: 0.76623984 | AL58: 0.70868383 | AM58: 0.73826658 | AN58: 0.89262776 | AO58: 0.87409091 | AP58: 0.80053389 | AQ58: 0.80454031 | AR58: 0.77751097 | AS58: 0.67578173 | AT58: 0.64820108 | AU58: 0.68317777 | AV58: 0.83408291 | AW58: 0.9170394 | AX58: 0.89900663 | AY58: 0.89065031 | AZ58: 0.95012401 | BA58: 1.0162872 | BB58: 0.94755015 | BC58: 0.92819929 | BD58: 0.97245195 | BE58: 0.90816418 | BF58: 0.91284349 | BG58: 0.90299463 | BH58: 0.7357605 | BI58: 0.688864 | BJ58: 0.69495682 | BK58: 0.72325938 | BL58: 0.66799997 | BM58: 0.67765031 | BN58: 0.71016645 | BO58: 0.62444571 | BP58: =_xlfn.XLOOKUP(B58,Countries_WB!$C$2:$C$219,Countries_WB!$D$2:$D$219,"No Data",0) -> Europe & Central Asia | BQ58: =_xlfn.XLOOKUP(B58,Countries_WB!$C$2:$C$219,Countries_WB!$E$2:$E$219,"No Data",0) -> High income
A59: Czechia | B59: CZE | C59: Price level ratio of PPP conversion factor (GDP) to market exchange rate | D59: PA.NUS.PPPC.RF | AI59: 0.30973988 | AJ59: 0.24851912 | AK59: 0.28466385 | AL59: 0.32630045 | AM59: 0.36349658 | AN59: 0.42020991 | AO59: 0.44472102 | AP59: 0.40705842 | AQ59: 0.43328036 | AR59: 0.4116193 | AS59: 0.37127792 | AT59: 0.37658176 | AU59: 0.44162918 | AV59: 0.50250984 | AW59: 0.56132915 | AX59: 0.60784947 | AY59: 0.63797748 | AZ59: 0.70253207 | BA59: 0.81519198 | BB59: 0.71543272 | BC59: 0.71591392 | BD59: 0.75414601 | BE59: 0.67923376 | BF59: 0.65329024 | BG59: 0.61198169 | BH59: 0.52596087 | BI59: 0.51458207 | BJ59: 0.53151988 | BK59: 0.56933159 | BL59: 0.53524944 | BM59: 0.53687737 | BN59: 0.58782582 | BO59: 0.55337064 | BP59: =_xlfn.XLOOKUP(B59,Countries_WB!$C$2:$C$219,Countries_WB!$D$2:$D$219,"No Data",0) -> Europe & Central Asia | BQ59: =_xlfn.XLOOKUP(B59,Countries_WB!$C$2:$C$219,Countries_WB!$E$2:$E$219,"No Data",0) -> High income
A60: Germany | B60: DEU | C60: Price level ratio of PPP conversion factor (GDP) to market exchange rate | D60: PA.NUS.PPPC.RF | AI60: 1.1459303 | AJ60: 1.1124761 | AK60: 1.2171259 | AL60: 1.1667361 | AM60: 1.187698 | AN60: 1.3434107 | AO60: 1.2661009 | AP60: 1.0973201 | AQ60: 1.0766756 | AR60: 1.0168776 | AS60: 0.87099342 | AT60: 0.83274648 | AU60: 0.86355182 | AV60: 1.0133964 | AW60: 1.0884867 | AX60: 1.0857437 | AY60: 1.064282 | AZ60: 1.1473601 | BA60: 1.2066093 | BB60: 1.1313052 | BC60: 1.0673093 | BD60: 1.0978894 | BE60: 1.0114447 | BF60: 1.0290046 | BG60: 1.0215334 | BH60: 0.86333639 | BI60: 0.83306414 | BJ60: 0.84136734 | BK60: 0.86853063 | BL60: 0.81525619 | BM60: 0.82809446 | BN60: 0.87082449 | BO60: 0.76694796 | BP60: =_xlfn.XLOOKUP(B60,Countries_WB!$C$2:$C$219,Countries_WB!$D$2:$D$219,"No Data",0) -> Europe & Central Asia | BQ60: =_xlfn.XLOOKUP(B60,Countries_WB!$C$2:$C$219,Countries_WB!$E$2:$E$219,"No Data",0) -> High income
A61: Djibouti | B61: DJI | C61: Price level ratio of PPP conversion factor (GDP) to market exchange rate | D61: PA.NUS.PPPC.RF | BD61: 0.52650966 | BE61: 0.55294305 | BF61: 0.56353657 | BG61: 0.57455706 | BH61: 0.58126099 | BI61: 0.59715204 | BJ61: 0.59656825 | BK61: 0.5863848 | BL61: 0.57864191 | BM61: 0.58134304 | BN61: 0.56581115 | BO61: 0.53215441 | BP61: =_xlfn.XLOOKUP(B61,Countries_WB!$C$2:$C$219,Countries_WB!$D$2:$D$219,"No Data",0) -> Middle East & North Africa | BQ61: =_xlfn.XLOOKUP(B61,Countries_WB!$C$2:$C$219,Countries_WB!$E$2:$E$219,"No Data",0) -> Lower middle income
A62: Dominica | B62: DMA | C62: Price level ratio of PPP conversion factor (GDP) to market exchange rate | D62: PA.NUS.PPPC.RF | AI62: 0.65033232 | AJ62: 0.67718664 | AK62: 0.69114345 | AL62: 0.69323213 | AM62: 0.73059058 | AN62: 0.72119519 | AO62: 0.73135103 | AP62: 0.7293411 | AQ62: 0.73954339 | AR62: 0.74776336 | AS62: 0.73557904 | AT62: 0.73436613 | AU62: 0.72881316 | AV62: 0.69241401 | AW62: 0.69988269 | AX62: 0.66877518 | AY62: 0.66411384 | AZ62: 0.65649982 | BA62: 0.65386169 | BB62: 0.70169865 | BC62: 0.69542492 | BD62: 0.69275167 | BE62: 0.6886069 | BF62: 0.691547 | BG62: 0.670752 | BH62: 0.68190932 | BI62: 0.67625805 | BJ62: 0.64353236 | BK62: 0.64554871 | BL62: 0.66260386 | BM62: 0.64665351 | BN62: 0.63757606 | BO62: 0.61676918 | BP62: =_xlfn.XLOOKUP(B62,Countries_WB!$C$2:$C$219,Countries_WB!$D$2:$D$219,"No Data",0) -> Latin America & Caribbean | BQ62: =_xlfn.XLOOKUP(B62,Countries_WB!$C$2:$C$219,Countries_WB!$E$2:$E$219,"No Data",0) -> Upper middle income
A63: Denmark | B63: DNK | C63: Price level ratio of PPP conversion factor (GDP) to market exchange rate | D63: PA.NUS.PPPC.RF | AI63: 1.4739628 | AJ63: 1.4160922 | AK63: 1.4915028 | AL63: 1.3642103 | AM63: 1.3828955 | AN63: 1.5575239 | AO63: 1.5016281 | AP63: 1.317213 | AQ63: 1.2926045 | AR63: 1.254634 | AS63: 1.0725621 | AT63: 1.0444484 | AU63: 1.0844752 | AV63: 1.3126615 | AW63: 1.4120576 | AX63: 1.428978 | AY63: 1.3936309 | AZ63: 1.4992399 | BA63: 1.5582527 | BB63: 1.4421187 | BC63: 1.3497731 | BD63: 1.3907419 | BE63: 1.3058555 | BF63: 1.3095509 | BG63: 1.3057849 | BH63: 1.0858291 | BI63: 1.051716 | BJ63: 1.0407072 | BK63: 1.0714815 | BL63: 0.99469737 | BM63: 1.0013688 | BN63: 1.0481453 | BO63: 0.90511045 | BP63: =_xlfn.XLOOKUP(B63,Countries_WB!$C$2:$C$219,Countries_WB!$D$2:$D$219,"No Data",0) -> Europe & Central Asia | BQ63: =_xlfn.XLOOKUP(B63,Countries_WB!$C$2:$C$219,Countries_WB!$E$2:$E$219,"No Data",0) -> High income
A64: Dominican Republic | B64: DOM | C64: Price level ratio of PPP conversion factor (GDP) to market exchange rate | D64: PA.NUS.PPPC.RF | AI64: 0.35342954 | AJ64: 0.36674826 | AK64: 0.3808423 | AL64: 0.39056486 | AM64: 0.4172603 | AN64: 0.43932162 | AO64: 0.44634068 | AP64: 0.44219859 | AQ64: 0.44363699 | AR64: 0.42179097 | AS64: 0.43269208 | AT64: 0.4350229 | AU64: 0.43450798 | AV64: 0.34064591 | AW64: 0.33731864 | AX64: 0.47903967 | AY64: 0.45066124 | AZ64: 0.46561001 | BA64: 0.48449523 | BB64: 0.47826974 | BC64: 0.48681965 | BD64: 0.49821953 | BE64: 0.51345524 | BF64: 0.49976373 | BG64: 0.49045077 | BH64: 0.46954766 | BI64: 0.45195148 | BJ64: 0.45468744 | BK64: 0.44386503 | BL64: 0.43149968 | BM64: 0.40479113 | BN64: 0.41243169 | BO64: 0.4426779 | BP64: =_xlfn.XLOOKUP(B64,Countries_WB!$C$2:$C$219,Countries_WB!$D$2:$D$219,"No Data",0) -> Latin America & Caribbean | BQ64: =_xlfn.XLOOKUP(B64,Countries_WB!$C$2:$C$219,Countries_WB!$E$2:$E$219,"No Data",0) -> Upper middle income
A65: Algeria | B65: DZA | C65: Price level ratio of PPP conversion factor (GDP) to market exchange rate | D65: PA.NUS.PPPC.RF | AI65: 0.34865568 | AJ65: 0.25149519 | AK65: 0.25362978 | AL65: 0.26331217 | AM65: 0.2215918 | AN65: 0.20526693 | AO65: 0.21764101 | AP65: 0.21719615 | AQ65: 0.20439969 | AR65: 0.19714495 | AS65: 0.20920105 | AT65: 0.19846703 | AU65: 0.19187177 | AV65: 0.20985627 | AW65: 0.24638231 | AX65: 0.27281064 | AY65: 0.29509195 | AZ65: 0.32050043 | BA65: 0.38905939 | BB65: 0.30530822 | BC65: 0.3421262 | BD65: 0.40412315 | BE65: 0.42036269 | BF65: 0.42120475 | BG65: 0.42243658 | BH65: 0.34770416 | BI65: 0.33949913 | BJ65: 0.35013693 | BK65: 0.34742411 | BL65: 0.33183568 | BM65: 0.29288219 | BN65: 0.30404731 | BO65: 0.32832139 | BP65: =_xlfn.XLOOKUP(B65,Countries_WB!$C$2:$C$219,Countries_WB!$D$2:$D$219,"No Data",0) -> Middle East & North Africa | BQ65: =_xlfn.XLOOKUP(B65,Countries_WB!$C$2:$C$219,Countries_WB!$E$2:$E$219,"No Data",0) -> Lower middle income
A66: East Asia & Pacific (excluding high income) | B66: EAP | C66: Price level ratio of PPP conversion factor (GDP) to market exchange rate | D66: PA.NUS.PPPC.RF | BO66: =BN66 -> 0 | BP66: =_xlfn.XLOOKUP(B66,Countries_WB!$C$2:$C$219,Countries_WB!$D$2:$D$219,"No Data",0) -> No Data | BQ66: =_xlfn.XLOOKUP(B66,Countries_WB!$C$2:$C$219,Countries_WB!$E$2:$E$219,"No Data",0) -> No Data
A67: Early-demographic dividend | B67: EAR | C67: Price level ratio of PPP conversion factor (GDP) to market exchange rate | D67: PA.NUS.PPPC.RF | BO67: =BN67 -> 0 | BP67: =_xlfn.XLOOKUP(B67,Countries_WB!$C$2:$C$219,Countries_WB!$D$2:$D$219,"No Data",0) -> No Data | BQ67: =_xlfn.XLOOKUP(B67,Countries_WB!$C$2:$C$219,Countries_WB!$E$2:$E$219,"No Data",0) -> No Data
A68: East Asia & Pacific | B68: EAS | C68: Price level ratio of PPP conversion factor (GDP) to market exchange rate | D68: PA.NUS.PPPC.RF | BO68: =BN68 -> 0 | BP68: =_xlfn.XLOOKUP(B68,Countries_WB!$C$2:$C$219,Countries_WB!$D$2:$D$219,"No Data",0) -> No Data | BQ68: =_xlfn.XLOOKUP(B68,Countries_WB!$C$2:$C$219,Countries_WB!$E$2:$E$219,"No Data",0) -> No Data
A69: Europe & Central Asia (excluding high income) | B69: ECA | C69: Price level ratio of PPP conversion factor (GDP) to market exchange rate | D69: PA.NUS.PPPC.RF | BO69: =BN69 -> 0 | BP69: =_xlfn.XLOOKUP(B69,Countries_WB!$C$2:$C$219,Countries_WB!$D$2:$D$219,"No Data",0) -> No Data | BQ69: =_xlfn.XLOOKUP(B69,Countries_WB!$C$2:$C$219,Countries_WB!$E$2:$E$219,"No Data",0) -> No Data
A70: Europe & Central Asia | B70: ECS | C70: Price level ratio of PPP conversion factor (GDP) to market exchange rate | D70: PA.NUS.PPPC.RF | BO70: =BN70 -> 0 | BP70: =_xlfn.XLOOKUP(B70,Countries_WB!$C$2:$C$219,Countries_WB!$D$2:$D$219,"No Data",0) -> No Data | BQ70: =_xlfn.XLOOKUP(B70,Countries_WB!$C$2:$C$219,Countries_WB!$E$2:$E$219,"No Data",0) -> No Data
A71: Ecuador | B71: ECU | C71: Price level ratio of PPP conversion factor (GDP) to market exchange rate | D71: PA.NUS.PPPC.RF | AI71: 0.30873526 | AJ71: 0.3192168 | AK71: 0.32553479 | AL71: 0.32639793 | AM71: 0.36753759 | AN71: 0.3787896 | AO71: 0.37752185 | AP71: 0.39712356 | AQ71: 0.37784883 | AR71: 0.2746048 | AS71: 0.2478074 | AT71: 0.3110531 | AU71: 0.34329437 | AV71: 0.3723119 | AW71: 0.37803135 | AX71: 0.39488066 | AY71: 0.41370937 | AZ71: 0.42961272 | BA71: 0.47989843 | BB71: 0.47996797 | BC71: 0.50967276 | BD71: 0.52757233 | BE71: 0.55104482 | BF71: 0.54298925 | BG71: 0.54443765 | BH71: 0.5537371 | BI71: 0.54920655 | BJ71: 0.53482097 | BK71: 0.53176475 | BL71: 0.52498158 | BM71: 0.51615106 | BN71: 0.50669936 | BO71: 0.49829272 | BP71: =_xlfn.XLOOKUP(B71,Countries_WB!$C$2:$C$219,Countries_WB!$D$2:$D$219,"No Data",0) -> Latin America & Caribbean | BQ71: =_xlfn.XLOOKUP(B71,Countries_WB!$C$2:$C$219,Countries_WB!$E$2:$E$219,"No Data",0) -> Upper middle income
A72: Egypt, Arab Rep. | B72: EGY | C72: Price level ratio of PPP conversion factor (GDP) to market exchange rate | D72: PA.NUS.PPPC.RF | AI72: 0.20640586 | AJ72: 0.17174841 | AK72: 0.17994111 | AL72: 0.19009324 | AM72: 0.1994494 | AN72: 0.21640343 | AO72: 0.22754997 | AP72: 0.24593005 | AQ72: 0.24912216 | AR72: 0.24769959 | AS72: 0.25062042 | AT72: 0.22925118 | AU72: 0.1941529 | AV72: 0.17397728 | AW72: 0.15971541 | AX72: 0.16858545 | AY72: 0.18351484 | AZ72: 0.20260201 | BA72: 0.23156603 | BB72: 0.25536391 | BC72: 0.2778342 | BD72: 0.28823017 | BE72: 0.29115301 | BF72: 0.29075368 | BG72: 0.31016663 | BH72: 0.30948647 | BI72: 0.31448856 | BJ72: 0.22191596 | BK72: 0.21752248 | BL72: 0.24569294 | BM72: 0.28208718 | BN72: 0.28917733 | BO72: 0.28453963 | BP72: =_xlfn.XLOOKUP(B72,Countries_WB!$C$2:$C$219,Countries_WB!$D$2:$D$219,"No Data",0) -> Middle East & North Africa | BQ72: =_xlfn.XLOOKUP(B72,Countries_WB!$C$2:$C$219,Countries_WB!$E$2:$E$219,"No Data",0) -> Lower middle income
A73: Euro area | B73: EMU | C73: Price level ratio of PPP conversion factor (GDP) to market exchange rate | D73: PA.NUS.PPPC.RF | BO73: =BN73 -> 0 | BP73: =_xlfn.XLOOKUP(B73,Countries_WB!$C$2:$C$219,Countries_WB!$D$2:$D$219,"No Data",0) -> No Data | BQ73: =_xlfn.XLOOKUP(B73,Countries_WB!$C$2:$C$219,Countries_WB!$E$2:$E$219,"No Data",0) -> No Data
A74: Eritrea | B74: ERI | C74: Price level ratio of PPP conversion factor (GDP) to market exchange rate | D74: PA.NUS.PPPC.RF | AK74: 0.23183928 | AL74: 0.19575233 | AM74: 0.19873692 | AN74: 0.20852681 | AO74: 0.22488208 | AP74: 0.20278624 | AQ74: 0.21398024 | AR74: 0.1949595 | AS74: 0.20181079 | AT74: 0.1932935 | AU74: 0.17911312 | AV74: 0.21530413 | AW74: 0.26338916 | AX74: 0.24658506 | AY74: 0.26633639 | AZ74: 0.27822835 | BA74: 0.31687942 | BB74: 0.40775957 | BC74: 0.33753111 | BD74: 0.39526621 | BE74: 0.41564717 | BF74: 0.39611073 | BG74: 0.39491297 | BH74: 0.37896904 | BI74: 0.37846154 | BJ74: 0.36284606 | BO74: =BN74 -> 0 | BP74: =_xlfn.XLOOKUP(B74,Countries_WB!$C$2:$C$219,Countries_WB!$D$2:$D$219,"No Data",0) -> Sub-Saharan Africa | BQ74: =_xlfn.XLOOKUP(B74,Countries_WB!$C$2:$C$219,Countries_WB!$E$2:$E$219,"No Data",0) -> Low income
A75: Spain | B75: ESP | C75: Price level ratio of PPP conversion factor (GDP) to market exchange rate | D75: PA.NUS.PPPC.RF | AI75: 1.0086827 | AJ75: 1.02347 | AK75: 1.0837851 | AL75: 0.89027062 | AM75: 0.86026456 | AN75: 0.94987857 | AO75: 0.94872061 | AP75: 0.82236591 | AQ75: 0.80611093 | AR75: 0.78783261 | AS75: 0.68322206 | AT75: 0.66956905 | AU75: 0.70191072 | AV75: 0.85880525 | AW75: 0.95269359 | AX75: 0.95733742 | AY75: 0.92417724 | AZ75: 1.0036244 | BA75: 1.0675655 | BB75: 1.0023925 | BC75: 0.96374431 | BD75: 0.99403561 | BE75: 0.89289729 | BF75: 0.89621405 | BG75: 0.87994445 | BH75: 0.7375376 | BI75: 0.71134464 | BJ75: 0.71264694 | BK75: 0.7461247 | BL75: 0.68620653 | BM75: 0.7096887 | BN75: 0.74033511 | BO75: 0.64048103 | BP75: =_xlfn.XLOOKUP(B75,Countries_WB!$C$2:$C$219,Countries_WB!$D$2:$D$219,"No Data",0) -> Europe & Central Asia | BQ75: =_xlfn.XLOOKUP(B75,Countries_WB!$C$2:$C$219,Countries_WB!$E$2:$E$219,"No Data",0) -> High income
A76: Estonia | B76: EST | C76: Price level ratio of PPP conversion factor (GDP) to market exchange rate | D76: PA.NUS.PPPC.RF | AL76: 0.46197142 | AM76: 0.4724619 | AN76: 0.48370102 | AO76: 0.49057875 | AP76: 0.46155996 | AQ76: 0.48438091 | AR76: 0.4922615 | AS76: 0.43198102 | AT76: 0.43677289 | AU76: 0.45798719 | AV76: 0.54849593 | AW76: 0.61322484 | AX76: 0.625952 | AY76: 0.65339982 | AZ76: 0.75432795 | BA76: 0.79838143 | BB76: 0.71841345 | BC76: 0.67826823 | BD76: 0.71212431 | BE76: 0.66945584 | BF76: 0.69384074 | BG76: 0.69997378 | BH76: 0.59645194 | BI76: 0.5842777 | BJ76: 0.6042755 | BK76: 0.63624751 | BL76: 0.60051747 | BM76: 0.59822864 | BN76: 0.64272592 | BO76: 0.60672872 | BP76: =_xlfn.XLOOKUP(B76,Countries_WB!$C$2:$C$219,Countries_WB!$D$2:$D$219,"No Data",0) -> Europe & Central Asia | BQ76: =_xlfn.XLOOKUP(B76,Countries_WB!$C$2:$C$219,Countries_WB!$E$2:$E$219,"No Data",0) -> High income
A77: Ethiopia | B77: ETH | C77: Price level ratio of PPP conversion factor (GDP) to market exchange rate | D77: PA.NUS.PPPC.RF | AI77: 0.62857626 | AJ77: 0.72404993 | AK77: 0.60410202 | AL77: 0.43894031 | AM77: 0.32673874 | AN77: 0.33358763 | AO77: 0.3249896 | AP77: 0.31126887 | AQ77: 0.29020966 | AR77: 0.26804368 | AS77: 0.25803634 | AT77: 0.23269663 | AU77: 0.21527285 | AV77: 0.23701175 | AW77: 0.23875855 | AX77: 0.25341711 | AY77: 0.27330552 | AZ77: 0.30792818 | BA77: 0.37454903 | BB77: 0.40992274 | BC77: 0.33211008 | BD77: 0.31237611 | BE77: 0.38487098 | BF77: 0.38917398 | BG77: 0.37452943 | BH77: 0.3864868 | BI77: 0.38169111 | BJ77: 0.38016324 | BK77: 0.35816751 | BL77: 0.3695607 | BM77: 0.38607805 | BN77: 0.36145585 | BO77: 0.36536217 | BP77: =_xlfn.XLOOKUP(B77,Countries_WB!$C$2:$C$219,Countries_WB!$D$2:$D$219,"No Data",0) -> Sub-Saharan Africa | BQ77: =_xlfn.XLOOKUP(B77,Countries_WB!$C$2:$C$219,Countries_WB!$E$2:$E$219,"No Data",0) -> Low income
A78: European Union | B78: EUU | C78: Price level ratio of PPP conversion factor (GDP) to market exchange rate | D78: PA.NUS.PPPC.RF | BO78: =BN78 -> 0 | BP78: =_xlfn.XLOOKUP(B78,Countries_WB!$C$2:$C$219,Countries_WB!$D$2:$D$219,"No Data",0) -> No Data | BQ78: =_xlfn.XLOOKUP(B78,Countries_WB!$C$2:$C$219,Countries_WB!$E$2:$E$219,"No Data",0) -> No Data
A79: Fragile and conflict affected situations | B79: FCS | C79: Price level ratio of PPP conversion factor (GDP) to market exchange rate | D79: PA.NUS.PPPC.RF | BO79: =BN79 -> 0 | BP79: =_xlfn.XLOOKUP(B79,Countries_WB!$C$2:$C$219,Countries_WB!$D$2:$D$219,"No Data",0) -> No Data | BQ79: =_xlfn.XLOOKUP(B79,Countries_WB!$C$2:$C$219,Countries_WB!$E$2:$E$219,"No Data",0) -> No Data
A80: Finland | B80: FIN | C80: Price level ratio of PPP conversion factor (GDP) to market exchange rate | D80: PA.NUS.PPPC.RF | AI80: 1.5630742 | AJ80: 1.4513013 | AK80: 1.2922817 | AL80: 1.0074487 | AM80: 1.0985862 | AN80: 1.3412296 | AO80: 1.2835335 | AP80: 1.1329435 | AQ80: 1.1031397 | AR80: 1.0572897 | AS80: 0.90877287 | AT80: 0.89808893 | AU80: 0.94380834 | AV80: 1.1333673 | AW80: 1.210572 | AX80: 1.2184919 | AY80: 1.1964915 | AZ80: 1.2809831 | BA80: 1.3415128 | BB80: 1.2504127 | BC80: 1.193837 | BD80: 1.2500705 | BE80: 1.1672241 | BF80: 1.202421 | BG80: 1.2052292 | BH80: 1.0071581 | BI80: 0.97506542 | BJ80: 0.97565706 | BK80: 1.0082352 | BL80: 0.93859094 | BM80: 0.94005253 | BN80: 0.97775959 | BO80: 0.8561654 | BP80: =_xlfn.XLOOKUP(B80,Countries_WB!$C$2:$C$219,Countries_WB!$D$2:$D$219,"No Data",0) -> Europe & Central Asia | BQ80: =_xlfn.XLOOKUP(B80,Countries_WB!$C$2:$C$219,Countries_WB!$E$2:$E$219,"No Data",0) -> High income
A81: Fiji | B81: FJI | C81: Price level ratio of PPP conversion factor (GDP) to market exchange rate | D81: PA.NUS.PPPC.RF | AI81: 0.43732334 | AJ81: 0.44999558 | AK81: 0.4591796 | AL81: 0.46891041 | AM81: 0.48745849 | AN81: 0.50268608 | AO81: 0.50890509 | AP81: 0.50228606 | AQ81: 0.38779305 | AR81: 0.41170938 | AS81: 0.35493442 | AT81: 0.33508487 | AU81: 0.35469578 | AV81: 0.43215438 | AW81: 0.47048575 | AX81: 0.49856447 | AY81: 0.49012416 | AZ81: 0.52857397 | BA81: 0.53533824 | BB81: 0.43949704 | BC81: 0.46142168 | BD81: 0.52972002 | BE81: 0.51943964 | BF81: 0.507588 | BG81: 0.4940336 | BH81: 0.43429623 | BI81: 0.44738148 | BJ81: 0.45431239 | BK81: 0.4455518 | BL81: 0.42944766 | BM81: 0.41601133 | BN81: 0.40652066 | BO81: 0.366053 | BP81: =_xlfn.XLOOKUP(B81,Countries_WB!$C$2:$C$219,Countries_WB!$D$2:$D$219,"No Data",0) -> East Asia & Pacific | BQ81: =_xlfn.XLOOKUP(B81,Countries_WB!$C$2:$C$219,Countries_WB!$E$2:$E$219,"No Data",0) -> Upper middle income
A82: France | B82: FRA | C82: Price level ratio of PPP conversion factor (GDP) to market exchange rate | D82: PA.NUS.PPPC.RF | AI82: 1.2346308 | AJ82: 1.1819463 | AK82: 1.2558773 | AL82: 1.1652757 | AM82: 1.1745924 | AN82: 1.2941359 | AO82: 1.2581177 | AP82: 1.0892504 | AQ82: 1.069105 | AR82: 1.0153876 | AS82: 0.85913516 | AT82: 0.81661082 | AU82: 0.85165745 | AV82: 1.0518061 | AW82: 1.1631992 | AX82: 1.1401565 | AY82: 1.1234408 | AZ82: 1.2178876 | BA82: 1.297021 | BB82: 1.2036373 | BC82: 1.1330569 | BD82: 1.1711369 | BE82: 1.0847484 | BF82: 1.0779577 | BG82: 1.0728507 | BH82: 0.89725642 | BI82: 0.86343313 | BJ82: 0.86997764 | BK82: 0.89299765 | BL82: 0.80186392 | BM82: 0.81137043 | BN82: 0.84999643 | BO82: 0.73818604 | BP82: =_xlfn.XLOOKUP(B82,Countries_WB!$C$2:$C$219,Countries_WB!$D$2:$D$219,"No Data",0) -> Europe & Central Asia | BQ82: =_xlfn.XLOOKUP(B82,Countries_WB!$C$2:$C$219,Countries_WB!$E$2:$E$219,"No Data",0) -> High income
A83: Faroe Islands | B83: FRO | C83: Price level ratio of PPP conversion factor (GDP) to market exchange rate | D83: PA.NUS.PPPC.RF | BO83: =BN83 -> 0 | BP83: =_xlfn.XLOOKUP(B83,Countries_WB!$C$2:$C$219,Countries_WB!$D$2:$D$219,"No Data",0) -> Europe & Central Asia | BQ83: =_xlfn.XLOOKUP(B83,Countries_WB!$C$2:$C$219,Countries_WB!$E$2:$E$219,"No Data",0) -> High income
A84: Micronesia, Fed. Sts. | B84: FSM | C84: Price level ratio of PPP conversion factor (GDP) to market exchange rate | D84: PA.NUS.PPPC.RF | AI84: 0.86413676 | AJ84: 0.87851046 | AK84: 0.8849667 | AL84: 0.89051561 | AM84: 0.8946973 | AN84: 0.89601938 | AO84: 0.89635934 | AP84: 0.88690244 | AQ84: 0.90326533 | AR84: 0.8837246 | AS84: 0.87347027 | AT84: 0.86369703 | AU84: 0.85124359 | AV84: 0.831729 | AW84: 0.81803132 | AX84: 0.80979174 | AY84: 0.79643048 | AZ84: 0.8000902 | BA84: 0.82432454 | BB84: 0.86299031 | BC84: 0.8834663 | BD84: 0.87929396 | BE84: 0.92462567 | BF84: 0.91450255 | BG84: 0.92486222 | BH84: 0.86762271 | BI84: 0.89378484 | BJ84: 0.9426535 | BK84: 1.0069271 | BL84: 1.0119154 | BM84: 1.0075581 | BN84: 0.97933492 | BO84: 0.96344329 | BP84: =_xlfn.XLOOKUP(B84,Countries_WB!$C$2:$C$219,Countries_WB!$D$2:$D$219,"No Data",0) -> East Asia & Pacific | BQ84: =_xlfn.XLOOKUP(B84,Countries_WB!$C$2:$C$219,Countries_WB!$E$2:$E$219,"No Data",0) -> Lower middle income
A85: Gabon | B85: GAB | C85: Price level ratio of PPP conversion factor (GDP) to market exchange rate | D85: PA.NUS.PPPC.RF | AI85: 0.5391538 | AJ85: 0.44611451 | AK85: 0.46586631 | AL85: 0.34278301 | AM85: 0.30972048 | AN85: 0.34194629 | AO85: 0.37209446 | AP85: 0.3236254 | AQ85: 0.26030099 | AR85: 0.29315075 | AS85: 0.31831539 | AT85: 0.28299556 | AU85: 0.29670927 | AV85: 0.34731872 | AW85: 0.40083407 | AX85: 0.46681384 | AY85: 0.50213045 | AZ85: 0.55623079 | BA85: 0.70564134 | BB85: 0.54474616 | BC85: 0.5963701 | BD85: 0.69121166 | BE85: 0.63905669 | BF85: 0.64068673 | BG85: 0.62868022 | BH85: 0.50237645 | BI85: 0.4888931 | BJ85: 0.48180912 | BK85: 0.52715136 | BL85: 0.49853214 | BM85: 0.45498254 | BN85: 0.56618669 | BO85: 0.53570368 | BP85: =_xlfn.XLOOKUP(B85,Countries_WB!$C$2:$C$219,Countries_WB!$D$2:$D$219,"No Data",0) -> Sub-Saharan Africa | BQ85: =_xlfn.XLOOKUP(B85,Countries_WB!$C$2:$C$219,Countries_WB!$E$2:$E$219,"No Data",0) -> Upper middle income
A86: United Kingdom | B86: GBR | C86: Price level ratio of PPP conversion factor (GDP) to market exchange rate | D86: PA.NUS.PPPC.RF | AI86: 1.1172621 | AJ86: 1.1423792 | AK86: 1.1483485 | AL86: 0.98477355 | AM86: 0.99767065 | AN86: 1.1249408 | AO86: 1.1121061 | AP86: 1.160239 | AQ86: 1.1936022 | AR86: 1.1742744 | AS86: 1.0659343 | AT86: 0.99978264 | AU86: 1.0339883 | AV86: 1.1360702 | AW86: 1.2593098 | AX86: 1.28658 | AY86: 1.2815676 | AZ86: 1.4188655 | BA86: 1.2898732 | BB86: 1.1061941 | BC86: 1.0851382 | BD86: 1.1312383 | BE86: 1.1083443 | BF86: 1.0869014 | BG86: 1.1492676 | BH86: 1.058064 | BI86: 0.92974744 | BJ86: 0.88107942 | BK86: 0.91746378 | BL86: 0.86727965 | BM86: 0.87893253 | BN86: 0.93067064 | BO86: 0.83971226 | BP86: =_xlfn.XLOOKUP(B86,Countries_WB!$C$2:$C$219,Countries_WB!$D$2:$D$219,"No Data",0) -> Europe & Central Asia | BQ86: =_xlfn.XLOOKUP(B86,Countries_WB!$C$2:$C$219,Countries_WB!$E$2:$E$219,"No Data",0) -> High income
A87: Georgia | B87: GEO | C87: Price level ratio of PPP conversion factor (GDP) to market exchange rate | D87: PA.NUS.PPPC.RF | AI87: 0.2726871 | AJ87: 0.28527412 | AK87: 0.29502141 | AL87: 0.29520535 | AM87: 0.30022318 | AN87: 0.30709099 | AO87: 0.31159429 | AP87: 0.31436288 | AQ87: 0.31034687 | AR87: 0.23052529 | AS87: 0.24170122 | AT87: 0.2374868 | AU87: 0.23384755 | AV87: 0.24270426 | AW87: 0.28688761 | AX87: 0.31748851 | AY87: 0.34005561 | AZ87: 0.38629779 | BA87: 0.46547035 | BB87: 0.40393747 | BC87: 0.42724144 | BD87: 0.4810541 | BE87: 0.45002106 | BF87: 0.43573154 | BG87: 0.40942141 | BH87: 0.33204197 | BI87: 0.31591027 | BJ87: 0.32060499 | BK87: 0.32351466 | BL87: 0.30055421 | BM87: 0.28855171 | BN87: 0.29394987 | BO87: 0.33090084 | BP87: =_xlfn.XLOOKUP(B87,Countries_WB!$C$2:$C$219,Countries_WB!$D$2:$D$219,"No Data",0) -> Europe & Central Asia | BQ87: =_xlfn.XLOOKUP(B87,Countries_WB!$C$2:$C$219,Countries_WB!$E$2:$E$219,"No Data",0) -> Upper middle income
A88: Ghana | B88: GHA | C88: Price level ratio of PPP conversion factor (GDP) to market exchange rate | D88: PA.NUS.PPPC.RF | AI88: 0.52810053 | AJ88: 0.54403061 | AK88: 0.49753729 | AL88: 0.43122868 | AM88: 0.37294363 | AN88: 0.41643471 | AO88: 0.41929411 | AP88: 0.39321534 | AQ88: 0.40321146 | AR88: 0.39286571 | AS88: 0.23916792 | AT88: 0.23988812 | AU88: 0.26224102 | AV88: 0.30259323 | AW88: 0.32470843 | AX88: 0.35966213 | AY88: 0.38925949 | AZ88: 0.43179119 | BA88: 0.44837342 | BB88: 0.38595449 | BC88: 0.43688333 | BD88: 0.4584833 | BE88: 0.41979008 | BF88: 0.44593582 | BG88: 0.36138584 | BH88: 0.34076928 | BI88: 0.39496392 | BJ88: 0.40545595 | BK88: 0.41536531 | BL88: 0.3890282 | BM88: 0.39158631 | BN88: 0.40492155 | BO88: 0.34041841 | BP88: =_xlfn.XLOOKUP(B88,Countries_WB!$C$2:$C$219,Countries_WB!$D$2:$D$219,"No Data",0) -> Sub-Saharan Africa | BQ88: =_xlfn.XLOOKUP(B88,Countries_WB!$C$2:$C$219,Countries_WB!$E$2:$E$219,"No Data",0) -> Lower middle income
A89: Gibraltar | B89: GIB | C89: Price level ratio of PPP conversion factor (GDP) to market exchange rate | D89: PA.NUS.PPPC.RF | BO89: =BN89 -> 0 | BP89: =_xlfn.XLOOKUP(B89,Countries_WB!$C$2:$C$219,Countries_WB!$D$2:$D$219,"No Data",0) -> Europe & Central Asia | BQ89: =_xlfn.XLOOKUP(B89,Countries_WB!$C$2:$C$219,Countries_WB!$E$2:$E$219,"No Data",0) -> High income
A90: Guinea | B90: GIN | C90: Price level ratio of PPP conversion factor (GDP) to market exchange rate | D90: PA.NUS.PPPC.RF | AI90: 0.69407275 | AJ90: 0.73972476 | AK90: 0.76294879 | AL90: 0.70830189 | AM90: 0.68816608 | AN90: 0.70350325 | AO90: 0.6927268 | AP90: 0.63316734 | AQ90: 0.57292022 | AR90: 0.52493826 | AS90: 0.43336536 | AT90: 0.38621108 | AU90: 0.37704233 | AV90: 0.42661194 | AW90: 0.42822381 | AX90: 0.32567989 | AY90: 0.30766448 | AZ90: 0.41747622 | BA90: 0.43608424 | BB90: 0.42266669 | BC90: 0.40656911 | BD90: 0.37336876 | BE90: 0.39937142 | BF90: 0.42455108 | BG90: 0.43625364 | BH90: 0.42281598 | BI90: 0.3522934 | BJ90: 0.35386464 | BK90: 0.37311925 | BL90: 0.39346679 | BM90: 0.39042392 | BN90: 0.4081593 | BO90: 0.47526106 | BP90: =_xlfn.XLOOKUP(B90,Countries_WB!$C$2:$C$219,Countries_WB!$D$2:$D$219,"No Data",0) -> Sub-Saharan Africa | BQ90: =_xlfn.XLOOKUP(B90,Countries_WB!$C$2:$C$219,Countries_WB!$E$2:$E$219,"No Data",0) -> Lower middle income
A91: Gambia, The | B91: GMB | C91: Price level ratio of PPP conversion factor (GDP) to market exchange rate | D91: PA.NUS.PPPC.RF | AI91: 0.29984104 | AJ91: 0.28327006 | AK91: 0.29125592 | AL91: 0.2919645 | AM91: 0.28218871 | AN91: 0.28847635 | AO91: 0.28401211 | AP91: 0.2784773 | AQ91: 0.27056175 | AR91: 0.26001187 | AS91: 0.23158735 | AT91: 0.21254844 | AU91: 0.19137738 | AV91: 0.16690697 | AW91: 0.29988177 | AX91: 0.31813581 | AY91: 0.31831299 | AZ91: 0.36515389 | BA91: 0.41150894 | BB91: 0.35593778 | BC91: 0.35342234 | BD91: 0.34424468 | BE91: 0.33765995 | BF91: 0.3302002 | BG91: 0.29966431 | BH91: 0.31967509 | BI91: 0.33391216 | BJ91: 0.32796467 | BK91: 0.33155412 | BL91: 0.33286694 | BM91: 0.32638805 | BN91: 0.3369774 | BO91: 0.32376518 | BP91: =_xlfn.XLOOKUP(B91,Countries_WB!$C$2:$C$219,Countries_WB!$D$2:$D$219,"No Data",0) -> Sub-Saharan Africa | BQ91: =_xlfn.XLOOKUP(B91,Countries_WB!$C$2:$C$219,Countries_WB!$E$2:$E$219,"No Data",0) -> Low income
A92: Guinea-Bissau | B92: GNB | C92: Price level ratio of PPP conversion factor (GDP) to market exchange rate | D92: PA.NUS.PPPC.RF | AI92: 0.4332269 | AJ92: 0.42027519 | AK92: 0.35770063 | AL92: 0.35821137 | AM92: 0.33803806 | AN92: 0.34183574 | AO92: 0.3202836 | AP92: 0.29359467 | AQ92: 0.31042902 | AR92: 0.32940942 | AS92: 0.28835326 | AT92: 0.29196682 | AU92: 0.30897139 | AV92: 0.34429352 | AW92: 0.3635981 | AX92: 0.37304875 | AY92: 0.35692958 | AZ92: 0.39595349 | BA92: 0.4689416 | BB92: 0.43102351 | BC92: 0.41681959 | BD92: 0.48889643 | BE92: 0.45478451 | BF92: 0.46516391 | BG92: 0.45225372 | BH92: 0.37778473 | BI92: 0.37867856 | BJ92: 0.3836149 | BK92: 0.41217121 | BL92: 0.3707346 | BM92: 0.37290574 | BN92: 0.39345656 | BO92: 0.35407147 | BP92: =_xlfn.XLOOKUP(B92,Countries_WB!$C$2:$C$219,Countries_WB!$D$2:$D$219,"No Data",0) -> Sub-Saharan Africa | BQ92: =_xlfn.XLOOKUP(B92,Countries_WB!$C$2:$C$219,Countries_WB!$E$2:$E$219,"No Data",0) -> Low income
A93: Equatorial Guinea | B93: GNQ | C93: Price level ratio of PPP conversion factor (GDP) to market exchange rate | D93: PA.NUS.PPPC.RF | AI93: 0.51431272 | AJ93: 0.49718733 | AK93: 0.43818335 | AL93: 0.38934081 | AM93: 0.24210152 | AN93: 0.2840186 | AO93: 0.2743837 | AP93: 0.20532425 | AQ93: 0.13746821 | AR93: 0.18075062 | AS93: 0.22401342 | AT93: 0.18730963 | AU93: 0.19090428 | AV93: 0.22593278 | AW93: 0.28302938 | AX93: 0.39187256 | AY93: 0.4332318 | AZ93: 0.4742073 | BA93: 0.59677096 | BB93: 0.44521333 | BC93: 0.52438933 | BD93: 0.63132172 | BE93: 0.57787555 | BF93: 0.58651302 | BG93: 0.57555663 | BH93: 0.46931338 | BI93: 0.45214412 | BJ93: 0.42871162 | BK93: 0.47928556 | BL93: 0.4322363 | BM93: 0.39015807 | BN93: 0.45563004 | BO93: 0.40760291 | BP93: =_xlfn.XLOOKUP(B93,Countries_WB!$C$2:$C$219,Countries_WB!$D$2:$D$219,"No Data",0) -> Sub-Saharan Africa | BQ93: =_xlfn.XLOOKUP(B93,Countries_WB!$C$2:$C$219,Countries_WB!$E$2:$E$219,"No Data",0) -> Upper middle income
A94: Greece | B94: GRC | C94: Price level ratio of PPP conversion factor (GDP) to market exchange rate | D94: PA.NUS.PPPC.RF | AI94: 0.72116509 | AJ94: 0.72672462 | AK94: 0.77995888 | AL94: 0.72488407 | AM94: 0.74564607 | AN94: 0.83970143 | AO94: 0.85134343 | AP94: 0.78269562 | AQ94: 0.74703217 | AR94: 0.71756597 | AS94: 0.6184916 | AT94: 0.59874804 | AU94: 0.62688418 | AV94: 0.77489803 | AW94: 0.8639026 | AX94: 0.88203014 | AY94: 0.86950219 | AZ94: 0.98431296 | BA94: 1.0412228 | BB94: 0.98251961 | BC94: 0.95718467 | BD94: 0.99269098 | BE94: 0.87964727 | BF94: 0.83842232 | BG94: 0.81189333 | BH94: 0.67577102 | BI94: 0.65150103 | BJ94: 0.64961299 | BK94: 0.66707042 | BL94: 0.61446724 | BM94: 0.62143235 | BN94: 0.64523806 | BO94: 0.56283765 | BP94: =_xlfn.XLOOKUP(B94,Countries_WB!$C$2:$C$219,Countries_WB!$D$2:$D$219,"No Data",0) -> Europe & Central Asia | BQ94: =_xlfn.XLOOKUP(B94,Countries_WB!$C$2:$C$219,Countries_WB!$E$2:$E$219,"No Data",0) -> High income
A95: Grenada | B95: GRD | C95: Price level ratio of PPP conversion factor (GDP) to market exchange rate | D95: PA.NUS.PPPC.RF | AI95: 0.61214354 | AJ95: 0.63161331 | AK95: 0.64231324 | AL95: 0.63925814 | AM95: 0.64586343 | AN95: 0.65191266 | AO95: 0.65730381 | AP95: 0.65769329 | AQ95: 0.66167578 | AR95: 0.65979831 | AS95: 0.66255232 | AT95: 0.6618475 | AU95: 0.65411594 | AV95: 0.64096179 | AW95: 0.6368841 | AX95: 0.63289442 | AY95: 0.64239226 | AZ95: 0.63999612 | BA95: 0.67723242 | BB95: 0.67285269 | BC95: 0.66805239 | BD95: 0.65592399 | BE95: 0.66680511 | BF95: 0.65528711 | BG95: 0.6417731 | BH95: 0.64277856 | BI95: 0.64078675 | BJ95: 0.6260418 | BK95: 0.60704293 | BL95: 0.61618849 | BM95: 0.60642668 | BN95: 0.59654632 | BO95: 0.56718045 | BP95: =_xlfn.XLOOKUP(B95,Countries_WB!$C$2:$C$219,Countries_WB!$D$2:$D$219,"No Data",0) -> Latin America & Caribbean | BQ95: =_xlfn.XLOOKUP(B95,Countries_WB!$C$2:$C$219,Countries_WB!$E$2:$E$219,"No Data",0) -> Upper middle income
A96: Greenland | B96: GRL | C96: Price level ratio of PPP conversion factor (GDP) to market exchange rate | D96: PA.NUS.PPPC.RF | BO96: =BN96 -> 0 | BP96: =_xlfn.XLOOKUP(B96,Countries_WB!$C$2:$C$219,Countries_WB!$D$2:$D$219,"No Data",0) -> Europe & Central Asia | BQ96: =_xlfn.XLOOKUP(B96,Countries_WB!$C$2:$C$219,Countries_WB!$E$2:$E$219,"No Data",0) -> High income
A97: Guatemala | B97: GTM | C97: Price level ratio of PPP conversion factor (GDP) to market exchange rate | D97: PA.NUS.PPPC.RF | AI97: 0.22337177 | AJ97: 0.25628259 | AK97: 0.26529842 | AL97: 0.27227269 | AM97: 0.2918306 | AN97: 0.30743746 | AO97: 0.31363385 | AP97: 0.33528966 | AQ97: 0.34428731 | AR97: 0.30877088 | AS97: 0.30685298 | AT97: 0.31895521 | AU97: 0.33595478 | AV97: 0.3390168 | AW97: 0.34979564 | AX97: 0.3730584 | AY97: 0.38148374 | AZ97: 0.39421044 | BA97: 0.42952019 | BB97: 0.40956215 | BC97: 0.43097051 | BD97: 0.46709535 | BE97: 0.46567094 | BF97: 0.47307135 | BG97: 0.48715983 | BH97: 0.48748038 | BI97: 0.50759062 | BJ97: 0.53519688 | BK97: 0.51722565 | BL97: 0.51409057 | BM97: 0.52036247 | BN97: 0.51055997 | BO97: 0.50575977 | BP97: =_xlfn.XLOOKUP(B97,Countries_WB!$C$2:$C$219,Countries_WB!$D$2:$D$219,"No Data",0) -> Latin America & Caribbean | BQ97: =_xlfn.XLOOKUP(B97,Countries_WB!$C$2:$C$219,Countries_WB!$E$2:$E$219,"No Data",0) -> Upper middle income
A98: Guam | B98: GUM | C98: Price level ratio of PPP conversion factor (GDP) to market exchange rate | D98: PA.NUS.PPPC.RF | BO98: =BN98 -> 0 | BP98: =_xlfn.XLOOKUP(B98,Countries_WB!$C$2:$C$219,Countries_WB!$D$2:$D$219,"No Data",0) -> East Asia & Pacific | BQ98: =_xlfn.XLOOKUP(B98,Countries_WB!$C$2:$C$219,Countries_WB!$E$2:$E$219,"No Data",0) -> High income
A99: Guyana | B99: GUY | C99: Price level ratio of PPP conversion factor (GDP) to market exchange rate | D99: PA.NUS.PPPC.RF | AI99: 0.43736366 | AJ99: 0.35056344 | AK99: 0.34092833 | AL99: 0.37423017 | AM99: 0.40211191 | AN99: 0.43097085 | AO99: 0.44486947 | AP99: 0.43740584 | AQ99: 0.42136317 | AR99: 0.3907519 | AS99: 0.39736623 | AT99: 0.37968316 | AU99: 0.37691789 | AV99: 0.38064874 | AW99: 0.38697292 | AX99: 0.40067739 | AY99: 0.40991403 | AZ99: 0.44498949 | BA99: 0.47531065 | BB99: 0.47698774 | BC99: 0.4908016 | BD99: 0.49147485 | BE99: 0.5132561 | BF99: 0.49796129 | BG99: 0.49372264 | BH99: 0.49800642 | BI99: 0.51443005 | BJ99: 0.51018301 | BK99: 0.48098631 | BL99: 0.48467394 | BM99: 0.35262219 | BN99: 0.41311171 | BO99: 0.43239529 | BP99: =_xlfn.XLOOKUP(B99,Countries_WB!$C$2:$C$219,Countries_WB!$D$2:$D$219,"No Data",0) -> Latin America & Caribbean | BQ99: =_xlfn.XLOOKUP(B99,Countries_WB!$C$2:$C$219,Countries_WB!$E$2:$E$219,"No Data",0) -> High income
A100: High income | B100: HIC | C100: Price level ratio of PPP conversion factor (GDP) to market exchange rate | D100: PA.NUS.PPPC.RF | BO100: =BN100 -> 0 | BP100: =_xlfn.XLOOKUP(B100,Countries_WB!$C$2:$C$219,Countries_WB!$D$2:$D$219,"No Data",0) -> No Data | BQ100: =_xlfn.XLOOKUP(B100,Countries_WB!$C$2:$C$219,Countries_WB!$E$2:$E$219,"No Data",0) -> No Data
...

Sheet Countries_WB
A1: Country | B1: Economy | C1: Code | D1: Region | E1: Income group | F1: Country code | G1: Country Currency
B2: Aruba | C2: ABW | D2: Latin America & Caribbean | E2: High income | F2: =C2 -> ABW | H2: 1
B3: Afghanistan | C3: AFG | D3: South Asia | E3: Low income | F3: =C3 -> AFG | H3: 2
B4: Angola | C4: AGO | D4: Sub-Saharan Africa | E4: Lower middle income | F4: =C4 -> AGO | H4: 3
B5: Albania | C5: ALB | D5: Europe & Central Asia | E5: Upper middle income | F5: =C5 -> ALB | H5: 4
B6: Andorra | C6: AND | D6: Europe & Central Asia | E6: High income | F6: =C6 -> AND | H6: 5
B7: United Arab Emirates | C7: ARE | D7: Middle East & North Africa | E7: High income | F7: =C7 -> ARE | H7: 6
B8: Argentina | C8: ARG | D8: Latin America & Caribbean | E8: Upper middle income | F8: =C8 -> ARG | H8: 7
B9: Armenia | C9: ARM | D9: Europe & Central Asia | E9: Upper middle income | F9: =C9 -> ARM | H9: 8
B10: American Samoa | C10: ASM | D10: East Asia & Pacific | E10: High income | F10: =C10 -> ASM | H10: 9
B11: Antigua and Barbuda | C11: ATG | D11: Latin America & Caribbean | E11: High income | F11: =C11 -> ATG | H11: 10
B12: Australia | C12: AUS | D12: East Asia & Pacific | E12: High income | F12: =C12 -> AUS | H12: 11
B13: Austria | C13: AUT | D13: Europe & Central Asia | E13: High income | F13: =C13 -> AUT | H13: 12
... B21: Bahrain | C21: BHR | D21: Middle East & North Africa | E21: High income | F21: =C21 -> BHR | H21: 20
A22: Bahamas | B22: Bahamas, The | C22: BHS | D22: Latin America & Caribbean | E22: High income | F22: =C22 -> BHS | H22: 21
B23: Bosnia and Herzegovina | C23: BIH | D23: Europe & Central Asia | E23: Upper middle income | F23: =C23 -> BIH | H23: 22
B24: Belarus | C24: BLR | D24: Europe & Central Asia | E24: Upper middle income | F24: =C24 -> BLR | H24: 23
B25: Belize | C25: BLZ | D25: Latin America & Caribbean | E25: Upper middle income | F25: =C25 -> BLZ | H25: 24
B26: Bermuda | C26: BMU | D26: North America | E26: High income | F26: =C26 -> BMU | H26: 25
A27: Bolivia (Plurinational State of) | B27: Bolivia | C27: BOL | D27: Latin America & Caribbean | E27: Lower middle income | F27: =C27 -> BOL | H27: 26
B28: Brazil | C28: BRA | D28: Latin America & Caribbean | E28: Upper middle income | F28: =C28 -> BRA | H28: 27
B29: Barbados | C29: BRB | D29: Latin America & Caribbean | E29: High income | F29: =C29 -> BRB | H29: 28
B30: Brunei Darussalam | C30: BRN | D30: East Asia & Pacific | E30: High income | F30: =C30 -> BRN | H30: 29
B31: Bhutan | C31: BTN | D31: South Asia | E31: Lower middle income | F31: =C31 -> BTN | H31: 30
B32: Botswana | C32: BWA | D32: Sub-Saharan Africa | E32: Upper middle income | F32: =C32 -> BWA | H32: 31
B33: Central African Republic | C33: CAF | D33: Sub-Saharan Africa | E33: Low income | F33: =C33 -> CAF | H33: 32
B34: Canada | C34: CAN | D34: North America | E34: High income | F34: =C34 -> CAN | H34: 33
B35: Switzerland | C35: CHE | D35: Europe & Central Asia | E35: High income | F35: =C35 -> CHE | H35: 34
A36: Jersey | B36: Channel Islands | C36: CHI | D36: Europe & Central Asia | E36: High income | F36: =C36 -> CHI | H36: 35
B37: Chile | C37: CHL | D37: Latin America & Caribbean | E37: High income | F37: =C37 -> CHL | H37: 36
B38: China | C38: CHN | D38: East Asia & Pacific | E38: Upper middle income | F38: =C38 -> CHN | H38: 37
A39: Ivory Coast | B39: Côte d’Ivoire | C39: CIV | D39: Sub-Saharan Africa | E39: Lower middle income | F39: =C39 -> CIV | H39: 38
B40: Cameroon | C40: CMR | D40: Sub-Saharan Africa | E40: Lower middle income | F40: =C40 -> CMR | H40: 39
B41: Congo, Dem. Rep. | C41: COD | D41: Sub-Saharan Africa | E41: Low income | F41: =C41 -> COD | H41: 40
B42: Congo, Rep. | C42: COG | D42: Sub-Saharan Africa | E42: Lower middle income | F42: =C42 -> COG | H42: 41
B43: Colombia | C43: COL | D43: Latin America & Caribbean | E43: Upper middle income | F43: =C43 -> COL | H43: 42
B44: Comoros | C44: COM | D44: Sub-Saharan Africa | E44: Lower middle income | F44: =C44 -> COM | H44: 43
B45: Cabo Verde | C45: CPV | D45: Sub-Saharan Africa | E45: Lower middle income | F45: =C45 -> CPV | H45: 44
B46: Costa Rica | C46: CRI | D46: Latin America & Caribbean | E46: Upper middle income | F46: =C46 -> CRI | H46: 45
B47: Cuba | C47: CUB | D47: Latin America & Caribbean | E47: Upper middle income | F47: =C47 -> CUB | H47: 46
B48: Curaçao | C48: CUW | D48: Latin America & Caribbean | E48: High income | F48: =C48 -> CUW | H48: 47
B49: Cayman Islands | C49: CYM | D49: Latin America & Caribbean | E49: High income | F49: =C49 -> CYM | H49: 48
B50: Cyprus | C50: CYP | D50: Europe & Central Asia | E50: High income | F50: =C50 -> CYP | H50: 49
A51: Czech Republic | B51: Czechia | C51: CZE | D51: Europe & Central Asia | E51: High income | F51: =C51 -> CZE | H51: 50
B52: Germany | C52: DEU | D52: Europe & Central Asia | E52: High income | F52: =C52 -> DEU | H52: 51
B53: Djibouti | C53: DJI | D53: Middle East & North Africa | E53: Lower middle income | F53: =C53 -> DJI | H53: 52
B54: Dominica | C54: DMA | D54: Latin America & Caribbean | E54: Upper middle income | F54: =C54 -> DMA | H54: 53
B55: Denmark | C55: DNK | D55: Europe & Central Asia | E55: High income | F55: =C55 -> DNK | H55: 54
B56: Dominican Republic | C56: DOM | D56: Latin America & Caribbean | E56: Upper middle income | F56: =C56 -> DOM | H56: 55
B57: Algeria | C57: DZA | D57: Middle East & North Africa | E57: Lower middle income | F57: =C57 -> DZA | H57: 56
B58: Ecuador | C58: ECU | D58: Latin America & Caribbean | E58: Upper middle income | F58: =C58 -> ECU | H58: 57
A59: Egypt | B59: Egypt, Arab Rep. | C59: EGY | D59: Middle East & North Africa | E59: Lower middle income | F59: =C59 -> EGY | H59: 58
B60: Eritrea | C60: ERI | D60: Sub-Saharan Africa | E60: Low income | F60: =C60 -> ERI | H60: 59
B61: Spain | C61: ESP | D61: Europe & Central Asia | E61: High income | F61: =C61 -> ESP | H61: 60
B62: Estonia | C62: EST | D62: Europe & Central Asia | E62: High income | F62: =C62 -> EST | H62: 61
B63: Ethiopia | C63: ETH | D63: Sub-Saharan Africa | E63: Low income | F63: =C63 -> ETH | H63: 62
B64: Finland | C64: FIN | D64: Europe & Central Asia | E64: High income | F64: =C64 -> FIN | H64: 63
B65: Fiji | C65: FJI | D65: East Asia & Pacific | E65: Upper middle income | F65: =C65 -> FJI | H65: 64
B66: France | C66: FRA | D66: Europe & Central Asia | E66: High income | F66: =C66 -> FRA | H66: 65
B67: Faroe Islands | C67: FRO | D67: Europe & Central Asia | E67: High income | F67: =C67 -> FRO | H67: 66
B68: Micronesia, Fed. Sts. | C68: FSM | D68: East Asia & Pacific | E68: Lower middle income | F68: =C68 -> FSM | H68: 67
B69: Gabon | C69: GAB | D69: Sub-Saharan Africa | E69: Upper middle income | F69: =C69 -> GAB | H69: 68
B70: United Kingdom | C70: GBR | D70: Europe & Central Asia | E70: High income | F70: =C70 -> GBR | H70: 69
B71: Georgia | C71: GEO | D71: Europe & Central Asia | E71: Upper middle income | F71: =C71 -> GEO | H71: 70
... B83: Guyana | C83: GUY | D83: Latin America & Caribbean | E83: High income | F83: =C83 -> GUY | H83: 82
A84: Hong Kong (China) | B84: Hong Kong SAR, China | C84: HKG | D84: East Asia & Pacific | E84: High income | F84: =C84 -> HKG | H84: 83
B85: Honduras | C85: HND | D85: Latin America & Caribbean | E85: Lower middle income | F85: =C85 -> HND | H85: 84
B86: Croatia | C86: HRV | D86: Europe & Central Asia | E86: High income | F86: =C86 -> HRV | H86: 85
B87: Haiti | C87: HTI | D87: Latin America & Caribbean | E87: Lower middle income | F87: =C87 -> HTI | H87: 86
B88: Hungary | C88: HUN | D88: Europe & Central Asia | E88: High income | F88: =C88 -> HUN | H88: 87
B89: Indonesia | C89: IDN | D89: East Asia & Pacific | E89: Upper middle income | F89: =C89 -> IDN | H89: 88
B90: Isle of Man | C90: IMN | D90: Europe & Central Asia | E90: High income | F90: =C90 -> IMN | H90: 89
B91: India | C91: IND | D91: South Asia | E91: Lower middle income | F91: =C91 -> IND | H91: 90
B92: Ireland | C92: IRL | D92: Europe & Central Asia | E92: High income | F92: =C92 -> IRL | H92: 91
A93: Iran | B93: Iran, Islamic Rep. | C93: IRN | D93: Middle East & North Africa | E93: Lower middle income | F93: =C93 -> IRN | H93: 92
B94: Iraq | C94: IRQ | D94: Middle East & North Africa | E94: Upper middle income | F94: =C94 -> IRQ | H94: 93
B95: Iceland | C95: ISL | D95: Europe & Central Asia | E95: High income | F95: =C95 -> ISL | H95: 94
B96: Israel | C96: ISR | D96: Middle East & North Africa | E96: High income | F96: =C96 -> ISR | H96: 95
B97: Italy | C97: ITA | D97: Europe & Central Asia | E97: High income | F97: =C97 -> ITA | H97: 96
B98: Jamaica | C98: JAM | D98: Latin America & Caribbean | E98: Upper middle income | F98: =C98 -> JAM | H98: 97
B99: Jordan | C99: JOR | D99: Middle East & North Africa | E99: Lower middle income | F99: =C99 -> JOR | H99: 98
B100: Japan | C100: JPN | D100: East Asia & Pacific | E100: High income | F100: =C100 -> JPN | H100: 99
B101: Kazakhstan | C101: KAZ | D101: Europe & Central Asia | E101: Upper middle income | F101: =C101 -> KAZ | H101: 100
B102: Kenya | C102: KEN | D102: Sub-Saharan Africa | E102: Lower middle income | F102: =C102 -> KEN | H102: 101
A103: Kyrgyzstan | B103: Kyrgyz Republic | C103: KGZ | D103: Europe & Central Asia | E103: Lower middle income | F103: =C103 -> KGZ | H103: 102
B104: Cambodia | C104: KHM | D104: East Asia & Pacific | E104: Lower middle income | F104: =C104 -> KHM | H104: 103
B105: Kiribati | C105: KIR | D105: East Asia & Pacific | E105: Lower middle income | F105: =C105 -> KIR | H105: 104
B106: St. Kitts and Nevis | C106: KNA | D106: Latin America & Caribbean | E106: High income | F106: =C106 -> KNA | H106: 105
A107: South Korea | B107: Korea, Rep. | C107: KOR | D107: East Asia & Pacific | E107: High income | F107: =C107 -> KOR | H107: 106
B108: Kuwait | C108: KWT | D108: Middle East & North Africa | E108: High income | F108: =C108 -> KWT | H108: 107
B109: Lao PDR | C109: LAO | D109: East Asia & Pacific | E109: Lower middle income | F109: =C109 -> LAO | H109: 108
B110: Lebanon | C110: LBN | D110: Middle East & North Africa | E110: Lower middle income | F110: =C110 -> LBN | H110: 109
B111: Liberia | C111: LBR | D111: Sub-Saharan Africa | E111: Low income | F111: =C111 -> LBR | H111: 110
B112: Libya | C112: LBY | D112: Middle East & North Africa | E112: Upper middle income | F112: =C112 -> LBY | H112: 111
B113: St. Lucia | C113: LCA | D113: Latin America & Caribbean | E113: Upper middle income | F113: =C113 -> LCA | H113: 112
B114: Liechtenstein | C114: LIE | D114: Europe & Central Asia | E114: High income | F114: =C114 -> LIE | H114: 113
B115: Sri Lanka | C115: LKA | D115: South Asia | E115: Lower middle income | F115: =C115 -> LKA | H115: 114
B116: Lesotho | C116: LSO | D116: Sub-Saharan Africa | E116: Lower middle income | F116: =C116 -> LSO | H116: 115
B117: Lithuania | C117: LTU | D117: Europe & Central Asia | E117: High income | F117: =C117 -> LTU | H117: 116
B118: Luxembourg | C118: LUX | D118: Europe & Central Asia | E118: High income | F118: =C118 -> LUX | H118: 117
...

Sheet Unemployment_WB
A1: Data Source | B1: World Development Indicators
A2: Last Updated Date | B2: 45343
A3: Vlookup | B3: 1 | C3: 2 | D3: 3 | E3: 4 | F3: 5 | G3: 6 | H3: 7 | I3: 8 | J3: 9 | K3: 10 | L3: 11 | M3: 12 | N3: 13 | O3: 14 | P3: 15 | Q3: 16 | R3: 17 | S3: 18 | T3: 19 | U3: 20 | V3: 21 | W3: 22 | X3: 23 | Y3: 24 | Z3: 25 | AA3: 26 | AB3: 27 | AC3: 28 | AD3: 29 | AE3: 30 | AF3: 31 | AG3: 32 | AH3: 33 | AI3: 34 | AJ3: 35 | AK3: 36 | AL3: 37 | AM3: 38 | AN3: 39 | AO3: 40 | AP3: 41 | AQ3: 42 | AR3: 43 | AS3: 44 | AT3: 45 | AU3: 46 | AV3: 47 | AW3: 48 | AX3: 49 | AY3: 50 | AZ3: 51 | BA3: 52 | BB3: 53 | BC3: 54 | BD3: 55 | BE3: 56 | BF3: 57 | BG3: 58 | BH3: 59 | BI3: 60 | BJ3: 61 | BK3: 62 | BL3: 63 | BM3: 64 | BN3: 65 | BO3: 65
A4: Country Name | B4: Country Code | C4: Indicator Name | D4: Indicator Code | E4: 1960 | F4: 1961 | G4: 1962 | H4: 1963 | I4: 1964 | J4: 1965 | K4: 1966 | L4: 1967 | M4: 1968 | N4: 1969 | O4: 1970 | P4: 1971 | Q4: 1972 | R4: 1973 | S4: 1974 | T4: 1975 | U4: 1976 | V4: 1977 | W4: 1978 | X4: 1979 | Y4: 1980 | Z4: 1981 | AA4: 1982 | AB4: 1983 | AC4: 1984 | AD4: 1985 | AE4: 1986 | AF4: 1987 | AG4: 1988 | AH4: 1989 | AI4: 1990 | AJ4: 1991 | AK4: 1992 | AL4: 1993 | AM4: 1994 | AN4: 1995 | AO4: 1996 | AP4: 1997 | AQ4: 1998 | AR4: 1999 | AS4: 2000 | AT4: 2001 | AU4: 2002 | AV4: 2003 | AW4: 2004 | AX4: 2005 | AY4: 2006 | AZ4: 2007 | BA4: 2008 | BB4: 2009 | BC4: 2010 | BD4: 2011 | BE4: 2012 | BF4: 2013 | BG4: 2014 | BH4: 2015 | BI4: 2016 | BJ4: 2017 | BK4: 2018 | BL4: 2019 | BM4: 2020 | BN4: 2021 | BO4: 2022
A5: Aruba | B5: ABW | C5: Unemployment, total (% of total labor force) (modeled ILO estimate) | D5: SL.UEM.TOTL.ZS
A6: Africa Eastern and Southern | B6: AFE | C6: Unemployment, total (% of total labor force) (modeled ILO estimate) | D6: SL.UEM.TOTL.ZS | AJ6: 7.8379511 | AK6: 7.9917248 | AL6: 7.9803818 | AM6: 7.8413725 | AN6: 7.5621295 | AO6: 7.4444711 | AP6: 7.3856467 | AQ6: 7.444838 | AR6: 7.516038 | AS6: 7.4709109 | AT6: 7.3471513 | AU6: 7.3080999 | AV6: 7.2648985 | AW6: 7.0632701 | AX6: 6.878497 | AY6: 6.8023942 | AZ6: 6.7462657 | BA6: 6.7367981 | BB6: 6.8592944 | BC6: 7.2753639 | BD6: 7.1493012 | BE6: 6.9848944 | BF6: 6.904383 | BG6: 6.8845004 | BH6: 6.9830641 | BI6: 7.1521569 | BJ6: 7.2742983 | BK6: 7.2375626 | BL6: 7.4267768 | BM6: 7.9102905 | BN6: 8.303939 | BO6: 7.7481444
A7: Afghanistan | B7: AFG | C7: Unemployment, total (% of total labor force) (modeled ILO estimate) | D7: SL.UEM.TOTL.ZS | AJ7: 7.942 | AK7: 7.94 | AL7: 7.945 | AM7: 7.947 | AN7: 7.942 | AO7: 7.934 | AP7: 7.932 | AQ7: 7.939 | AR7: 7.942 | AS7: 7.942 | AT7: 7.942 | AU7: 7.935 | AV7: 7.929 | AW7: 7.926 | AX7: 7.925 | AY7: 7.925 | AZ7: 7.924 | BA7: 7.928 | BB7: 7.923 | BC7: 7.921 | BD7: 7.918 | BE7: 7.914 | BF7: 7.914 | BG7: 7.91 | BH7: 9.002 | BI7: 10.092 | BJ7: 11.18 | BK7: 11.131 | BL7: 11.082 | BM7: 11.71 | BN7: 12.075 | BO7: 14.1
A8: Africa Western and Central | B8: AFW | C8: Unemployment, total (% of total labor force) (modeled ILO estimate) | D8: SL.UEM.TOTL.ZS | AJ8: 4.3259424 | AK8: 4.4459193 | AL8: 4.5902871 | AM8: 4.6228542 | AN8: 4.6113348 | AO8: 4.5145815 | AP8: 4.4709269 | AQ8: 4.4821582 | AR8: 4.7096532 | AS8: 4.7676789 | AT8: 4.6926193 | AU8: 4.4707161 | AV8: 4.3728644 | AW8: 4.3064126 | AX8: 4.3353844 | AY8: 4.2188987 | AZ8: 4.1959548 | BA8: 4.211854 | BB8: 4.2524911 | BC8: 4.2257546 | BD8: 4.2018549 | BE8: 4.1592643 | BF8: 3.8162161 | BG8: 3.9321254 | BH8: 4.1975756 | BI8: 4.1641298 | BJ8: 4.2384821 | BK8: 4.266695 | BL8: 4.2774828 | BM8: 4.7375009 | BN8: 4.5850142 | BO8: 3.8090795
A9: Angola | B9: AGO | C9: Unemployment, total (% of total labor force) (modeled ILO estimate) | D9: SL.UEM.TOTL.ZS | AJ9: 16.668 | AK9: 16.857 | AL9: 17.46 | AM9: 17.483 | AN9: 16.924 | AO9: 15.967 | AP9: 15.84 | AQ9: 16.117 | AR9: 16.43 | AS9: 16.562 | AT9: 16.597 | AU9: 16.317 | AV9: 16.34 | AW9: 16.187 | AX9: 16.173 | AY9: 15.969 | AZ9: 15.905 | BA9: 16.013 | BB9: 16.298 | BC9: 16.551 | BD9: 16.77 | BE9: 16.495 | BF9: 16.423 | BG9: 16.317 | BH9: 16.448 | BI9: 16.577 | BJ9: 16.639 | BK9: 16.626 | BL9: 16.5 | BM9: 16.698 | BN9: 15.8 | BO9: 14.478
A10: Albania | B10: ALB | C10: Unemployment, total (% of total labor force) (modeled ILO estimate) | D10: SL.UEM.TOTL.ZS | AJ10: 10.307 | AK10: 30.015 | AL10: 25.258 | AM10: 20.84 | AN10: 14.611 | AO10: 13.931 | AP10: 16.876 | AQ10: 20.047 | AR10: 20.84 | AS10: 19.028 | AT10: 18.575 | AU10: 17.895 | AV10: 16.989 | AW10: 16.31 | AX10: 15.97 | AY10: 15.63 | AZ10: 15.97 | BA10: 13.06 | BB10: 13.67 | BC10: 14.09 | BD10: 13.48 | BE10: 13.38 | BF10: 15.87 | BG10: 18.05 | BH10: 17.19 | BI10: 15.42 | BJ10: 13.62 | BK10: 12.3 | BL10: 11.47 | BM10: 12.833 | BN10: 12.59 | BO10: 11.629
A11: Andorra | B11: AND | C11: Unemployment, total (% of total labor force) (modeled ILO estimate) | D11: SL.UEM.TOTL.ZS
A12: Arab World | B12: ARB | C12: Unemployment, total (% of total labor force) (modeled ILO estimate) | D12: SL.UEM.TOTL.ZS | AJ12: 11.673849 | AK12: 11.904649 | AL12: 12.629525 | AM12: 12.750067 | AN12: 13.21112 | AO12: 12.222114 | AP12: 11.734528 | AQ12: 11.700889 | AR12: 11.860295 | AS12: 12.346092 | AT12: 12.228064 | AU12: 12.24775 | AV12: 12.209149 | AW12: 11.235308 | AX12: 11.060112 | AY12: 10.352288 | AZ12: 9.9647074 | BA12: 9.6779038 | BB12: 9.3075633 | BC12: 9.3832294 | BD12: 10.477601 | BE12: 10.958356 | BF12: 11.029713 | BG12: 11.120267 | BH12: 11.282761 | BI12: 11.076547 | BJ12: 11.45384 | BK12: 11.059249 | BL12: 10.673567 | BM12: 11.975018 | BN12: 11.684176 | BO12: 10.732883
A13: United Arab Emirates | B13: ARE | C13: Unemployment, total (% of total labor force) (modeled ILO estimate) | D13: SL.UEM.TOTL.ZS | AJ13: 1.66 | AK13: 1.737 | AL13: 1.907 | AM13: 1.838 | AN13: 1.8 | AO13: 1.841 | AP13: 1.914 | AQ13: 2.071 | AR13: 2.195 | AS13: 2.25 | AT13: 2.441 | AU13: 2.653 | AV13: 2.892 | AW13: 2.963 | AX13: 3.12 | AY13: 2.96 | AZ13: 2.917 | BA13: 2.795 | BB13: 2.887 | BC13: 2.756 | BD13: 2.544 | BE13: 2.256 | BF13: 2.07 | BG13: 1.956 | BH13: 1.789 | BI13: 1.64 | BJ13: 2.46 | BK13: 2.24 | BL13: 2.33 | BM13: 4.29 | BN13: 3.11 | BO13: 2.971
A14: Argentina | B14: ARG | C14: Unemployment, total (% of total labor force) (modeled ILO estimate) | D14: SL.UEM.TOTL.ZS | AJ14: 5.44 | AK14: 6.36 | AL14: 10.1 | AM14: 11.76 | AN14: 18.8 | AO14: 17.11 | AP14: 14.82 | AQ14: 12.65 | AR14: 14.05 | AS14: 15 | AT14: 17.32 | AU14: 19.59 | AV14: 15.36 | AW14: 13.52 | AX14: 11.51 | AY14: 10.08 | AZ14: 8.47 | BA14: 7.84 | BB14: 8.65 | BC14: 7.71 | BD14: 7.18 | BE14: 7.22 | BF14: 7.1 | BG14: 7.27 | BH14: 7.583 | BI14: 8.085 | BJ14: 8.35 | BK14: 9.22 | BL14: 9.84 | BM14: 11.46 | BN14: 8.74 | BO14: 6.805
A15: Armenia | B15: ARM | C15: Unemployment, total (% of total labor force) (modeled ILO estimate) | D15: SL.UEM.TOTL.ZS | AJ15: 1.6 | AK15: 1.8 | AL15: 5.3 | AM15: 6.6 | AN15: 6.7 | AO15: 9.3 | AP15: 10.8 | AQ15: 9.4 | AR15: 11.2 | AS15: 11.023 | AT15: 10.848 | AU15: 10.651 | AV15: 10.463 | AW15: 10.3 | AX15: 10.137 | AY15: 9.979 | AZ15: 9.81 | BA15: 10.126 | BB15: 10.512 | BC15: 10.851 | BD15: 11.16 | BE15: 11.385 | BF15: 11.682 | BG15: 11.989 | BH15: 12.308 | BI15: 12.625 | BJ15: 12.914 | BK15: 13.21 | BL15: 12.2 | BM15: 12.18 | BN15: 10.01 | BO15: 8.588
A16: American Samoa | B16: ASM | C16: Unemployment, total (% of total labor force) (modeled ILO estimate) | D16: SL.UEM.TOTL.ZS
A17: Antigua and Barbuda | B17: ATG | C17: Unemployment, total (% of total labor force) (modeled ILO estimate) | D17: SL.UEM.TOTL.ZS
A18: Australia | B18: AUS | C18: Unemployment, total (% of total labor force) (modeled ILO estimate) | D18: SL.UEM.TOTL.ZS | AJ18: 9.59 | AK18: 10.73 | AL18: 10.88 | AM18: 9.72 | AN18: 8.47 | AO18: 8.51 | AP18: 8.37 | AQ18: 7.68 | AR18: 6.88 | AS18: 6.29 | AT18: 6.75 | AU18: 6.38 | AV18: 5.93 | AW18: 5.4 | AX18: 5.04 | AY18: 4.79 | AZ18: 4.38 | BA18: 4.24 | BB18: 5.57 | BC18: 5.21 | BD18: 5.08 | BE18: 5.23 | BF18: 5.66 | BG18: 6.08 | BH18: 6.06 | BI18: 5.71 | BJ18: 5.59 | BK18: 5.3 | BL18: 5.16 | BM18: 6.46 | BN18: 5.12 | BO18: 3.7
A19: Austria | B19: AUT | C19: Unemployment, total (% of total labor force) (modeled ILO estimate) | D19: SL.UEM.TOTL.ZS | AJ19: 3.42 | AK19: 3.59 | AL19: 4.25 | AM19: 3.54 | AN19: 4.35 | AO19: 5.28 | AP19: 5.15 | AQ19: 5.52 | AR19: 4.7 | AS19: 4.69 | AT19: 4.01 | AU19: 4.85 | AV19: 4.78 | AW19: 5.97 | AX19: 5.68 | AY19: 5.32 | AZ19: 4.91 | BA19: 4.2 | BB19: 5.37 | BC19: 4.88 | BD19: 4.64 | BE19: 4.91 | BF19: 5.37 | BG19: 5.67 | BH19: 5.8 | BI19: 6.06 | BJ19: 5.56 | BK19: 4.93 | BL19: 4.56 | BM19: 5.2 | BN19: 6.46 | BO19: 4.99
A20: Azerbaijan | B20: AZE | C20: Unemployment, total (% of total labor force) (modeled ILO estimate) | D20: SL.UEM.TOTL.ZS | AJ20: 0.9 | AK20: 1.8 | AL20: 4.5 | AM20: 6.3 | AN20: 7.2 | AO20: 8.1 | AP20: 9.1 | AQ20: 10 | AR20: 10.9 | AS20: 11.78 | AT20: 10.91 | AU20: 10.04 | AV20: 9.17 | AW20: 7.99 | AX20: 7.26 | AY20: 6.62 | AZ20: 6.33 | BA20: 5.86 | BB20: 5.74 | BC20: 5.63 | BD20: 5.42 | BE20: 5.19 | BF20: 4.97 | BG20: 4.91 | BH20: 4.96 | BI20: 5 | BJ20: 5 | BK20: 4.9 | BL20: 5 | BM20: 7.24 | BN20: 6.04 | BO20: 5.65
A21: Burundi | B21: BDI | C21: Unemployment, total (% of total labor force) (modeled ILO estimate) | D21: SL.UEM.TOTL.ZS | AJ21: 3.195 | AK21: 3.252 | AL21: 3.381 | AM21: 3.347 | AN21: 3.391 | AO21: 3.399 | AP21: 3.307 | AQ21: 3.212 | AR21: 3.29 | AS21: 3.285 | AT21: 3.239 | AU21: 3.202 | AV21: 3.281 | AW21: 3.19 | AX21: 3.244 | AY21: 3.18 | AZ21: 2.424 | BA21: 1.63 | BB21: 1.625 | BC21: 1.604 | BD21: 1.602 | BE21: 1.589 | BF21: 1.575 | BG21: 1.57 | BH21: 1.517 | BI21: 1.383 | BJ21: 1.263 | BK21: 1.143 | BL21: 1.027 | BM21: 1.03 | BN21: 1.138 | BO21: 0.906
A22: Belgium | B22: BEL | C22: Unemployment, total (% of total labor force) (modeled ILO estimate) | D22: SL.UEM.TOTL.ZS | AJ22: 6.98 | AK22: 6.7 | AL22: 8.08 | AM22: 9.65 | AN22: 9.34 | AO22: 9.48 | AP22: 8.95 | AQ22: 9.32 | AR22: 8.65 | AS22: 6.59 | AT22: 6.18 | AU22: 6.91 | AV22: 7.68 | AW22: 7.36 | AX22: 8.44 | AY22: 8.25 | AZ22: 7.46 | BA22: 6.98 | BB22: 7.91 | BC22: 8.29 | BD22: 7.14 | BE22: 7.54 | BF22: 8.43 | BG22: 8.52 | BH22: 8.48 | BI22: 7.83 | BJ22: 7.09 | BK22: 5.95 | BL22: 5.36 | BM22: 5.55 | BN22: 6.26 | BO22: 5.56
A23: Benin | B23: BEN | C23: Unemployment, total (% of total labor force) (modeled ILO estimate) | D23: SL.UEM.TOTL.ZS | AJ23: 1.691 | AK23: 1.51 | AL23: 1.517 | AM23: 1.495 | AN23: 1.32 | AO23: 1.273 | AP23: 1.1 | AQ23: 1.06 | AR23: 0.955 | AS23: 0.868 | AT23: 0.763 | AU23: 0.69 | AV23: 0.752 | AW23: 0.796 | AX23: 0.877 | AY23: 0.898 | AZ23: 0.9 | BA23: 0.872 | BB23: 0.93 | BC23: 1.04 | BD23: 2.65 | BE23: 2.392 | BF23: 2.044 | BG23: 1.808 | BH23: 1.811 | BI23: 1.843 | BJ23: 1.749 | BK23: 1.47 | BL23: 1.372 | BM23: 1.616 | BN23: 1.784 | BO23: 1.476
A24: Burkina Faso | B24: BFA | C24: Unemployment, total (% of total labor force) (modeled ILO estimate) | D24: SL.UEM.TOTL.ZS | AJ24: 2.431 | AK24: 2.481 | AL24: 2.38 | AM24: 2.58 | AN24: 2.53 | AO24: 2.428 | AP24: 2.394 | AQ24: 2.44 | AR24: 2.565 | AS24: 2.721 | AT24: 2.78 | AU24: 2.91 | AV24: 2.78 | AW24: 3.508 | AX24: 4 | AY24: 3.676 | AZ24: 3.3 | BA24: 3.525 | BB24: 3.779 | BC24: 3.741 | BD24: 3.836 | BE24: 3.825 | BF24: 4.054 | BG24: 4.28 | BH24: 4.526 | BI24: 4.651 | BJ24: 4.691 | BK24: 4.69 | BL24: 4.708 | BM24: 5.148 | BN24: 5.36 | BO24: 5.065
A25: Bangladesh | B25: BGD | C25: Unemployment, total (% of total labor force) (modeled ILO estimate) | D25: SL.UEM.TOTL.ZS | AJ25: 2.2 | AK25: 2.26 | AL25: 2.323 | AM25: 2.385 | AN25: 2.448 | AO25: 2.51 | AP25: 2.7 | AQ25: 2.89 | AR25: 3.081 | AS25: 3.27 | AT25: 3.617 | AU25: 3.968 | AV25: 4.32 | AW25: 4.288 | AX25: 4.25 | AY25: 3.59 | AZ25: 4.055 | BA25: 4.525 | BB25: 5 | BC25: 3.38 | BD25: 3.73 | BE25: 4.079 | BF25: 4.43 | BG25: 4.405 | BH25: 4.379 | BI25: 4.35 | BJ25: 4.37 | BK25: 4.373 | BL25: 4.376 | BM25: 5.316 | BN25: 5.246 | BO25: 4.271
A26: Bulgaria | B26: BGR | C26: Unemployment, total (% of total labor force) (modeled ILO estimate) | D26: SL.UEM.TOTL.ZS | AJ26: 11.1 | AK26: 15.3 | AL26: 16.4 | AM26: 12.8 | AN26: 11.1 | AO26: 12.5 | AP26: 13.7 | AQ26: 12.2 | AR26: 14.1 | AS26: 16.22 | AT26: 19.92 | AU26: 18.11 | AV26: 13.73 | AW26: 12.04 | AX26: 10.08 | AY26: 8.95 | AZ26: 6.88 | BA26: 5.61 | BB26: 6.82 | BC26: 10.28 | BD26: 11.26 | BE26: 12.27 | BF26: 12.94 | BG26: 11.42 | BH26: 9.14 | BI26: 7.57 | BJ26: 6.16 | BK26: 5.21 | BL26: 4.23 | BM26: 5.12 | BN26: 5.27 | BO26: 4.27
A27: Bahrain | B27: BHR | C27: Unemployment, total (% of total labor force) (modeled ILO estimate) | D27: SL.UEM.TOTL.ZS | AJ27: 1.144 | AK27: 1.059 | AL27: 0.963 | AM27: 1.094 | AN27: 1.129 | AO27: 1.258 | AP27: 1.202 | AQ27: 1.186 | AR27: 1.18 | AS27: 1.145 | AT27: 1.176 | AU27: 1.187 | AV27: 1.169 | AW27: 1.101 | AX27: 1.052 | AY27: 1.046 | AZ27: 1.027 | BA27: 1.03 | BB27: 1.077 | BC27: 1.13 | BD27: 1.207 | BE27: 1.2 | BF27: 1.182 | BG27: 1.147 | BH27: 1.166 | BI27: 1.193 | BJ27: 1.192 | BK27: 1.198 | BL27: 1.22 | BM27: 1.786 | BN27: 1.548 | BO27: 1.339
A28: Bahamas, The | B28: BHS | C28: Unemployment, total (% of total labor force) (modeled ILO estimate) | D28: SL.UEM.TOTL.ZS | AJ28: 12.17 | AK28: 14.81 | AL28: 12.72 | AM28: 13.83 | AN28: 10.83 | AO28: 11.46 | AP28: 9.76 | AQ28: 7.65 | AR28: 7.45 | AS28: 7.238 | AT28: 6.87 | AU28: 9.05 | AV28: 10.84 | AW28: 10.2 | AX28: 10.2 | AY28: 7.54 | AZ28: 7.88 | BA28: 8.18 | BB28: 14.25 | BC28: 14.433 | BD28: 14.52 | BE28: 14.02 | BF28: 16.18 | BG28: 13.8 | BH28: 12 | BI28: 12.7 | BJ28: 9.8 | BK28: 10 | BL28: 9.933 | BM28: 12.563 | BN28: 11.579 | BO28: 10.089
A29: Bosnia and Herzegovina | B29: BIH | C29: Unemployment, total (% of total labor force) (modeled ILO estimate) | D29: SL.UEM.TOTL.ZS | AJ29: 17.55 | AK29: 18.511 | AL29: 19.451 | AM29: 20.289 | AN29: 21.066 | AO29: 21.838 | AP29: 22.699 | AQ29: 23.596 | AR29: 24.554 | AS29: 25.483 | AT29: 26.489 | AU29: 27.432 | AV29: 28.416 | AW29: 29.293 | AX29: 30.213 | AY29: 31.11 | AZ29: 28.98 | BA29: 23.41 | BB29: 24.07 | BC29: 27.31 | BD29: 27.58 | BE29: 28.01 | BF29: 27.49 | BG29: 27.52 | BH29: 27.69 | BI29: 25.41 | BJ29: 20.53 | BK29: 18.4 | BL29: 15.69 | BM29: 15.87 | BN29: 14.9 | BO29: 12.66
... A31: Belize | B31: BLZ | C31: Unemployment, total (% of total labor force) (modeled ILO estimate) | D31: SL.UEM.TOTL.ZS | AJ31: 9.643 | AK31: 9.659 | AL31: 9.78 | AM31: 11.1 | AN31: 12.48 | AO31: 13.82 | AP31: 12.68 | AQ31: 14.31 | AR31: 12.84 | AS31: 10.808 | AT31: 9.07 | AU31: 10.04 | AV31: 10.363 | AW31: 10.601 | AX31: 10.91 | AY31: 9.39 | AZ31: 8.51 | BA31: 8.18 | BB31: 8.335 | BC31: 8.424 | BD31: 8.435 | BE31: 8.38 | BF31: 8.35 | BG31: 8.24 | BH31: 7.58 | BI31: 7 | BJ31: 6.6 | BK31: 7.899 | BL31: 9.05 | BM31: 10.619 | BN31: 10.16 | BO31: 8.672
A32: Bermuda | B32: BMU | C32: Unemployment, total (% of total labor force) (modeled ILO estimate) | D32: SL.UEM.TOTL.ZS
A33: Bolivia | B33: BOL | C33: Unemployment, total (% of total labor force) (modeled ILO estimate) | D33: SL.UEM.TOTL.ZS | AJ33: 2.934 | AK33: 3.032 | AL33: 3.051 | AM33: 3.08 | AN33: 2.665 | AO33: 2.375 | AP33: 2.08 | AQ33: 2.122 | AR33: 2.299 | AS33: 2.439 | AT33: 2.622 | AU33: 2.603 | AV33: 2.653 | AW33: 2.615 | AX33: 2.597 | AY33: 2.574 | AZ33: 2.612 | BA33: 2.6 | BB33: 2.97 | BC33: 2.604 | BD33: 2.25 | BE33: 2.07 | BF33: 2.44 | BG33: 2.02 | BH33: 3.11 | BI33: 3.5 | BJ33: 3.65 | BK33: 3.52 | BL33: 3.68 | BM33: 7.9 | BN33: 5.09 | BO33: 3.552
A34: Brazil | B34: BRA | C34: Unemployment, total (% of total labor force) (modeled ILO estimate) | D34: SL.UEM.TOTL.ZS | AJ34: 6.254 | AK34: 6.42 | AL34: 6.03 | AM34: 6.577 | AN34: 7.09 | AO34: 8.03 | AP34: 9 | AQ34: 10.15 | AR34: 11.13 | AS34: 10.894 | AT34: 10.65 | AU34: 10.64 | AV34: 11.17 | AW34: 10.07 | AX34: 10.55 | AY34: 9.69 | AZ34: 9.28 | BA34: 8.27 | BB34: 9.42 | BC34: 8.426 | BD34: 7.58 | BE34: 7.25 | BF34: 7.07 | BG34: 6.76 | BH34: 8.54 | BI34: 11.58 | BJ34: 12.79 | BK34: 12.33 | BL34: 11.94 | BM34: 13.7 | BN34: 13.16 | BO34: 9.23
A35: Barbados | B35: BRB | C35: Unemployment, total (% of total labor force) (modeled ILO estimate) | D35: SL.UEM.TOTL.ZS | AJ35: 22.318 | AK35: 22.94 | AL35: 24.54 | AM35: 22.98 | AN35: 19.66 | AO35: 14.71 | AP35: 14.61 | AQ35: 12.4 | AR35: 10.61 | AS35: 9.35 | AT35: 9.85 | AU35: 10.32 | AV35: 11 | AW35: 9.57 | AX35: 9.08 | AY35: 8.73 | AZ35: 7.41 | BA35: 8.12 | BB35: 10.02 | BC35: 10.69 | BD35: 11.19 | BE35: 11.59 | BF35: 11.55 | BG35: 12.17 | BH35: 9.8 | BI35: 8.25 | BJ35: 8.62 | BK35: 8.32 | BL35: 8.41 | BM35: 9.743 | BN35: 9.479 | BO35: 8.501
A36: Brunei Darussalam | B36: BRN | C36: Unemployment, total (% of total labor force) (modeled ILO estimate) | D36: SL.UEM.TOTL.ZS | AJ36: 4.7 | AK36: 4.792 | AL36: 4.889 | AM36: 4.985 | AN36: 5.081 | AO36: 5.174 | AP36: 5.273 | AQ36: 5.371 | AR36: 5.465 | AS36: 5.554 | AT36: 5.643 | AU36: 5.734 | AV36: 5.826 | AW36: 5.92 | AX36: 6.015 | AY36: 6.106 | AZ36: 6.198 | BA36: 6.293 | BB36: 6.393 | BC36: 6.483 | BD36: 6.569 | BE36: 6.66 | BF36: 6.759 | BG36: 6.86 | BH36: 7.683 | BI36: 8.505 | BJ36: 9.32 | BK36: 8.7 | BL36: 6.6 | BM36: 7.41 | BN36: 4.91 | BO36: 4.452
A37: Bhutan | B37: BTN | C37: Unemployment, total (% of total labor force) (modeled ILO estimate) | D37: SL.UEM.TOTL.ZS | AJ37: 1.382 | AK37: 1.385 | AL37: 1.39 | AM37: 1.391 | AN37: 1.393 | AO37: 1.395 | AP37: 1.397 | AQ37: 1.4 | AR37: 1.4 | AS37: 1.65 | AT37: 1.9 | AU37: 1.85 | AV37: 1.8 | AW37: 2.49 | AX37: 3.1 | AY37: 3.13 | AZ37: 3.7 | BA37: 3.831 | BB37: 3.96 | BC37: 3.32 | BD37: 3.23 | BE37: 2.05 | BF37: 2.87 | BG37: 2.63 | BH37: 2.45 | BI37: 2.747 | BJ37: 3.048 | BK37: 3.35 | BL37: 2.72 | BM37: 5.03 | BN37: 4.8 | BO37: 5.95
A38: Botswana | B38: BWA | C38: Unemployment, total (% of total labor force) (modeled ILO estimate) | D38: SL.UEM.TOTL.ZS | AJ38: 13.82 | AK38: 16.35 | AL38: 18.772 | AM38: 21.2 | AN38: 21.393 | AO38: 21.59 | AP38: 20.976 | AQ38: 20.86 | AR38: 18.182 | AS38: 15.88 | AT38: 18.54 | AU38: 21.308 | AV38: 23.8 | AW38: 21.739 | AX38: 19.865 | AY38: 17.78 | AZ38: 16.901 | BA38: 16.18 | BB38: 16.17 | BC38: 17.86 | BD38: 18.039 | BE38: 17.803 | BF38: 18.059 | BG38: 18.397 | BH38: 18.878 | BI38: 19.336 | BJ38: 19.702 | BK38: 19.618 | BL38: 20.09 | BM38: 21.02 | BN38: 23.11 | BO38: 23.62
A39: Central African Republic | B39: CAF | C39: Unemployment, total (% of total labor force) (modeled ILO estimate) | D39: SL.UEM.TOTL.ZS | AJ39: 5.73 | AK39: 5.859 | AL39: 5.926 | AM39: 5.953 | AN39: 5.877 | AO39: 5.82 | AP39: 5.746 | AQ39: 5.72 | AR39: 5.719 | AS39: 5.675 | AT39: 5.713 | AU39: 5.745 | AV39: 5.766 | AW39: 5.704 | AX39: 5.684 | AY39: 5.623 | AZ39: 5.584 | BA39: 5.537 | BB39: 5.644 | BC39: 5.759 | BD39: 5.732 | BE39: 5.682 | BF39: 5.72 | BG39: 5.833 | BH39: 6.011 | BI39: 6.061 | BJ39: 6.108 | BK39: 6.02 | BL39: 6.079 | BM39: 6.66 | BN39: 6.812 | BO39: 6.341
A40: Canada | B40: CAN | C40: Unemployment, total (% of total labor force) (modeled ILO estimate) | D40: SL.UEM.TOTL.ZS | AJ40: 10.32 | AK40: 11.2 | AL40: 11.38 | AM40: 10.4 | AN40: 9.49 | AO40: 9.62 | AP40: 9.1 | AQ40: 8.28 | AR40: 7.58 | AS40: 6.83 | AT40: 7.22 | AU40: 7.66 | AV40: 7.57 | AW40: 7.19 | AX40: 6.76 | AY40: 6.48 | AZ40: 6.16 | BA40: 6.28 | BB40: 8.46 | BC40: 8.18 | BD40: 7.64 | BE40: 7.39 | BF40: 7.14 | BG40: 7.02 | BH40: 6.95 | BI40: 7.04 | BJ40: 6.43 | BK40: 5.84 | BL40: 5.69 | BM40: 9.66 | BN40: 7.53 | BO40: 5.28
A41: Central Europe and the Baltics | B41: CEB | C41: Unemployment, total (% of total labor force) (modeled ILO estimate) | D41: SL.UEM.TOTL.ZS | AJ41: 9.5266724 | AK41: 10.136854 | AL41: 11.395204 | AM41: 11.24423 | AN41: 10.720347 | AO41: 10.080436 | AP41: 9.2129477 | AQ41: 9.0189667 | AR41: 10.417796 | AS41: 12.412203 | AT41: 13.234583 | AU41: 13.759916 | AV41: 13.00498 | AW41: 12.926342 | AX41: 12.061768 | AY41: 10.104908 | AZ41: 7.8115847 | BA41: 6.6081466 | BB41: 8.4877348 | BC41: 9.8998958 | BD41: 9.7892991 | BE41: 9.9797136 | BF41: 10.050961 | BG41: 8.8650158 | BH41: 7.8191091 | BI41: 6.4902577 | BJ41: 5.2979679 | BK41: 4.3174609 | BL41: 3.7815313 | BM41: 4.3700959 | BN41: 4.4854401 | BO41: 4.0070304
A42: Switzerland | B42: CHE | C42: Unemployment, total (% of total labor force) (modeled ILO estimate) | D42: SL.UEM.TOTL.ZS | AJ42: 1.82 | AK42: 2.34 | AL42: 3.55 | AM42: 3.58 | AN42: 3.09 | AO42: 3.68 | AP42: 4.13 | AQ42: 3.57 | AR42: 3.05 | AS42: 2.66 | AT42: 2.49 | AU42: 2.92 | AV42: 4.12 | AW42: 4.32 | AX42: 4.44 | AY42: 3.99 | AZ42: 3.64 | BA42: 3.35 | BB42: 4.11 | BC42: 4.81 | BD42: 4.41 | BE42: 4.49 | BF42: 4.75 | BG42: 4.83 | BH42: 4.8 | BI42: 4.92 | BJ42: 4.8 | BK42: 4.71 | BL42: 4.39 | BM42: 4.82 | BN42: 5.1 | BO42: 4.3
A43: Channel Islands | B43: CHI | C43: Unemployment, total (% of total labor force) (modeled ILO estimate) | D43: SL.UEM.TOTL.ZS | AJ43: 5.681 | AK43: 6.121 | AL43: 7.073 | AM43: 7.251 | AN43: 6.999 | AO43: 6.928 | AP43: 6.72 | AQ43: 6.316 | AR43: 5.949 | AS43: 5.391 | AT43: 5.082 | AU43: 5.351 | AV43: 5.678 | AW43: 5.876 | AX43: 5.806 | AY43: 5.511 | AZ43: 5.209 | BA43: 5.277 | BB43: 6.622 | BC43: 6.969 | BD43: 7.206 | BE43: 8.01 | BF43: 8.557 | BG43: 8.354 | BH43: 7.973 | BI43: 7.522 | BJ43: 6.949 | BK43: 6.415 | BL43: 6.267 | BM43: 6.718 | BN43: 6.727 | BO43: 6.033
A44: Chile | B44: CHL | C44: Unemployment, total (% of total labor force) (modeled ILO estimate) | D44: SL.UEM.TOTL.ZS | AJ44: 5.23 | AK44: 4.35 | AL44: 4.49 | AM44: 5.87 | AN44: 4.7 | AO44: 7.41 | AP44: 7.14 | AQ44: 7.31 | AR44: 11.16 | AS44: 10.49 | AT44: 10.39 | AU44: 10.17 | AV44: 9.77 | AW44: 10.16 | AX44: 9.34 | AY44: 9.02 | AZ44: 8.43 | BA44: 9.29 | BB44: 11.31 | BC44: 8.41 | BD44: 7.32 | BE44: 6.64 | BF44: 6.2 | BG44: 6.65 | BH44: 6.49 | BI44: 6.73 | BJ44: 6.95 | BK44: 7.21 | BL44: 7.27 | BM44: 10.94 | BN44: 9.28 | BO44: 8.25
... A55: Cuba | B55: CUB | C55: Unemployment, total (% of total labor force) (modeled ILO estimate) | D55: SL.UEM.TOTL.ZS | AJ55: 8.321 | AK55: 8.793 | AL55: 9.283 | AM55: 8.812 | AN55: 8.27 | AO55: 7.61 | AP55: 7.1 | AQ55: 6.23 | AR55: 6.26 | AS55: 5.45 | AT55: 4.08 | AU55: 3.31 | AV55: 2.33 | AW55: 1.85 | AX55: 1.95 | AY55: 1.91 | AZ55: 1.79 | BA55: 1.58 | BB55: 1.67 | BC55: 2.5 | BD55: 3.18 | BE55: 3.46 | BF55: 3.29 | BG55: 2.7 | BH55: 2.4 | BI55: 2 | BJ55: 1.7 | BK55: 1.7 | BL55: 1.2 | BM55: 1.4 | BN55: 1.388 | BO55: 1.254
A56: Curacao | B56: CUW | C56: Unemployment, total (% of total labor force) (modeled ILO estimate) | D56: SL.UEM.TOTL.ZS
A57: Cayman Islands | B57: CYM | C57: Unemployment, total (% of total labor force) (modeled ILO estimate) | D57: SL.UEM.TOTL.ZS
A58: Cyprus | B58: CYP | C58: Unemployment, total (% of total labor force) (modeled ILO estimate) | D58: SL.UEM.TOTL.ZS | AJ58: 3 | AK58: 2.09 | AL58: 2.7 | AM58: 2.7 | AN58: 2.6 | AO58: 3.1 | AP58: 3.4 | AQ58: 3.3 | AR58: 5.53 | AS58: 4.77 | AT58: 4.04 | AU58: 3.34 | AV58: 4.15 | AW58: 4.77 | AX58: 5.48 | AY58: 4.59 | AZ58: 3.95 | BA58: 3.76 | BB58: 5.59 | BC58: 6.36 | BD58: 7.94 | BE58: 12.1 | BF58: 16.13 | BG58: 16.28 | BH58: 15.03 | BI58: 13.01 | BJ58: 11.16 | BK58: 8.5 | BL58: 7.15 | BM58: 7.76 | BN58: 7.51 | BO58: 6.78
A59: Czechia | B59: CZE | C59: Unemployment, total (% of total labor force) (modeled ILO estimate) | D59: SL.UEM.TOTL.ZS | AJ59: 2.27 | AK59: 2.6 | AL59: 4.32 | AM59: 4.3 | AN59: 4.02 | AO59: 3.89 | AP59: 4.79 | AQ59: 6.45 | AR59: 8.7 | AS59: 8.76 | AT59: 8.13 | AU59: 7.28 | AV59: 7.78 | AW59: 8.3 | AX59: 7.93 | AY59: 7.14 | AZ59: 5.32 | BA59: 4.39 | BB59: 6.66 | BC59: 7.28 | BD59: 6.71 | BE59: 6.98 | BF59: 6.95 | BG59: 6.11 | BH59: 5.05 | BI59: 3.95 | BJ59: 2.89 | BK59: 2.25 | BL59: 2.02 | BM59: 2.55 | BN59: 2.8 | BO59: 2.22
A60: Germany | B60: DEU | C60: Unemployment, total (% of total labor force) (modeled ILO estimate) | D60: SL.UEM.TOTL.ZS | AJ60: 5.32 | AK60: 6.32 | AL60: 7.68 | AM60: 8.73 | AN60: 8.16 | AO60: 8.82 | AP60: 9.86 | AQ60: 9.79 | AR60: 8.85 | AS60: 7.92 | AT60: 7.77 | AU60: 8.48 | AV60: 9.78 | AW60: 10.73 | AX60: 11.17 | AY60: 10.25 | AZ60: 8.66 | BA60: 7.52 | BB60: 7.74 | BC60: 6.97 | BD60: 5.82 | BE60: 5.38 | BF60: 5.23 | BG60: 4.98 | BH60: 4.62 | BI60: 4.12 | BJ60: 3.75 | BK60: 3.38 | BL60: 3.14 | BM60: 3.86 | BN60: 3.64 | BO60: 3.14
A61: Djibouti | B61: DJI | C61: Unemployment, total (% of total labor force) (modeled ILO estimate) | D61: SL.UEM.TOTL.ZS | AJ61: 27.481 | AK61: 27.274 | AL61: 28.08 | AM61: 27.957 | AN61: 28.217 | AO61: 28.011 | AP61: 27.99 | AQ61: 27.743 | AR61: 27.307 | AS61: 27.176 | AT61: 27.063 | AU61: 27.036 | AV61: 26.876 | AW61: 26.812 | AX61: 26.815 | AY61: 26.707 | AZ61: 26.562 | BA61: 26.391 | BB61: 26.578 | BC61: 26.624 | BD61: 26.526 | BE61: 26.324 | BF61: 26.266 | BG61: 26.273 | BH61: 26.105 | BI61: 25.972 | BJ61: 26.06 | BK61: 26.218 | BL61: 26.307 | BM61: 27.848 | BN61: 27.963 | BO61: 26.666
A62: Dominica | B62: DMA | C62: Unemployment, total (% of total labor force) (modeled ILO estimate) | D62: SL.UEM.TOTL.ZS
A63: Denmark | B63: DNK | C63: Unemployment, total (% of total labor force) (modeled ILO estimate) | D63: SL.UEM.TOTL.ZS | AJ63: 9.1 | AK63: 9.03 | AL63: 10.72 | AM63: 8.04 | AN63: 6.99 | AO63: 6.84 | AP63: 5.4 | AQ63: 5.04 | AR63: 5.14 | AS63: 4.48 | AT63: 4.16 | AU63: 4.27 | AV63: 5.4 | AW63: 5.2 | AX63: 4.83 | AY63: 3.9 | AZ63: 3.8 | BA63: 3.68 | BB63: 6.41 | BC63: 7.75 | BD63: 7.77 | BE63: 7.8 | BF63: 7.38 | BG63: 6.93 | BH63: 6.28 | BI63: 5.99 | BJ63: 5.83 | BK63: 5.13 | BL63: 5.02 | BM63: 5.64 | BN63: 5.04 | BO63: 4.43
A64: Dominican Republic | B64: DOM | C64: Unemployment, total (% of total labor force) (modeled ILO estimate) | D64: SL.UEM.TOTL.ZS | AJ64: 6.904 | AK64: 6.693 | AL64: 6.323 | AM64: 6.282 | AN64: 6.444 | AO64: 6.491 | AP64: 6.32 | AQ64: 6.298 | AR64: 6.305 | AS64: 6.43 | AT64: 7.26 | AU64: 6.78 | AV64: 6.94 | AW64: 6.3 | AX64: 6.59 | AY64: 5.65 | AZ64: 5.16 | BA64: 4.76 | BB64: 5.47 | BC64: 5.21 | BD64: 6.09 | BE64: 6.72 | BF64: 7.35 | BG64: 6.72 | BH64: 7.61 | BI64: 7.28 | BJ64: 5.83 | BK64: 5.86 | BL64: 6.18 | BM64: 6.13 | BN64: 7.7 | BO64: 5.504
A65: Algeria | B65: DZA | C65: Unemployment, total (% of total labor force) (modeled ILO estimate) | D65: SL.UEM.TOTL.ZS | AJ65: 20.6 | AK65: 24.38 | AL65: 26.23 | AM65: 27.74 | AN65: 31.84 | AO65: 28.32 | AP65: 25.43 | AQ65: 26.856 | AR65: 28.542 | AS65: 29.77 | AT65: 27.3 | AU65: 25.9 | AV65: 23.72 | AW65: 17.65 | AX65: 15.27 | AY65: 12.27 | AZ65: 13.79 | BA65: 11.33 | BB65: 10.16 | BC65: 9.96 | BD65: 9.96 | BE65: 10.97 | BF65: 9.82 | BG65: 10.21 | BH65: 11.21 | BI65: 10.2 | BJ65: 12 | BK65: 12.145 | BL65: 12.275 | BM65: 14.036 | BN65: 13.729 | BO65: 12.491
A66: East Asia & Pacific (excluding high income) | B66: EAP | C66: Unemployment, total (% of total labor force) (modeled ILO estimate) | D66: SL.UEM.TOTL.ZS | AJ66: 2.4086869 | AK66: 2.3762666 | AL66: 2.6265117 | AM66: 2.9228306 | AN66: 3.005432 | AO66: 3.1099111 | AP66: 3.2022542 | AQ66: 3.3686991 | AR66: 3.4605473 | AS66: 3.4167263 | AT66: 3.8422292 | AU66: 4.1581836 | AV66: 4.4083309 | AW66: 4.4005534 | AX66: 4.4774888 | AY66: 4.3716725 | AZ66: 4.3512774 | BA66: 4.4349808 | BB66: 4.4205417 | BC66: 4.1584468 | BD66: 4.1096987 | BE66: 4.0494344 | BF66: 4.050905 | BG66: 4.0470057 | BH66: 4.1212178 | BI66: 4.0391316 | BJ66: 3.9171341 | BK66: 3.8108075 | BL66: 3.896865 | BM66: 4.3737331 | BN66: 4.1283669 | BO66: 4.2374005
A67: Early-demographic dividend | B67: EAR | C67: Unemployment, total (% of total labor force) (modeled ILO estimate) | D67: SL.UEM.TOTL.ZS | AJ67: 5.8603166 | AK67: 5.9259573 | AL67: 6.0888735 | AM67: 6.3678509 | AN67: 6.7291853 | AO67: 6.6738193 | AP67: 6.6095973 | AQ67: 6.7872237 | AR67: 7.0638606 | AS67: 7.1437136 | AT67: 7.2894633 | AU67: 7.5681464 | AV67: 7.5619278 | AW67: 7.531055 | AX67: 7.538829 | AY67: 7.2447941 | AZ67: 7.1536398 | BA67: 7.0434224 | BB67: 7.1249794 | BC67: 6.9421704 | BD67: 6.8054232 | BE67: 6.8461668 | BF67: 6.7814681 | BG67: 6.7118323 | BH67: 6.8590602 | BI67: 6.7669005 | BJ67: 6.6898525 | BK67: 6.7003494 | BL67: 6.2272121 | BM67: 7.2643585 | BN67: 6.6479446 | BO67: 5.5492451
A68: East Asia & Pacific | B68: EAS | C68: Unemployment, total (% of total labor force) (modeled ILO estimate) | D68: SL.UEM.TOTL.ZS | AJ68: 2.4636997 | AK68: 2.4550392 | AL68: 2.7118483 | AM68: 2.9802362 | AN68: 3.0533639 | AO68: 3.1612521 | AP68: 3.2505278 | AQ68: 3.5396614 | AR68: 3.6465768 | AS68: 3.5507794 | AT68: 3.945893 | AU68: 4.2453904 | AV68: 4.4659807 | AW68: 4.4193768 | AX68: 4.4664486 | AY68: 4.3440749 | AZ68: 4.2958014 | BA68: 4.3751429 | BB68: 4.4569342 | BC68: 4.2101464 | BD68: 4.1235174 | BE68: 4.0556044 | BF68: 4.0410179 | BG68: 4.0226708 | BH68: 4.0898243 | BI68: 4.0006938 | BJ68: 3.8709935 | BK68: 3.7524884 | BL68: 3.818124 | BM68: 4.3052469 | BN68: 4.0616679 | BO68: 4.1069462
A69: Europe & Central Asia (excluding high income) | B69: ECA | C69: Unemployment, total (% of total labor force) (modeled ILO estimate) | D69: SL.UEM.TOTL.ZS | AJ69: 4.8843905 | AK69: 5.3843204 | AL69: 6.0747088 | AM69: 7.6797275 | AN69: 8.992784 | AO69: 9.9076259 | AP69: 10.953654 | AQ69: 12.060522 | AR69: 12.239532 | AS69: 10.857206 | AT69: 10.196868 | AU69: 9.6858898 | AV69: 9.5198904 | AW69: 9.1900455 | AX69: 8.5808376 | AY69: 8.0649213 | AZ69: 7.2826586 | BA69: 7.2732734 | BB69: 9.0025285 | BC69: 8.3587919 | BD69: 7.705407 | BE69: 7.109038 | BF69: 7.131711 | BG69: 7.3585466 | BH69: 7.4852528 | BI69: 7.506351 | BJ69: 7.2935257 | BK69: 6.9461383 | BL69: 7.0871814 | BM69: 7.6235132 | BN69: 7.1348764 | BO69: 5.8819316
A70: Europe & Central Asia | B70: ECS | C70: Unemployment, total (% of total labor force) (modeled ILO estimate) | D70: SL.UEM.TOTL.ZS | AJ70: 6.9105679 | AK70: 7.4988627 | AL70: 8.6277001 | AM70: 9.6277286 | AN70: 9.9068304 | AO70: 10.25034 | AP70: 10.503902 | AQ70: 10.690073 | AR70: 10.592493 | AS70: 9.7694794 | AT70: 9.0840849 | AU70: 9.0948225 | AV70: 9.1142436 | AW70: 9.0877849 | AX70: 8.7357057 | AY70: 8.0863261 | AZ70: 7.1704855 | BA70: 7.0756273 | BB70: 8.9064863 | BC70: 8.9806579 | BD70: 8.7280958 | BE70: 8.9439199 | BF70: 9.1468273 | BG70: 8.8932061 | BH70: 8.5054234 | BI70: 8.0374538 | BJ70: 7.431477 | BK70: 6.8336888 | BL70: 6.5889491 | BM70: 7.0511257 | BN70: 6.8719531 | BO70: 5.8210944
A71: Ecuador | B71: ECU | C71: Unemployment, total (% of total labor force) (modeled ILO estimate) | D71: SL.UEM.TOTL.ZS | AJ71: 4.354 | AK71: 4.311 | AL71: 4.384 | AM71: 4.389 | AN71: 4.386 | AO71: 4.399 | AP71: 4.398 | AQ71: 4.358 | AR71: 4.645 | AS71: 4.8 | AT71: 4.25 | AU71: 4.824 | AV71: 5.66 | AW71: 5 | AX71: 3.78 | AY71: 3.55 | AZ71: 3.14 | BA71: 3.92 | BB71: 4.61 | BC71: 4.09 | BD71: 3.46 | BE71: 3.23 | BF71: 3.08 | BG71: 3.48 | BH71: 3.62 | BI71: 4.6 | BJ71: 3.84 | BK71: 3.53 | BL71: 3.81 | BM71: 6.13 | BN71: 4.55 | BO71: 3.76
A72: Egypt, Arab Rep. | B72: EGY | C72: Unemployment, total (% of total labor force) (modeled ILO estimate) | D72: SL.UEM.TOTL.ZS | AJ72: 9.38 | AK72: 8.92 | AL72: 10.92 | AM72: 10.93 | AN72: 11.04 | AO72: 9 | AP72: 8.37 | AQ72: 8.03 | AR72: 7.95 | AS72: 8.98 | AT72: 9.26 | AU72: 10.01 | AV72: 10.91 | AW72: 10.32 | AX72: 11.05 | AY72: 10.49 | AZ72: 8.8 | BA72: 8.52 | BB72: 9.09 | BC72: 8.76 | BD72: 11.85 | BE72: 12.6 | BF72: 13.15 | BG72: 13.1 | BH72: 13.05 | BI72: 12.45 | BJ72: 11.77 | BK72: 9.86 | BL72: 7.85 | BM72: 7.97 | BN72: 7.44 | BO72: 6.397
A73: Euro area | B73: EMU | C73: Unemployment, total (% of total labor force) (modeled ILO estimate) | D73: SL.UEM.TOTL.ZS | AJ73: 8.2823758 | AK73: 8.9224587 | AL73: 10.719893 | AM73: 11.789279 | AN73: 11.470294 | AO73: 11.687464 | AP73: 11.688514 | AQ73: 11.241599 | AR73: 10.448837 | AS73: 9.4199288 | AT73: 8.3557926 | AU73: 8.6221863 | AV73: 8.9732968 | AW73: 9.2450932 | AX73: 9.0943157 | AY73: 8.3802695 | AZ73: 7.4988195 | BA73: 7.5402306 | BB73: 9.6045477 | BC73: 10.140241 | BD73: 10.182561 | BE73: 11.366318 | BF73: 11.913953 | BG73: 11.559826 | BH73: 10.826992 | BI73: 9.9950181 | BJ73: 9.0297257 | BK73: 8.1534998 | BL73: 7.5141703 | BM73: 7.8264185 | BN73: 7.7294515 | BO73: 6.7455619
A74: Eritrea | B74: ERI | C74: Unemployment, total (% of total labor force) (modeled ILO estimate) | D74: SL.UEM.TOTL.ZS | AJ74: 5.572 | AK74: 5.749 | AL74: 5.824 | AM74: 5.874 | AN74: 5.702 | AO74: 5.603 | AP74: 5.685 | AQ74: 5.794 | AR74: 5.904 | AS74: 5.954 | AT74: 6.009 | AU74: 6.034 | AV74: 6.013 | AW74: 5.906 | AX74: 5.933 | AY74: 5.941 | AZ74: 5.958 | BA74: 5.908 | BB74: 5.997 | BC74: 6.105 | BD74: 6.023 | BE74: 5.889 | BF74: 5.839 | BG74: 5.862 | BH74: 5.991 | BI74: 6.044 | BJ74: 6.073 | BK74: 5.931 | BL74: 5.934 | BM74: 6.453 | BN74: 6.511 | BO74: 5.974
... A82: France | B82: FRA | C82: Unemployment, total (% of total labor force) (modeled ILO estimate) | D82: SL.UEM.TOTL.ZS | AJ82: 9.13 | AK82: 10.2 | AL82: 11.32 | AM82: 12.59 | AN82: 11.83 | AO82: 12.37 | AP82: 12.57 | AQ82: 12.07 | AR82: 11.98 | AS82: 10.22 | AT82: 8.61 | AU82: 8.7 | AV82: 8.31 | AW82: 8.91 | AX82: 8.88 | AY82: 8.83 | AZ82: 8.01 | BA82: 7.39 | BB82: 9.12 | BC82: 9.28 | BD82: 9.23 | BE82: 9.84 | BF82: 9.91 | BG82: 10.27 | BH82: 10.35 | BI82: 10.06 | BJ82: 9.41 | BK82: 9.02 | BL82: 8.41 | BM82: 8.01 | BN82: 7.86 | BO82: 7.31
A83: Faroe Islands | B83: FRO | C83: Unemployment, total (% of total labor force) (modeled ILO estimate) | D83: SL.UEM.TOTL.ZS
A84: Micronesia, Fed. Sts. | B84: FSM | C84: Unemployment, total (% of total labor force) (modeled ILO estimate) | D84: SL.UEM.TOTL.ZS
A85: Gabon | B85: GAB | C85: Unemployment, total (% of total labor force) (modeled ILO estimate) | D85: SL.UEM.TOTL.ZS | AJ85: 17.065 | AK85: 17.69 | AL85: 17.78 | AM85: 17.836 | AN85: 17.335 | AO85: 17.277 | AP85: 17.097 | AQ85: 17.098 | AR85: 17.68 | AS85: 18.016 | AT85: 18.008 | AU85: 17.451 | AV85: 17.151 | AW85: 17.144 | AX85: 16.91 | AY85: 17.858 | AZ85: 18.244 | BA85: 19.267 | BB85: 19.776 | BC85: 20.39 | BD85: 19.764 | BE85: 19.47 | BF85: 19.562 | BG85: 19.732 | BH85: 19.82 | BI85: 20.041 | BJ85: 20.283 | BK85: 20.479 | BL85: 20.369 | BM85: 21.432 | BN85: 21.411 | BO85: 20.61
A86: United Kingdom | B86: GBR | C86: Unemployment, total (% of total labor force) (modeled ILO estimate) | D86: SL.UEM.TOTL.ZS | AJ86: 8.55 | AK86: 9.77 | AL86: 10.35 | AM86: 9.65 | AN86: 8.69 | AO86: 8.19 | AP86: 7.07 | AQ86: 6.2 | AR86: 6.04 | AS86: 5.56 | AT86: 4.7 | AU86: 5.04 | AV86: 4.81 | AW86: 4.59 | AX86: 4.75 | AY86: 5.35 | AZ86: 5.26 | BA86: 5.62 | BB86: 7.54 | BC86: 7.79 | BD86: 8.04 | BE86: 7.88 | BF86: 7.52 | BG86: 6.11 | BH86: 5.3 | BI86: 4.81 | BJ86: 4.33 | BK86: 4 | BL86: 3.74 | BM86: 4.472 | BN86: 4.826 | BO86: 3.73
A87: Georgia | B87: GEO | C87: Unemployment, total (% of total labor force) (modeled ILO estimate) | D87: SL.UEM.TOTL.ZS | AJ87: 2.7 | AK87: 5.4 | AL87: 5.4 | AM87: 8.4 | AN87: 7.6 | AO87: 11.5 | AP87: 11.5 | AQ87: 14.53 | AR87: 13.8 | AS87: 10.82 | AT87: 11.16 | AU87: 12.59 | AV87: 11.51 | AW87: 12.62 | AX87: 13.81 | AY87: 13.57 | AZ87: 13.28 | BA87: 17.87 | BB87: 20.71 | BC87: 20.2 | BD87: 19.63 | BE87: 19.65 | BF87: 19.42 | BG87: 17.44 | BH87: 16.51 | BI87: 16.6 | BJ87: 13.94 | BK87: 12.67 | BL87: 11.57 | BM87: 11.73 | BN87: 11.851 | BO87: 11.683
A88: Ghana | B88: GHA | C88: Unemployment, total (% of total labor force) (modeled ILO estimate) | D88: SL.UEM.TOTL.ZS | AJ88: 3.49 | AK88: 4.7 | AL88: 5.224 | AM88: 5.911 | AN88: 6.495 | AO88: 7.108 | AP88: 7.647 | AQ88: 8.2 | AR88: 10.1 | AS88: 10.46 | AT88: 9.632 | AU88: 8.732 | AV88: 7.736 | AW88: 6.757 | AX88: 5.814 | AY88: 4.9 | AZ88: 5.121 | BA88: 5.143 | BB88: 5.379 | BC88: 5.38 | BD88: 4.191 | BE88: 3.102 | BF88: 2.17 | BG88: 4.387 | BH88: 6.81 | BI88: 5.295 | BJ88: 3.37 | BK88: 3.254 | BL88: 3.17 | BM88: 3.419 | BN88: 3.557 | BO88: 3.518
A89: Gibraltar | B89: GIB | C89: Unemployment, total (% of total labor force) (modeled ILO estimate) | D89: SL.UEM.TOTL.ZS
A90: Guinea | B90: GIN | C90: Unemployment, total (% of total labor force) (modeled ILO estimate) | D90: SL.UEM.TOTL.ZS | AJ90: 4.541 | AK90: 4.579 | AL90: 4.546 | AM90: 4.482 | AN90: 4.42 | AO90: 4.45 | AP90: 4.395 | AQ90: 4.444 | AR90: 4.477 | AS90: 4.612 | AT90: 4.615 | AU90: 4.55 | AV90: 4.678 | AW90: 4.814 | AX90: 4.999 | AY90: 5.071 | AZ90: 4.891 | BA90: 4.894 | BB90: 5.085 | BC90: 5.266 | BD90: 5.246 | BE90: 4.919 | BF90: 5.026 | BG90: 5.195 | BH90: 5.379 | BI90: 5.053 | BJ90: 4.771 | BK90: 4.705 | BL90: 5.02 | BM90: 6.064 | BN90: 5.97 | BO90: 5.526
A91: Gambia, The | B91: GMB | C91: Unemployment, total (% of total labor force) (modeled ILO estimate) | D91: SL.UEM.TOTL.ZS | AJ91: 9.523 | AK91: 9.672 | AL91: 9.72 | AM91: 9.893 | AN91: 10.046 | AO91: 10.106 | AP91: 9.862 | AQ91: 9.738 | AR91: 9.536 | AS91: 9.519 | AT91: 9.417 | AU91: 9.936 | AV91: 9.877 | AW91: 9.821 | AX91: 9.786 | AY91: 10.208 | AZ91: 10.454 | BA91: 9.975 | BB91: 9.6 | BC91: 9.464 | BD91: 10.255 | BE91: 10.35 | BF91: 9.526 | BG91: 8.202 | BH91: 7.278 | BI91: 6.331 | BJ91: 5.16 | BK91: 4.13 | BL91: 4.037 | BM91: 4.763 | BN91: 4.715 | BO91: 4.265
A92: Guinea-Bissau | B92: GNB | C92: Unemployment, total (% of total labor force) (modeled ILO estimate) | D92: SL.UEM.TOTL.ZS | AJ92: 3.097 | AK92: 3.179 | AL92: 3.243 | AM92: 3.275 | AN92: 3.223 | AO92: 3.079 | AP92: 3.031 | AQ92: 3.562 | AR92: 3.763 | AS92: 3.786 | AT92: 3.246 | AU92: 3.28 | AV92: 3.363 | AW92: 3.355 | AX92: 3.27 | AY92: 3.244 | AZ92: 3.239 | BA92: 3.258 | BB92: 3.243 | BC92: 3.223 | BD92: 3.148 | BE92: 3.231 | BF92: 3.255 | BG92: 3.376 | BH92: 3.246 | BI92: 3.199 | BJ92: 3.123 | BK92: 3.2 | BL92: 3.229 | BM92: 3.72 | BN92: 3.812 | BO92: 3.24
A93: Equatorial Guinea | B93: GNQ | C93: Unemployment, total (% of total labor force) (modeled ILO estimate) | D93: SL.UEM.TOTL.ZS | AJ93: 7.393 | AK93: 7.619 | AL93: 7.78 | AM93: 7.894 | AN93: 7.907 | AO93: 7.934 | AP93: 7.941 | AQ93: 8.001 | AR93: 8.079 | AS93: 8.115 | AT93: 8.237 | AU93: 8.316 | AV93: 8.348 | AW93: 8.253 | AX93: 8.214 | AY93: 8.124 | AZ93: 8.071 | BA93: 8.04 | BB93: 8.211 | BC93: 8.394 | BD93: 8.339 | BE93: 8.186 | BF93: 8.093 | BG93: 8.07 | BH93: 8.185 | BI93: 8.257 | BJ93: 8.334 | BK93: 8.244 | BL93: 8.327 | BM93: 9.034 | BN93: 9.187 | BO93: 8.584
A94: Greece | B94: GRC | C94: Unemployment, total (% of total labor force) (modeled ILO estimate) | D94: SL.UEM.TOTL.ZS | AJ94: 7.57 | AK94: 8.93 | AL94: 10.18 | AM94: 9.81 | AN94: 10.12 | AO94: 10.4 | AP94: 10.47 | AQ94: 12.23 | AR94: 12.14 | AS94: 11.34 | AT94: 10.76 | AU94: 10.35 | AV94: 9.84 | AW94: 10.63 | AX94: 10.07 | AY94: 8.91 | AZ94: 8.35 | BA94: 7.66 | BB94: 9.55 | BC94: 12.72 | BD94: 17.97 | BE94: 24.73 | BF94: 27.69 | BG94: 26.71 | BH94: 24.98 | BI94: 23.51 | BJ94: 21.41 | BK94: 19.18 | BL94: 17.04 | BM94: 15.9 | BN94: 14.66 | BO94: 12.43
A95: Grenada | B95: GRD | C95: Unemployment, total (% of total labor force) (modeled ILO estimate) | D95: SL.UEM.TOTL.ZS
A96: Greenland | B96: GRL | C96: Unemployment, total (% of total labor force) (modeled ILO estimate) | D96: SL.UEM.TOTL.ZS
A97: Guatemala | B97: GTM | C97: Unemployment, total (% of total labor force) (modeled ILO estimate) | D97: SL.UEM.TOTL.ZS | AJ97: 2.696 | AK97: 2.652 | AL97: 2.612 | AM97: 2.595 | AN97: 2.59 | AO97: 2.638 | AP97: 2.623 | AQ97: 2.621 | AR97: 2.578 | AS97: 2.615 | AT97: 2.752 | AU97: 2.753 | AV97: 2.81 | AW97: 2.97 | AX97: 3.06 | AY97: 2.953 | AZ97: 2.832 | BA97: 2.882 | BB97: 3.214 | BC97: 3.5 | BD97: 3.169 | BE97: 2.76 | BF97: 3.02 | BG97: 2.72 | BH97: 2.51 | BI97: 2.58 | BJ97: 2.46 | BK97: 2.28 | BL97: 2.19 | BM97: 2.88 | BN97: 2.17 | BO97: 3.05
A98: Guam | B98: GUM | C98: Unemployment, total (% of total labor force) (modeled ILO estimate) | D98: SL.UEM.TOTL.ZS | AJ98: 3.51 | AK98: 3.84 | AL98: 5.53 | AM98: 7.6 | AN98: 7.9 | AO98: 8.28 | AP98: 9.67 | AQ98: 7.74 | AR98: 13.95 | AS98: 15.32 | AT98: 13.21 | AU98: 11.39 | AV98: 9.703 | AW98: 7.7 | AX98: 7 | AY98: 7.4 | AZ98: 8.3 | BA98: 8.897 | BB98: 9.3 | BC98: 8.2 | BD98: 13.3 | BE98: 12.2 | BF98: 11.5 | BG98: 7.6 | BH98: 6.9 | BI98: 5.4 | BJ98: 5.417 | BK98: 5.449 | BL98: 5.399 | BM98: 6.248 | BN98: 6.002 | BO98: 5.569
A99: Guyana | B99: GUY | C99: Unemployment, total (% of total labor force) (modeled ILO estimate) | D99: SL.UEM.TOTL.ZS | AJ99: 12.171 | AK99: 11.9 | AL99: 11.645 | AM99: 11.57 | AN99: 11.597 | AO99: 11.575 | AP99: 11.596 | AQ99: 11.705 | AR99: 11.78 | AS99: 11.909 | AT99: 11.8 | AU99: 11.81 | AV99: 11.532 | AW99: 11.281 | AX99: 11.075 | AY99: 10.7 | AZ99: 10.883 | BA99: 11.098 | BB99: 11.412 | BC99: 11.758 | BD99: 11.971 | BE99: 12.224 | BF99: 12.522 | BG99: 12.889 | BH99: 13.286 | BI99: 13.577 | BJ99: 13.822 | BK99: 14.02 | BL99: 13.52 | BM99: 15.69 | BN99: 14.98 | BO99: 12.301
A100: High income | B100: HIC | C100: Unemployment, total (% of total labor force) (modeled ILO estimate) | D100: SL.UEM.TOTL.ZS | AJ100: 6.8917343 | AK100: 7.4270081 | AL100: 7.9681763 | AM100: 7.9647835 | AN100: 7.5556057 | AO100: 7.5141093 | AP100: 7.2324588 | AQ100: 7.1520313 | AR100: 7.001541 | AS100: 6.6033022 | AT100: 6.5463984 | AU100: 7.0660233 | AV100: 7.1875518 | AW100: 7.0351666 | AX100: 6.7567112 | AY100: 6.2227099 | AZ100: 5.6763559 | BA100: 5.9222567 | BB100: 8.0117641 | BC100: 8.282954 | BD100: 7.9687222 | BE100: 8.0061256 | BF100: 7.8926314 | BG100: 7.279374 | BH100: 6.6876655 | BI100: 6.1969255 | BJ100: 5.6302986 | BK100: 5.1075152 | BL100: 4.7922992 | BM100: 6.5631501 | BN100: 5.6596141 | BO100: 4.5701922
A101: Hong Kong SAR, China | B101: HKG | C101: Unemployment, total (% of total labor force) (modeled ILO estimate) | D101: SL.UEM.TOTL.ZS | AJ101: 1.8 | AK101: 1.96 | AL101: 1.96 | AM101: 1.9 | AN101: 3.22 | AO101: 2.83 | AP101: 2.22 | AQ101: 4.58 | AR101: 6.25 | AS101: 4.92 | AT101: 5.09 | AU101: 7.28 | AV101: 7.86 | AW101: 6.74 | AX101: 5.58 | AY101: 4.77 | AZ101: 4.01 | BA101: 3.56 | BB101: 5.26 | BC101: 4.33 | BD101: 3.42 | BE101: 3.29 | BF101: 3.4 | BG101: 3.3 | BH101: 3.31 | BI101: 3.39 | BJ101: 3.12 | BK101: 2.81 | BL101: 2.92 | BM101: 5.81 | BN101: 5.17 | BO101: 4.32
A102: Honduras | B102: HND | C102: Unemployment, total (% of total labor force) (modeled ILO estimate) | D102: SL.UEM.TOTL.ZS | AJ102: 4.58 | AK102: 3.06 | AL102: 3.098 | AM102: 3.137 | AN102: 3.24 | AO102: 4.37 | AP102: 3.32 | AQ102: 4.02 | AR102: 3.85 | AS102: 3.882 | AT102: 4 | AU102: 4.02 | AV102: 5.3 | AW102: 5.99 | AX102: 4.91 | AY102: 3.57 | AZ102: 3.21 | BA102: 3.16 | BB102: 3.29 | BC102: 4.12 | BD102: 4.47 | BE102: 3.75 | BF102: 5.65 | BG102: 7.08 | BH102: 6.15 | BI102: 6.73 | BJ102: 5.53 | BK102: 5.62 | BL102: 5.55 | BM102: 10.68 | BN102: 8.23 | BO102: 6.998
A103: Heavily indebted poor countries (HIPC) | B103: HPC | C103: Unemployment, total (% of total labor force) (modeled ILO estimate) | D103: SL.UEM.TOTL.ZS | AJ103: 5.1701618 | AK103: 5.3152124 | AL103: 5.3135222 | AM103: 5.2589068 | AN103: 5.0404902 | AO103: 4.9856311 | AP103: 4.893137 | AQ103: 4.969046 | AR103: 5.131191 | AS103: 5.1950035 | AT103: 5.1180297 | AU103: 5.0950899 | AV103: 5.0585105 | AW103: 4.9323832 | AX103: 4.7780787 | AY103: 4.6970037 | AZ103: 4.6467472 | BA103: 4.6217393 | BB103: 4.6978027 | BC103: 4.9063726 | BD103: 4.8731326 | BE103: 4.6959943 | BF103: 4.4726016 | BG103: 4.4772796 | BH103: 4.6286068 | BI103: 4.6140705 | BJ103: 4.6592827 | BK103: 4.5819519 | BL103: 4.5962247 | BM103: 5.4083339 | BN103: 5.3739943 | BO103: 4.8804886
A104: Croatia | B104: HRV | C104: Unemployment, total (% of total labor force) (modeled ILO estimate) | D104: SL.UEM.TOTL.ZS | AJ104: 11.14 | AK104: 10.937 | AL104: 10.712 | AM104: 10.333 | AN104: 9.996 | AO104: 9.68 | AP104: 9.71 | AQ104: 11.39 | AR104: 13.56 | AS104: 16.06 | AT104: 15.82 | AU104: 15.05 | AV104: 13.92 | AW104: 13.66 | AX104: 12.6 | AY104: 11.13 | AZ104: 9.91 | BA104: 8.53 | BB104: 9.2 | BC104: 11.62 | BD104: 13.68 | BE104: 15.93 | BF104: 17.25 | BG104: 17.29 | BH104: 16.18 | BI104: 13.1 | BJ104: 11.21 | BK104: 8.43 | BL104: 6.62 | BM104: 7.51 | BN104: 7.61 | BO104: 6.96
A105: Haiti | B105: HTI | C105: Unemployment, total (% of total labor force) (modeled ILO estimate) | D105: SL.UEM.TOTL.ZS | AJ105: 7.352 | AK105: 7.428 | AL105: 7.607 | AM105: 8.006 | AN105: 7.58 | AO105: 7.33 | AP105: 6.966 | AQ105: 7.16 | AR105: 7.2 | AS105: 8.448 | AT105: 9.756 | AU105: 11.059 | AV105: 12.196 | AW105: 13.472 | AX105: 14.6 | AY105: 15.926 | AZ105: 16.8 | BA105: 16.191 | BB105: 15.33 | BC105: 15.256 | BD105: 14.476 | BE105: 14.1 | BF105: 13.62 | BG105: 13.802 | BH105: 13.717 | BI105: 13.858 | BJ105: 13.835 | BK105: 13.896 | BL105: 14.089 | BM105: 15.646 | BN105: 15.558 | BO105: 14.776
A106: Hungary | B106: HUN | C106: Unemployment, total (% of total labor force) (modeled ILO estimate) | D106: SL.UEM.TOTL.ZS | AJ106: 8.5 | AK106: 9.94 | AL106: 12.1 | AM106: 10.85 | AN106: 10.17 | AO106: 10.02 | AP106: 8.99 | AQ106: 8.93 | AR106: 6.93 | AS106: 6.56 | AT106: 5.67 | AU106: 5.61 | AV106: 5.79 | AW106: 5.83 | AX106: 7.19 | AY106: 7.49 | AZ106: 7.41 | BA106: 7.82 | BB106: 10.03 | BC106: 11.17 | BD106: 11.03 | BE106: 11 | BF106: 10.18 | BG106: 7.73 | BH106: 6.81 | BI106: 5.11 | BJ106: 4.16 | BK106: 3.71 | BL106: 3.42 | BM106: 4.25 | BN106: 4.05 | BO106: 3.61
A107: IBRD only | B107: IBD | C107: Unemployment, total (% of total labor force) (modeled ILO estimate) | D107: SL.UEM.TOTL.ZS | AJ107: 4.7222198 | AK107: 4.7692783 | AL107: 5.0075229 | AM107: 5.397751 | AN107: 5.7518541 | AO107: 5.8846306 | AP107: 6.0211517 | AQ107: 6.2792605 | AR107: 6.5634493 | AS107: 6.5261946 | AT107: 6.7045153 | AU107: 6.9446652 | AV107: 7.0700781 | AW107: 6.9612002 | AX107: 6.9312112 | AY107: 6.6748763 | AZ107: 6.4783335 | BA107: 6.426826 | BB107: 6.7277455 | BC107: 6.4947534 | BD107: 6.3588184 | BE107: 6.2486862 | BF107: 6.2359198 | BG107: 6.2160342 | BH107: 6.3401181 | BI107: 6.4384254 | BJ107: 6.3874809 | BK107: 6.2541639 | BL107: 6.0348567 | BM107: 6.9092808 | BN107: 6.2779852 | BO107: 5.5286998
A108: IDA & IBRD total | B108: IBT | C108: Unemployment, total (% of total labor force) (modeled ILO estimate) | D108: SL.UEM.TOTL.ZS | AJ108: 4.6175957 | AK108: 4.6695028 | AL108: 4.8852649 | AM108: 5.2143441 | AN108: 5.4942614 | AO108: 5.6073531 | AP108: 5.7119953 | AQ108: 5.9393726 | AR108: 6.1878172 | AS108: 6.1563856 | AT108: 6.2957284 | AU108: 6.4827707 | AV108: 6.5748119 | AW108: 6.4621477 | AX108: 6.4138163 | AY108: 6.1725186 | AZ108: 6.0084299 | BA108: 5.9751355 | BB108: 6.2267638 | BC108: 6.0188286 | BD108: 5.9121952 | BE108: 5.8877128 | BF108: 5.8406031 | BG108: 5.7974966 | BH108: 5.9551382 | BI108: 6.0080796 | BJ108: 6.0086708 | BK108: 5.9170656 | BL108: 5.7675054 | BM108: 6.6266024 | BN108: 6.1618552 | BO108: 5.4255993
... A112: IDA only | B112: IDX | C112: Unemployment, total (% of total labor force) (modeled ILO estimate) | D112: SL.UEM.TOTL.ZS | AJ112: 4.5946884 | AK112: 4.6713021 | AL112: 4.6976566 | AM112: 4.677089 | AN112: 4.5452202 | AO112: 4.5462461 | AP112: 4.513395 | AQ112: 4.5958253 | AR112: 4.7316242 | AS112: 4.8078549 | AT112: 4.8544348 | AU112: 4.9327993 | AV112: 4.9653804 | AW112: 4.8945661 | AX112: 4.7756652 | AY112: 4.5989542 | AZ112: 4.6573249 | BA112: 4.734414 | BB112: 4.8185587 | BC112: 4.6902169 | BD112: 4.7278687 | BE112: 4.7390025 | BF112: 4.6358989 | BG112: 4.6318129 | BH112: 4.7428739 | BI112: 4.7490038 | BJ112: 4.7865413 | BK112: 4.6904001 | BL112: 4.6955241 | BM112: 5.5396147 | BN112: 5.6907136 | BO112: 5.0972571
A113: Isle of Man | B113: IMN | C113: Unemployment, total (% of total labor force) (modeled ILO estimate) | D113: SL.UEM.TOTL.ZS
A114: India | B114: IND | C114: Unemployment, total (% of total labor force) (modeled ILO estimate) | D114: SL.UEM.TOTL.ZS | AJ114: 6.838 | AK114: 6.838 | AL114: 6.838 | AM114: 6.83 | AN114: 6.998 | AO114: 7.165 | AP114: 7.339 | AQ114: 7.511 | AR114: 7.68 | AS114: 7.85 | AT114: 8.022 | AU114: 8.202 | AV114: 8.368 | AW114: 8.535 | AX114: 8.7 | AY114: 8.618 | AZ114: 8.537 | BA114: 8.463 | BB114: 8.383 | BC114: 8.3 | BD114: 8.215 | BE114: 8.138 | BF114: 8.06 | BG114: 7.976 | BH114: 7.891 | BI114: 7.808 | BJ114: 7.728 | BK114: 7.65 | BL114: 6.51 | BM114: 7.86 | BN114: 6.38 | BO114: 4.822
A115: Not classified | B115: INX | C115: Unemployment, total (% of total labor force) (modeled ILO estimate) | D115: SL.UEM.TOTL.ZS
A116: Ireland | B116: IRL | C116: Unemployment, total (% of total labor force) (modeled ILO estimate) | D116: SL.UEM.TOTL.ZS | AJ116: 15.77 | AK116: 15.02 | AL116: 15.57 | AM116: 14.54 | AN116: 11.97 | AO116: 11.69 | AP116: 10.19 | AQ116: 7.7 | AR116: 5.8 | AS116: 4.32 | AT116: 3.68 | AU116: 4.22 | AV116: 4.48 | AW116: 4.49 | AX116: 4.34 | AY116: 4.41 | AZ116: 4.98 | BA116: 6.77 | BB116: 12.61 | BC116: 14.53 | BD116: 15.35 | BE116: 15.45 | BF116: 13.73 | BG116: 11.86 | BH116: 9.91 | BI116: 8.37 | BJ116: 6.71 | BK116: 5.74 | BL116: 4.95 | BM116: 5.62 | BN116: 6.19 | BO116: 4.48
A117: Iran, Islamic Rep. | B117: IRN | C117: Unemployment, total (% of total labor force) (modeled ILO estimate) | D117: SL.UEM.TOTL.ZS | AJ117: 11.1 | AK117: 10.662 | AL117: 10.554 | AM117: 10.41 | AN117: 9.866 | AO117: 9.1 | AP117: 9.692 | AQ117: 10.366 | AR117: 11.162 | AS117: 11.691 | AT117: 12.345 | AU117: 12.8 | AV117: 11.529 | AW117: 10.3 | AX117: 11.81 | AY117: 11.52 | AZ117: 10.77 | BA117: 10.63 | BB117: 12.11 | BC117: 13.68 | BD117: 12.49 | BE117: 12.27 | BF117: 10.6 | BG117: 10.68 | BH117: 11.17 | BI117: 12.62 | BJ117: 12.23 | BK117: 12.19 | BL117: 10.74 | BM117: 9.69 | BN117: 9.28 | BO117: 8.815
A118: Iraq | B118: IRQ | C118: Unemployment, total (% of total labor force) (modeled ILO estimate) | D118: SL.UEM.TOTL.ZS | AJ118: 8.711 | AK118: 8.439 | AL118: 8.445 | AM118: 8.309 | AN118: 8.502 | AO118: 8.593 | AP118: 8.385 | AQ118: 8.185 | AR118: 8.111 | AS118: 8.155 | AT118: 8.352 | AU118: 8.65 | AV118: 8.94 | AW118: 8.708 | AX118: 8.587 | AY118: 8.436 | AZ118: 8.65 | BA118: 8.475 | BB118: 8.405 | BC118: 8.257 | BD118: 8.171 | BE118: 7.96 | BF118: 9.215 | BG118: 10.59 | BH118: 10.82 | BI118: 10.82 | BJ118: 13.02 | BK118: 13.449 | BL118: 14 | BM118: 15.746 | BN118: 16.17 | BO118: 15.322
A119: Iceland | B119: ISL | C119: Unemployment, total (% of total labor force) (modeled ILO estimate) | D119: SL.UEM.TOTL.ZS | AJ119: 2.55 | AK119: 4.31 | AL119: 5.26 | AM119: 5.33 | AN119: 5.2 | AO119: 3.6 | AP119: 3.72 | AQ119: 3.07 | AR119: 2.18 | AS119: 1.94 | AT119: 1.87 | AU119: 2.99 | AV119: 4 | AW119: 4.03 | AX119: 2.55 | AY119: 2.83 | AZ119: 2.25 | BA119: 2.95 | BB119: 7.22 | BC119: 7.56 | BD119: 7.03 | BE119: 6 | BF119: 5.38 | BG119: 4.9 | BH119: 3.98 | BI119: 2.98 | BJ119: 2.74 | BK119: 2.7 | BL119: 3.51 | BM119: 5.48 | BN119: 6.03 | BO119: 3.79
A120: Israel | B120: ISR | C120: Unemployment, total (% of total labor force) (modeled ILO estimate) | D120: SL.UEM.TOTL.ZS | AJ120: 13.39 | AK120: 14.08 | AL120: 12.74 | AM120: 9.93 | AN120: 8.78 | AO120: 8.46 | AP120: 9.75 | AQ120: 10.75 | AR120: 11.18 | AS120: 11.1 | AT120: 11.81 | AU120: 12.89 | AV120: 13.51 | AW120: 13.03 | AX120: 11.34 | AY120: 10.71 | AZ120: 9.38 | BA120: 7.7 | BB120: 9.53 | BC120: 8.48 | BD120: 7.14 | BE120: 6.76 | BF120: 6.14 | BG120: 5.79 | BH120: 5.18 | BI120: 4.72 | BJ120: 4.14 | BK120: 3.92 | BL120: 3.73 | BM120: 4.17 | BN120: 4.81 | BO120: 3.695
A121: Italy | B121: ITA | C121: Unemployment, total (% of total labor force) (modeled ILO estimate) | D121: SL.UEM.TOTL.ZS | AJ121: 10.1 | AK121: 9.32 | AL121: 10.21 | AM121: 11.09 | AN121: 11.66 | AO121: 11.86 | AP121: 11.98 | AQ121: 12.12 | AR121: 11.68 | AS121: 10.83 | AT121: 9.6 | AU121: 9.21 | AV121: 8.87 | AW121: 7.87 | AX121: 7.73 | AY121: 6.78 | AZ121: 6.08 | BA121: 6.72 | BB121: 7.75 | BC121: 8.36 | BD121: 8.36 | BE121: 10.65 | BF121: 12.15 | BG121: 12.68 | BH121: 11.9 | BI121: 11.69 | BJ121: 11.21 | BK121: 10.61 | BL121: 9.95 | BM121: 9.16 | BN121: 9.5 | BO121: 8.07
...

Sheet Average_Diet
J1: Model diet
B2: Percentage edible/eaten | C2: Functional unit (g) | D2: Calories | E2: From carb | F2: From fat | G2: From protein | H2: Food item | I2: Quantity (/100g) | J2: Calories | K2: From carb | L2: From fat | M2: From protein
A3: Loaf of Fresh White Bread | B3: 0.9 | C3: 100 | D3: 266 | E3: 208 | F3: 28.6 | G3: 29.8 | H3: =A3 -> Loaf of Fresh White Bread | I3: 3.3 | J3: =$I3*D3 -> 877.8 | K3: =$I3*E3 -> 686.4 | L3: =$I3*F3 -> 94.38 | M3: =$I3*G3 -> 98.34
A4: Eggs | B4: 1 | C4: 100 | D4: 143 | E4: 3.2 | F4: 89.5 | G4: 50.3 | H4: =A4 -> Eggs | I4: 0.5 | J4: =$I4*D4 -> 71.5 | K4: =$I4*E4 -> 1.6 | L4: =$I4*F4 -> 44.75 | M4: =$I4*G4 -> 25.15
A5: Local Cheese | B5: 0.9 | C5: 100 | D5: 403 | E5: 5.4 | F5: 291 | G5: 106 | H5: =A5 -> Local Cheese | I5: 1.1 | J5: =$I5*D5 -> 443.3 | K5: =$I5*E5 -> 5.94 | L5: =$I5*F5 -> 320.1 | M5: =$I5*G5 -> 116.6
A6: Apples | B6: 0.8 | C6: 100 | D6: 52 | E6: 49.7 | F6: 1.4 | G6: 0.9 | H6: =A6 -> Apples | I6: 0.5 | J6: =$I6*D6 -> 26 | K6: =$I6*E6 -> 24.85 | L6: =$I6*F6 -> 0.7 | M6: =$I6*G6 -> 0.45
A7: Oranges | B7: 0.8 | C7: 100 | D7: 47 | E7: 42.8 | F7: 1 | G7: 3.2 | H7: =A7 -> Oranges | I7: 0.5 | J7: =$I7*D7 -> 23.5 | K7: =$I7*E7 -> 21.4 | L7: =$I7*F7 -> 0.5 | M7: =$I7*G7 -> 1.6
A8: Potato | B8: 0.9 | C8: 100 | D8: 93 | E8: 85 | F8: 1.1 | G8: 7 | H8: =A8 -> Potato | I8: 3 | J8: =$I8*D8 -> 279 | K8: =$I8*E8 -> 255 | L8: =$I8*F8 -> 3.3 | M8: =$I8*G8 -> 21
A9: Lettuce | B9: 0.5 | C9: 100 | D9: 14 | E9: 10.6 | F9: 1.2 | G9: 2.2 | H9: =A9 -> Lettuce | I9: 0.6 | J9: =$I9*D9 -> 8.4 | K9: =$I9*E9 -> 6.36 | L9: =$I9*F9 -> 0.72 | M9: =$I9*G9 -> 1.32
A10: Rice | B10: 1 | C10: 100 | D10: 130 | E10: 117 | F10: 2.3 | G10: 10.3 | H10: =A10 -> Rice | I10: 3 | J10: =$I10*D10 -> 390 | K10: =$I10*E10 -> 351 | L10: =$I10*F10 -> 6.9 | M10: =$I10*G10 -> 30.9
A11: Tomato | B11: 0.8 | C11: 100 | D11: 18 | E11: 14.2 | F11: 0 | G11: 1.7 | H11: =A11 -> Tomato | I11: 0.6 | J11: =$I11*D11 -> 10.8 | K11: =$I11*E11 -> 8.52 | L11: =$I11*F11 -> 0 | M11: =$I11*G11 -> 1.02
A12: Banana | B12: 0.7 | C12: 100 | D12: 89 | E12: 82.6 | F12: 2.8 | G12: 3.7 | H12: =A12 -> Banana | I12: 0.6 | J12: =$I12*D12 -> 53.4 | K12: =$I12*E12 -> 49.56 | L12: =$I12*F12 -> 1.68 | M12: =$I12*G12 -> 2.22
A13: Onion | B13: 0.8 | C13: 100 | D13: 40 | E13: 36.1 | F13: 0.8 | G13: 3.1 | H13: =A13 -> Onion | I13: 0.3 | J13: =$I13*D13 -> 12 | K13: =$I13*E13 -> 10.83 | L13: =$I13*F13 -> 0.24 | M13: =$I13*G13 -> 0.93
A14: Beef Round | B14: 1 | C14: 100 | D14: 145 | E14: 0 | F14: 37.9 | G14: 107 | H14: =A14 -> Beef Round | I14: 0.1 | J14: =$I14*D14 -> 14.5 | K14: =$I14*E14 -> 0 | L14: =$I14*F14 -> 3.79 | M14: =$I14*G14 -> 10.7
... A16: Milk | B16: 1 | C16: 100 | D16: 60 | E16: 0.179 | F16: 29.2 | G16: 12.9 | H16: =A16 -> Milk | I16: 1 | J16: =$I16*D16 -> 60 | K16: =$I16*E16 -> 0.179 | L16: =$I16*F16 -> 29.2 | M16: =$I16*G16 -> 12.9
H17: Total | I17: =SUM(I3:I16)*0.1 -> 1.53 | J17: =SUM(J3:J16) -> 2303.2 | K17: =SUM(K3:K16) -> 1421.719 | L17: =SUM(L3:L16) -> 512.7 | M17: =SUM(M3:M16) -> 349.53
I18: kg | J18: calories | K18: =K17/$J$17 -> 0.61727987 | L18: =L17/$J$17 -> 0.22260333 | M18: =M17/$J$17 -> 0.15175842
A20: Target | D20: 2300 | E20: 0.65 | F20: 0.225 | G20: 0.1 | J20: 2300 | K20: 0.65 | L20: 0.225 | M20: 0.1
A24: The following guidance is used to ensure that the model diet created for a living wage study follows WHO recommendations on nutrition:
A26: ● Number of calories in the model diet needs to be sufficient accord- ing to WHO (2004) recommendations. We created an Excel calorie requirement program for this calculation.
A28: ● At least 10% of calories must come from proteins as recommended by WHO/FAO (2003). Also, in accordance with these recommenda- tions, proteins need to come from a variety of sources including some ‘higher quality’ sources of proteins such as foods of animal- origin and legumes.
A30: ● Some dairy (which is rich in calcium and high quality protein) should be included in the diet, especially for children (FAO, 2014a).
A32: ● 15–30% of calories must come from fats as recommended by WHO/ FAO (2003).
A34: ● 55–75% of calories must come from carbohydrates as recommended by WHO/FAO (2003).
A36: ● At least 300 grams1 of vegetables and fruits per day (includ- ing legumes) must be included in the model diet to help provide micronutrients and minerals.

Sheet Fert_WHO
A1: Indicator | B1: Year | C1: Country | D1: Global | E1: WHO region | F1: SDG region | G1: World bank income group | H1: Comments | I1: Value Numeric
A2: Total fertility rate (live births per woman) | B2: 2023 | C2: Afghanistan | D2: =_xlfn.IFNA(VLOOKUP(C2,Countries_WB!$B$2:$C$219,2,FALSE),VLOOKUP(C2,Countries_WB!$A$2:$C$219,3,FALSE)) -> AFG | E2: Eastern Mediterranean | G2: Low income | I2: 3.782
A3: Total fertility rate (live births per woman) | B3: 2023 | C3: Albania | D3: =_xlfn.IFNA(VLOOKUP(C3,Countries_WB!$B$2:$C$219,2,FALSE),VLOOKUP(C3,Countries_WB!$A$2:$C$219,3,FALSE)) -> ALB | E3: Europe | G3: Upper middle income | I3: 1.537
A4: Total fertility rate (live births per woman) | B4: 2023 | C4: Algeria | D4: =_xlfn.IFNA(VLOOKUP(C4,Countries_WB!$B$2:$C$219,2,FALSE),VLOOKUP(C4,Countries_WB!$A$2:$C$219,3,FALSE)) -> DZA | E4: Africa | G4: Lower middle income | I4: 2.778
A5: Total fertility rate (live births per woman) | B5: 2023 | C5: American Samoa | D5: =_xlfn.IFNA(VLOOKUP(C5,Countries_WB!$B$2:$C$219,2,FALSE),VLOOKUP(C5,Countries_WB!$A$2:$C$219,3,FALSE)) -> ASM | E5: Western Pacific | G5: High income | I5: 2.483
A6: Total fertility rate (live births per woman) | B6: 2023 | C6: Andorra | D6: =_xlfn.IFNA(VLOOKUP(C6,Countries_WB!$B$2:$C$219,2,FALSE),VLOOKUP(C6,Countries_WB!$A$2:$C$219,3,FALSE)) -> AND | E6: Europe | G6: High income | I6: 1.129
A7: Total fertility rate (live births per woman) | B7: 2023 | C7: Angola | D7: =_xlfn.IFNA(VLOOKUP(C7,Countries_WB!$B$2:$C$219,2,FALSE),VLOOKUP(C7,Countries_WB!$A$2:$C$219,3,FALSE)) -> AGO | E7: Africa | G7: Lower middle income | I7: 5.178
A8: Total fertility rate (live births per woman) | B8: 2023 | C8: Anguilla | D8: =_xlfn.IFNA(VLOOKUP(C8,Countries_WB!$B$2:$C$219,2,FALSE),VLOOKUP(C8,Countries_WB!$A$2:$C$219,3,FALSE)) -> #N/A | E8: Americas | I8: 1.675
A9: Total fertility rate (live births per woman) | B9: 2023 | C9: Antigua and Barbuda | D9: =_xlfn.IFNA(VLOOKUP(C9,Countries_WB!$B$2:$C$219,2,FALSE),VLOOKUP(C9,Countries_WB!$A$2:$C$219,3,FALSE)) -> ATG | E9: Americas | G9: High income | I9: 1.948
A10: Total fertility rate (live births per woman) | B10: 2023 | C10: Argentina | D10: =_xlfn.IFNA(VLOOKUP(C10,Countries_WB!$B$2:$C$219,2,FALSE),VLOOKUP(C10,Countries_WB!$A$2:$C$219,3,FALSE)) -> ARG | E10: Americas | G10: Upper middle income | I10: 2.193
A11: Total fertility rate (live births per woman) | B11: 2023 | C11: Armenia | D11: =_xlfn.IFNA(VLOOKUP(C11,Countries_WB!$B$2:$C$219,2,FALSE),VLOOKUP(C11,Countries_WB!$A$2:$C$219,3,FALSE)) -> ARM | E11: Europe | G11: Upper middle income | I11: 1.76
A12: Total fertility rate (live births per woman) | B12: 2023 | C12: Aruba | D12: =_xlfn.IFNA(VLOOKUP(C12,Countries_WB!$B$2:$C$219,2,FALSE),VLOOKUP(C12,Countries_WB!$A$2:$C$219,3,FALSE)) -> ABW | E12: Americas | G12: High income | H12: (13) For statistical purposes, the data for Netherlands do not include this area. | I12: 1.886
A13: Total fertility rate (live births per woman) | B13: 2023 | C13: Australia | D13: =_xlfn.IFNA(VLOOKUP(C13,Countries_WB!$B$2:$C$219,2,FALSE),VLOOKUP(C13,Countries_WB!$A$2:$C$219,3,FALSE)) -> AUS | E13: Western Pacific | G13: High income | H13: (15) Including Christmas Island, Cocos (Keeling) Islands and Norfolk Island. | I13: 1.781
A14: Total fertility rate (live births per woman) | B14: 2023 | C14: Austria | D14: =_xlfn.IFNA(VLOOKUP(C14,Countries_WB!$B$2:$C$219,2,FALSE),VLOOKUP(C14,Countries_WB!$A$2:$C$219,3,FALSE)) -> AUT | E14: Europe | G14: High income | I14: 1.575
A15: Total fertility rate (live births per woman) | B15: 2023 | C15: Azerbaijan | D15: =_xlfn.IFNA(VLOOKUP(C15,Countries_WB!$B$2:$C$219,2,FALSE),VLOOKUP(C15,Countries_WB!$A$2:$C$219,3,FALSE)) -> AZE | E15: Europe | G15: Upper middle income | H15: (4) Including Nagorno-Karabakh. | I15: 1.987
A16: Total fertility rate (live births per woman) | B16: 2023 | C16: Bahamas | D16: =_xlfn.IFNA(VLOOKUP(C16,Countries_WB!$B$2:$C$219,2,FALSE),VLOOKUP(C16,Countries_WB!$A$2:$C$219,3,FALSE)) -> BHS | E16: Americas | G16: High income | I16: 1.706
A17: Total fertility rate (live births per woman) | B17: 2023 | C17: Bahrain | D17: =_xlfn.IFNA(VLOOKUP(C17,Countries_WB!$B$2:$C$219,2,FALSE),VLOOKUP(C17,Countries_WB!$A$2:$C$219,3,FALSE)) -> BHR | E17: Eastern Mediterranean | G17: High income | I17: 1.881
A18: Total fertility rate (live births per woman) | B18: 2023 | C18: Bangladesh | D18: =_xlfn.IFNA(VLOOKUP(C18,Countries_WB!$B$2:$C$219,2,FALSE),VLOOKUP(C18,Countries_WB!$A$2:$C$219,3,FALSE)) -> BGD | E18: South-East Asia | G18: Lower middle income | I18: 1.917
A19: Total fertility rate (live births per woman) | B19: 2023 | C19: Barbados | D19: =_xlfn.IFNA(VLOOKUP(C19,Countries_WB!$B$2:$C$219,2,FALSE),VLOOKUP(C19,Countries_WB!$A$2:$C$219,3,FALSE)) -> BRB | E19: Americas | G19: High income | I19: 1.642
A20: Total fertility rate (live births per woman) | B20: 2023 | C20: Belarus | D20: =_xlfn.IFNA(VLOOKUP(C20,Countries_WB!$B$2:$C$219,2,FALSE),VLOOKUP(C20,Countries_WB!$A$2:$C$219,3,FALSE)) -> BLR | E20: Europe | G20: Upper middle income | I20: 1.738
A21: Total fertility rate (live births per woman) | B21: 2023 | C21: Belgium | D21: =_xlfn.IFNA(VLOOKUP(C21,Countries_WB!$B$2:$C$219,2,FALSE),VLOOKUP(C21,Countries_WB!$A$2:$C$219,3,FALSE)) -> BEL | E21: Europe | G21: High income | I21: 1.727
A22: Total fertility rate (live births per woman) | B22: 2023 | C22: Belize | D22: =_xlfn.IFNA(VLOOKUP(C22,Countries_WB!$B$2:$C$219,2,FALSE),VLOOKUP(C22,Countries_WB!$A$2:$C$219,3,FALSE)) -> BLZ | E22: Americas | G22: Upper middle income | I22: 2.178
A23: Total fertility rate (live births per woman) | B23: 2023 | C23: Benin | D23: =_xlfn.IFNA(VLOOKUP(C23,Countries_WB!$B$2:$C$219,2,FALSE),VLOOKUP(C23,Countries_WB!$A$2:$C$219,3,FALSE)) -> BEN | E23: Africa | G23: Lower middle income | I23: 4.513
A24: Total fertility rate (live births per woman) | B24: 2023 | C24: Bermuda | D24: =_xlfn.IFNA(VLOOKUP(C24,Countries_WB!$B$2:$C$219,2,FALSE),VLOOKUP(C24,Countries_WB!$A$2:$C$219,3,FALSE)) -> BMU | E24: Americas | G24: High income | I24: 1.36
A25: Total fertility rate (live births per woman) | B25: 2023 | C25: Bhutan | D25: =_xlfn.IFNA(VLOOKUP(C25,Countries_WB!$B$2:$C$219,2,FALSE),VLOOKUP(C25,Countries_WB!$A$2:$C$219,3,FALSE)) -> BTN | E25: South-East Asia | G25: Lower middle income | I25: 1.854
A26: Total fertility rate (live births per woman) | B26: 2023 | C26: Bolivia (Plurinational State of) | D26: =_xlfn.IFNA(VLOOKUP(C26,Countries_WB!$B$2:$C$219,2,FALSE),VLOOKUP(C26,Countries_WB!$A$2:$C$219,3,FALSE)) -> BOL | E26: Americas | G26: Lower middle income | I26: 2.558
A27: Total fertility rate (live births per woman) | B27: 2023 | C27: Bonaire, Saint Eustatius and Saba | D27: =_xlfn.IFNA(VLOOKUP(C27,Countries_WB!$B$2:$C$219,2,FALSE),VLOOKUP(C27,Countries_WB!$A$2:$C$219,3,FALSE)) -> #N/A | E27: Americas | I27: 1.791
A28: Total fertility rate (live births per woman) | B28: 2023 | C28: Bosnia and Herzegovina | D28: =_xlfn.IFNA(VLOOKUP(C28,Countries_WB!$B$2:$C$219,2,FALSE),VLOOKUP(C28,Countries_WB!$A$2:$C$219,3,FALSE)) -> BIH | E28: Europe | G28: Upper middle income | I28: 1.219
A29: Total fertility rate (live births per woman) | B29: 2023 | C29: Botswana | D29: =_xlfn.IFNA(VLOOKUP(C29,Countries_WB!$B$2:$C$219,2,FALSE),VLOOKUP(C29,Countries_WB!$A$2:$C$219,3,FALSE)) -> BWA | E29: Africa | G29: Upper middle income | I29: 2.675
A30: Total fertility rate (live births per woman) | B30: 2023 | C30: Brazil | D30: =_xlfn.IFNA(VLOOKUP(C30,Countries_WB!$B$2:$C$219,2,FALSE),VLOOKUP(C30,Countries_WB!$A$2:$C$219,3,FALSE)) -> BRA | E30: Americas | G30: Upper middle income | I30: 1.663
A31: Total fertility rate (live births per woman) | B31: 2023 | C31: British Virgin Islands | D31: =_xlfn.IFNA(VLOOKUP(C31,Countries_WB!$B$2:$C$219,2,FALSE),VLOOKUP(C31,Countries_WB!$A$2:$C$219,3,FALSE)) -> VGB | E31: Americas | G31: High income | I31: 1.37
A32: Total fertility rate (live births per woman) | B32: 2023 | C32: Brunei Darussalam | D32: =_xlfn.IFNA(VLOOKUP(C32,Countries_WB!$B$2:$C$219,2,FALSE),VLOOKUP(C32,Countries_WB!$A$2:$C$219,3,FALSE)) -> BRN | E32: Western Pacific | G32: High income | I32: 1.748
A33: Total fertility rate (live births per woman) | B33: 2023 | C33: Bulgaria | D33: =_xlfn.IFNA(VLOOKUP(C33,Countries_WB!$B$2:$C$219,2,FALSE),VLOOKUP(C33,Countries_WB!$A$2:$C$219,3,FALSE)) -> BGR | E33: Europe | G33: Upper middle income | I33: 1.616
A34: Total fertility rate (live births per woman) | B34: 2023 | C34: Burkina Faso | D34: =_xlfn.IFNA(VLOOKUP(C34,Countries_WB!$B$2:$C$219,2,FALSE),VLOOKUP(C34,Countries_WB!$A$2:$C$219,3,FALSE)) -> BFA | E34: Africa | G34: Low income | I34: 4.797
A35: Total fertility rate (live births per woman) | B35: 2023 | C35: Burundi | D35: =_xlfn.IFNA(VLOOKUP(C35,Countries_WB!$B$2:$C$219,2,FALSE),VLOOKUP(C35,Countries_WB!$A$2:$C$219,3,FALSE)) -> BDI | E35: Africa | G35: Low income | I35: 5.004
A36: Total fertility rate (live births per woman) | B36: 2023 | C36: Cabo Verde | D36: =_xlfn.IFNA(VLOOKUP(C36,Countries_WB!$B$2:$C$219,2,FALSE),VLOOKUP(C36,Countries_WB!$A$2:$C$219,3,FALSE)) -> CPV | E36: Africa | G36: Lower middle income | I36: 2.138
A37: Total fertility rate (live births per woman) | B37: 2023 | C37: Cambodia | D37: =_xlfn.IFNA(VLOOKUP(C37,Countries_WB!$B$2:$C$219,2,FALSE),VLOOKUP(C37,Countries_WB!$A$2:$C$219,3,FALSE)) -> KHM | E37: Western Pacific | G37: Lower middle income | I37: 2.381
A38: Total fertility rate (live births per woman) | B38: 2023 | C38: Cameroon | D38: =_xlfn.IFNA(VLOOKUP(C38,Countries_WB!$B$2:$C$219,2,FALSE),VLOOKUP(C38,Countries_WB!$A$2:$C$219,3,FALSE)) -> CMR | E38: Africa | G38: Lower middle income | I38: 4.265
A39: Total fertility rate (live births per woman) | B39: 2023 | C39: Canada | D39: =_xlfn.IFNA(VLOOKUP(C39,Countries_WB!$B$2:$C$219,2,FALSE),VLOOKUP(C39,Countries_WB!$A$2:$C$219,3,FALSE)) -> CAN | E39: Americas | G39: High income | I39: 1.481
... A43: Total fertility rate (live births per woman) | B43: 2023 | C43: Chile | D43: =_xlfn.IFNA(VLOOKUP(C43,Countries_WB!$B$2:$C$219,2,FALSE),VLOOKUP(C43,Countries_WB!$A$2:$C$219,3,FALSE)) -> CHL | E43: Americas | G43: High income | I43: 1.59
A44: Total fertility rate (live births per woman) | B44: 2023 | C44: China | D44: =_xlfn.IFNA(VLOOKUP(C44,Countries_WB!$B$2:$C$219,2,FALSE),VLOOKUP(C44,Countries_WB!$A$2:$C$219,3,FALSE)) -> CHN | E44: Western Pacific | G44: Upper middle income | H44: (8) For statistical purposes, the data for China do not include Hong Kong and Macao, Special Administrative Regions (SAR) of China, and Taiwan Province of China. | I44: 1.707
A45: Total fertility rate (live births per woman) | B45: 2023 | C45: Hong Kong SAR, China | D45: =_xlfn.IFNA(VLOOKUP(C45,Countries_WB!$B$2:$C$219,2,FALSE),VLOOKUP(C45,Countries_WB!$A$2:$C$219,3,FALSE)) -> HKG | E45: Western Pacific | G45: High income | H45: (9) As of 1 July 1997, Hong Kong became a Special Administrative Region (SAR) of China. For statistical purposes, the data for China do not include this area. | I45: 1.422
A46: Total fertility rate (live births per woman) | B46: 2023 | C46: Macao SAR, China | D46: =_xlfn.IFNA(VLOOKUP(C46,Countries_WB!$B$2:$C$219,2,FALSE),VLOOKUP(C46,Countries_WB!$A$2:$C$219,3,FALSE)) -> MAC | E46: Western Pacific | G46: High income | H46: (10) As of 20 December 1999, Macao became a Special Administrative Region (SAR) of China. For statistical purposes, the data for China do not include this area. | I46: 1.303
A47: Total fertility rate (live births per woman) | B47: 2023 | C47: Colombia | D47: =_xlfn.IFNA(VLOOKUP(C47,Countries_WB!$B$2:$C$219,2,FALSE),VLOOKUP(C47,Countries_WB!$A$2:$C$219,3,FALSE)) -> COL | E47: Americas | G47: Upper middle income | I47: 1.718
A48: Total fertility rate (live births per woman) | B48: 2023 | C48: Comoros | D48: =_xlfn.IFNA(VLOOKUP(C48,Countries_WB!$B$2:$C$219,2,FALSE),VLOOKUP(C48,Countries_WB!$A$2:$C$219,3,FALSE)) -> COM | E48: Africa | G48: Lower middle income | I48: 3.895
A49: Total fertility rate (live births per woman) | B49: 2023 | C49: Congo, Rep. | D49: =_xlfn.IFNA(VLOOKUP(C49,Countries_WB!$B$2:$C$219,2,FALSE),VLOOKUP(C49,Countries_WB!$A$2:$C$219,3,FALSE)) -> COG | E49: Africa | G49: Lower middle income | I49: 4.17
A50: Total fertility rate (live births per woman) | B50: 2023 | C50: Cook Islands | D50: =_xlfn.IFNA(VLOOKUP(C50,Countries_WB!$B$2:$C$219,2,FALSE),VLOOKUP(C50,Countries_WB!$A$2:$C$219,3,FALSE)) -> #N/A | E50: Western Pacific | I50: 2.121
A51: Total fertility rate (live births per woman) | B51: 2023 | C51: Costa Rica | D51: =_xlfn.IFNA(VLOOKUP(C51,Countries_WB!$B$2:$C$219,2,FALSE),VLOOKUP(C51,Countries_WB!$A$2:$C$219,3,FALSE)) -> CRI | E51: Americas | G51: Upper middle income | I51: 1.673
A52: Total fertility rate (live births per woman) | B52: 2023 | C52: Côte d’Ivoire | D52: =_xlfn.IFNA(VLOOKUP(C52,Countries_WB!$B$2:$C$219,2,FALSE),VLOOKUP(C52,Countries_WB!$A$2:$C$219,3,FALSE)) -> CIV | E52: Africa | G52: Lower middle income | I52: 4.371
A53: Total fertility rate (live births per woman) | B53: 2023 | C53: Croatia | D53: =_xlfn.IFNA(VLOOKUP(C53,Countries_WB!$B$2:$C$219,2,FALSE),VLOOKUP(C53,Countries_WB!$A$2:$C$219,3,FALSE)) -> HRV | E53: Europe | G53: High income | I53: 1.406
A54: Total fertility rate (live births per woman) | B54: 2023 | C54: Cuba | D54: =_xlfn.IFNA(VLOOKUP(C54,Countries_WB!$B$2:$C$219,2,FALSE),VLOOKUP(C54,Countries_WB!$A$2:$C$219,3,FALSE)) -> CUB | E54: Americas | G54: Upper middle income | I54: 1.569
A55: Total fertility rate (live births per woman) | B55: 2023 | C55: Curaçao | D55: =_xlfn.IFNA(VLOOKUP(C55,Countries_WB!$B$2:$C$219,2,FALSE),VLOOKUP(C55,Countries_WB!$A$2:$C$219,3,FALSE)) -> CUW | E55: Americas | G55: High income | H55: (13) For statistical purposes, the data for Netherlands do not include this area. | I55: 1.713
A56: Total fertility rate (live births per woman) | B56: 2023 | C56: Cyprus | D56: =_xlfn.IFNA(VLOOKUP(C56,Countries_WB!$B$2:$C$219,2,FALSE),VLOOKUP(C56,Countries_WB!$A$2:$C$219,3,FALSE)) -> CYP | E56: Europe | G56: High income | H56: (5) Refers to the whole country. | I56: 1.295
A57: Total fertility rate (live births per woman) | B57: 2023 | C57: Czechia | D57: =_xlfn.IFNA(VLOOKUP(C57,Countries_WB!$B$2:$C$219,2,FALSE),VLOOKUP(C57,Countries_WB!$A$2:$C$219,3,FALSE)) -> CZE | E57: Europe | G57: High income | I57: 1.689
A58: Total fertility rate (live births per woman) | B58: 2023 | C58: Democratic People's Republic of Korea | D58: =_xlfn.IFNA(VLOOKUP(C58,Countries_WB!$B$2:$C$219,2,FALSE),VLOOKUP(C58,Countries_WB!$A$2:$C$219,3,FALSE)) -> #N/A | E58: South-East Asia | G58: Low income | I58: 1.86
A59: Total fertility rate (live births per woman) | B59: 2023 | C59: Congo, Dem. Rep. | D59: =_xlfn.IFNA(VLOOKUP(C59,Countries_WB!$B$2:$C$219,2,FALSE),VLOOKUP(C59,Countries_WB!$A$2:$C$219,3,FALSE)) -> COD | E59: Africa | G59: Low income | I59: 5.415
A60: Total fertility rate (live births per woman) | B60: 2023 | C60: Denmark | D60: =_xlfn.IFNA(VLOOKUP(C60,Countries_WB!$B$2:$C$219,2,FALSE),VLOOKUP(C60,Countries_WB!$A$2:$C$219,3,FALSE)) -> DNK | E60: Europe | G60: High income | H60: (21) For statistical purposes, the data for Denmark do not include Faroe Islands, and Greenland. | I60: 1.773
A61: Total fertility rate (live births per woman) | B61: 2023 | C61: Djibouti | D61: =_xlfn.IFNA(VLOOKUP(C61,Countries_WB!$B$2:$C$219,2,FALSE),VLOOKUP(C61,Countries_WB!$A$2:$C$219,3,FALSE)) -> DJI | E61: Eastern Mediterranean | G61: Lower middle income | I61: 2.499
A62: Total fertility rate (live births per woman) | B62: 2023 | C62: Dominica | D62: =_xlfn.IFNA(VLOOKUP(C62,Countries_WB!$B$2:$C$219,2,FALSE),VLOOKUP(C62,Countries_WB!$A$2:$C$219,3,FALSE)) -> DMA | E62: Americas | G62: Upper middle income | I62: 1.556
A63: Total fertility rate (live births per woman) | B63: 2023 | C63: Dominican Republic | D63: =_xlfn.IFNA(VLOOKUP(C63,Countries_WB!$B$2:$C$219,2,FALSE),VLOOKUP(C63,Countries_WB!$A$2:$C$219,3,FALSE)) -> DOM | E63: Americas | G63: Upper middle income | I63: 2.224
A64: Total fertility rate (live births per woman) | B64: 2023 | C64: Ecuador | D64: =_xlfn.IFNA(VLOOKUP(C64,Countries_WB!$B$2:$C$219,2,FALSE),VLOOKUP(C64,Countries_WB!$A$2:$C$219,3,FALSE)) -> ECU | E64: Americas | G64: Upper middle income | I64: 2.311
A65: Total fertility rate (live births per woman) | B65: 2023 | C65: Egypt | D65: =_xlfn.IFNA(VLOOKUP(C65,Countries_WB!$B$2:$C$219,2,FALSE),VLOOKUP(C65,Countries_WB!$A$2:$C$219,3,FALSE)) -> EGY | E65: Eastern Mediterranean | G65: Lower middle income | I65: 3.115
A66: Total fertility rate (live births per woman) | B66: 2023 | C66: El Salvador | D66: =_xlfn.IFNA(VLOOKUP(C66,Countries_WB!$B$2:$C$219,2,FALSE),VLOOKUP(C66,Countries_WB!$A$2:$C$219,3,FALSE)) -> SLV | E66: Americas | G66: Upper middle income | I66: 1.948
A67: Total fertility rate (live births per woman) | B67: 2023 | C67: Equatorial Guinea | D67: =_xlfn.IFNA(VLOOKUP(C67,Countries_WB!$B$2:$C$219,2,FALSE),VLOOKUP(C67,Countries_WB!$A$2:$C$219,3,FALSE)) -> GNQ | E67: Africa | G67: Upper middle income | I67: 4.111
A68: Total fertility rate (live births per woman) | B68: 2023 | C68: Eritrea | D68: =_xlfn.IFNA(VLOOKUP(C68,Countries_WB!$B$2:$C$219,2,FALSE),VLOOKUP(C68,Countries_WB!$A$2:$C$219,3,FALSE)) -> ERI | E68: Africa | G68: Low income | I68: 3.737
A69: Total fertility rate (live births per woman) | B69: 2023 | C69: Estonia | D69: =_xlfn.IFNA(VLOOKUP(C69,Countries_WB!$B$2:$C$219,2,FALSE),VLOOKUP(C69,Countries_WB!$A$2:$C$219,3,FALSE)) -> EST | E69: Europe | G69: High income | I69: 1.637
A70: Total fertility rate (live births per woman) | B70: 2023 | C70: Eswatini | D70: =_xlfn.IFNA(VLOOKUP(C70,Countries_WB!$B$2:$C$219,2,FALSE),VLOOKUP(C70,Countries_WB!$A$2:$C$219,3,FALSE)) -> SWZ | E70: Africa | G70: Lower middle income | I70: 2.787
A71: Total fertility rate (live births per woman) | B71: 2023 | C71: Ethiopia | D71: =_xlfn.IFNA(VLOOKUP(C71,Countries_WB!$B$2:$C$219,2,FALSE),VLOOKUP(C71,Countries_WB!$A$2:$C$219,3,FALSE)) -> ETH | E71: Africa | G71: Low income | I71: 3.777
A72: Total fertility rate (live births per woman) | B72: 2023 | C72: Falkland Islands (Malvinas) | D72: =_xlfn.IFNA(VLOOKUP(C72,Countries_WB!$B$2:$C$219,2,FALSE),VLOOKUP(C72,Countries_WB!$A$2:$C$219,3,FALSE)) -> #N/A | I72: 1.77
A73: Total fertility rate (live births per woman) | B73: 2023 | C73: Faroe Islands | D73: =_xlfn.IFNA(VLOOKUP(C73,Countries_WB!$B$2:$C$219,2,FALSE),VLOOKUP(C73,Countries_WB!$A$2:$C$219,3,FALSE)) -> FRO | I73: 2.382
A74: Total fertility rate (live births per woman) | B74: 2023 | C74: Fiji | D74: =_xlfn.IFNA(VLOOKUP(C74,Countries_WB!$B$2:$C$219,2,FALSE),VLOOKUP(C74,Countries_WB!$A$2:$C$219,3,FALSE)) -> FJI | E74: Western Pacific | G74: Upper middle income | I74: 2.643
A75: Total fertility rate (live births per woman) | B75: 2023 | C75: Finland | D75: =_xlfn.IFNA(VLOOKUP(C75,Countries_WB!$B$2:$C$219,2,FALSE),VLOOKUP(C75,Countries_WB!$A$2:$C$219,3,FALSE)) -> FIN | E75: Europe | G75: High income | H75: (22) Including Åland Islands. | I75: 1.414
A76: Total fertility rate (live births per woman) | B76: 2023 | C76: France | D76: =_xlfn.IFNA(VLOOKUP(C76,Countries_WB!$B$2:$C$219,2,FALSE),VLOOKUP(C76,Countries_WB!$A$2:$C$219,3,FALSE)) -> FRA | E76: Europe | G76: High income | H76: (27) For statistical purposes, the data for France do not include French Guiana, French Polynesia, Guadeloupe, Martinique, Mayotte, New Caledonia, Réunion, Saint Pierre and Miquelon, Saint Barthélemy, Saint Martin (French part), Wallis and Futuna Islands. | I76: 1.844
A77: Total fertility rate (live births per woman) | B77: 2023 | C77: French Guiana | D77: =_xlfn.IFNA(VLOOKUP(C77,Countries_WB!$B$2:$C$219,2,FALSE),VLOOKUP(C77,Countries_WB!$A$2:$C$219,3,FALSE)) -> #N/A | H77: (2) For statistical purposes, the data for France do not include this area. | I77: 3.177
A78: Total fertility rate (live births per woman) | B78: 2023 | C78: French Polynesia | D78: =_xlfn.IFNA(VLOOKUP(C78,Countries_WB!$B$2:$C$219,2,FALSE),VLOOKUP(C78,Countries_WB!$A$2:$C$219,3,FALSE)) -> PYF | E78: Western Pacific | G78: High income | H78: (2) For statistical purposes, the data for France do not include this area. | I78: 1.873
A79: Total fertility rate (live births per woman) | B79: 2023 | C79: Gabon | D79: =_xlfn.IFNA(VLOOKUP(C79,Countries_WB!$B$2:$C$219,2,FALSE),VLOOKUP(C79,Countries_WB!$A$2:$C$219,3,FALSE)) -> GAB | E79: Africa | G79: Upper middle income | I79: 3.694
A80: Total fertility rate (live births per woman) | B80: 2023 | C80: Gambia | D80: =_xlfn.IFNA(VLOOKUP(C80,Countries_WB!$B$2:$C$219,2,FALSE),VLOOKUP(C80,Countries_WB!$A$2:$C$219,3,FALSE)) -> #N/A | E80: Africa | G80: Low income | I80: 4.871
A81: Total fertility rate (live births per woman) | B81: 2023 | C81: Georgia | D81: =_xlfn.IFNA(VLOOKUP(C81,Countries_WB!$B$2:$C$219,2,FALSE),VLOOKUP(C81,Countries_WB!$A$2:$C$219,3,FALSE)) -> GEO | E81: Europe | G81: Upper middle income | H81: (6) Including Abkhazia and South Ossetia. | I81: 2.014
A82: Total fertility rate (live births per woman) | B82: 2023 | C82: Germany | D82: =_xlfn.IFNA(VLOOKUP(C82,Countries_WB!$B$2:$C$219,2,FALSE),VLOOKUP(C82,Countries_WB!$A$2:$C$219,3,FALSE)) -> DEU | E82: Europe | G82: High income | I82: 1.618
A83: Total fertility rate (live births per woman) | B83: 2023 | C83: Ghana | D83: =_xlfn.IFNA(VLOOKUP(C83,Countries_WB!$B$2:$C$219,2,FALSE),VLOOKUP(C83,Countries_WB!$A$2:$C$219,3,FALSE)) -> GHA | E83: Africa | G83: Lower middle income | I83: 3.622
A84: Total fertility rate (live births per woman) | B84: 2023 | C84: Gibraltar | D84: =_xlfn.IFNA(VLOOKUP(C84,Countries_WB!$B$2:$C$219,2,FALSE),VLOOKUP(C84,Countries_WB!$A$2:$C$219,3,FALSE)) -> GIB | I84: 1.86
A85: Total fertility rate (live births per woman) | B85: 2023 | C85: Greece | D85: =_xlfn.IFNA(VLOOKUP(C85,Countries_WB!$B$2:$C$219,2,FALSE),VLOOKUP(C85,Countries_WB!$A$2:$C$219,3,FALSE)) -> GRC | E85: Europe | G85: High income | I85: 1.261
A86: Total fertility rate (live births per woman) | B86: 2023 | C86: Greenland | D86: =_xlfn.IFNA(VLOOKUP(C86,Countries_WB!$B$2:$C$219,2,FALSE),VLOOKUP(C86,Countries_WB!$A$2:$C$219,3,FALSE)) -> GRL | E86: Europe | G86: High income | I86: 1.89
A87: Total fertility rate (live births per woman) | B87: 2023 | C87: Grenada | D87: =_xlfn.IFNA(VLOOKUP(C87,Countries_WB!$B$2:$C$219,2,FALSE),VLOOKUP(C87,Countries_WB!$A$2:$C$219,3,FALSE)) -> GRD | E87: Americas | G87: Upper middle income | I87: 1.969
A88: Total fertility rate (live births per woman) | B88: 2023 | C88: Guadeloupe | D88: =_xlfn.IFNA(VLOOKUP(C88,Countries_WB!$B$2:$C$219,2,FALSE),VLOOKUP(C88,Countries_WB!$A$2:$C$219,3,FALSE)) -> #N/A | H88: (2) For statistical purposes, the data for France do not include this area. | I88: 2.09
A89: Total fertility rate (live births per woman) | B89: 2023 | C89: Guam | D89: =_xlfn.IFNA(VLOOKUP(C89,Countries_WB!$B$2:$C$219,2,FALSE),VLOOKUP(C89,Countries_WB!$A$2:$C$219,3,FALSE)) -> GUM | E89: Western Pacific | G89: High income | H89: (14) For statistical purposes, the data for United States of America do not include this area. | I89: 2.227
A90: Total fertility rate (live births per woman) | B90: 2023 | C90: Guatemala | D90: =_xlfn.IFNA(VLOOKUP(C90,Countries_WB!$B$2:$C$219,2,FALSE),VLOOKUP(C90,Countries_WB!$A$2:$C$219,3,FALSE)) -> GTM | E90: Americas | G90: Upper middle income | I90: 2.653
A91: Total fertility rate (live births per woman) | B91: 2023 | C91: Guinea | D91: =_xlfn.IFNA(VLOOKUP(C91,Countries_WB!$B$2:$C$219,2,FALSE),VLOOKUP(C91,Countries_WB!$A$2:$C$219,3,FALSE)) -> GIN | E91: Africa | G91: Lower middle income | I91: 4.342
A92: Total fertility rate (live births per woman) | B92: 2023 | C92: Guinea-Bissau | D92: =_xlfn.IFNA(VLOOKUP(C92,Countries_WB!$B$2:$C$219,2,FALSE),VLOOKUP(C92,Countries_WB!$A$2:$C$219,3,FALSE)) -> GNB | E92: Africa | G92: Low income | I92: 4.131
A93: Total fertility rate (live births per woman) | B93: 2023 | C93: Guyana | D93: =_xlfn.IFNA(VLOOKUP(C93,Countries_WB!$B$2:$C$219,2,FALSE),VLOOKUP(C93,Countries_WB!$A$2:$C$219,3,FALSE)) -> GUY | E93: Americas | G93: High income | I93: 2.357
A94: Total fertility rate (live births per woman) | B94: 2023 | C94: Haiti | D94: =_xlfn.IFNA(VLOOKUP(C94,Countries_WB!$B$2:$C$219,2,FALSE),VLOOKUP(C94,Countries_WB!$A$2:$C$219,3,FALSE)) -> HTI | E94: Americas | G94: Lower middle income | I94: 2.723
A95: Total fertility rate (live births per woman) | B95: 2023 | C95: Holy See | D95: =_xlfn.IFNA(VLOOKUP(C95,Countries_WB!$B$2:$C$219,2,FALSE),VLOOKUP(C95,Countries_WB!$A$2:$C$219,3,FALSE)) -> #N/A | I95: 1
A96: Total fertility rate (live births per woman) | B96: 2023 | C96: Honduras | D96: =_xlfn.IFNA(VLOOKUP(C96,Countries_WB!$B$2:$C$219,2,FALSE),VLOOKUP(C96,Countries_WB!$A$2:$C$219,3,FALSE)) -> HND | E96: Americas | G96: Lower middle income | I96: 2.305
A97: Total fertility rate (live births per woman) | B97: 2023 | C97: Hungary | D97: =_xlfn.IFNA(VLOOKUP(C97,Countries_WB!$B$2:$C$219,2,FALSE),VLOOKUP(C97,Countries_WB!$A$2:$C$219,3,FALSE)) -> HUN | E97: Europe | G97: High income | I97: 1.547
A98: Total fertility rate (live births per woman) | B98: 2023 | C98: Iceland | D98: =_xlfn.IFNA(VLOOKUP(C98,Countries_WB!$B$2:$C$219,2,FALSE),VLOOKUP(C98,Countries_WB!$A$2:$C$219,3,FALSE)) -> ISL | E98: Europe | G98: High income | I98: 1.71
A99: Total fertility rate (live births per woman) | B99: 2023 | C99: India | D99: =_xlfn.IFNA(VLOOKUP(C99,Countries_WB!$B$2:$C$219,2,FALSE),VLOOKUP(C99,Countries_WB!$A$2:$C$219,3,FALSE)) -> IND | E99: South-East Asia | G99: Lower middle income | I99: 2.128
A100: Total fertility rate (live births per woman) | B100: 2023 | C100: Indonesia | D100: =_xlfn.IFNA(VLOOKUP(C100,Countries_WB!$B$2:$C$219,2,FALSE),VLOOKUP(C100,Countries_WB!$A$2:$C$219,3,FALSE)) -> IDN | E100: South-East Asia | G100: Upper middle income | I100: 2.211
A101: Total fertility rate (live births per woman) | B101: 2023 | C101: Iran | D101: =_xlfn.IFNA(VLOOKUP(C101,Countries_WB!$B$2:$C$219,2,FALSE),VLOOKUP(C101,Countries_WB!$A$2:$C$219,3,FALSE)) -> IRN | E101: Eastern Mediterranean | G101: Lower middle income | I101: 2.096
A102: Total fertility rate (live births per woman) | B102: 2023 | C102: Iraq | D102: =_xlfn.IFNA(VLOOKUP(C102,Countries_WB!$B$2:$C$219,2,FALSE),VLOOKUP(C102,Countries_WB!$A$2:$C$219,3,FALSE)) -> IRQ | E102: Eastern Mediterranean | G102: Upper middle income | I102: 3.414
A103: Total fertility rate (live births per woman) | B103: 2023 | C103: Ireland | D103: =_xlfn.IFNA(VLOOKUP(C103,Countries_WB!$B$2:$C$219,2,FALSE),VLOOKUP(C103,Countries_WB!$A$2:$C$219,3,FALSE)) -> IRL | E103: Europe | G103: High income | I103: 1.779
...

Sheet Tax_Rates
A1: Country | B1: Taxation rate | C1: Source
A2: Switzerland | B2: 9.88
A3: Norway | B3: 21.131082
A4: Iceland | B4: 21.041793
A5: Belgium | B5: 25
A6: Italy | B6: 23
A7: Netherlands | B7: 8.9
A8: Ireland | B8: 20
A9: Denmark | B9: 44.444554
A10: United Kingdom | B10: 12
A11: Israel | B11: 10
A12: France | B12: 1
A13: United States | B13: 12
... A15: Australia | B15: 19
A16: Uruguay | B16: 24 | C16: PWC website (average for middle income value)
A17: New Zealand | B17: 13
A18: Finland | B18: 6
A19: Canada | B19: 15
A20: Cyprus | B20: 25 | C20: PWC website (average for middle income value)
A21: Greece | B21: 22
A22: Austria | B22: 8
A23: Germany | B23: 5
A24: Spain | B24: 20
A25: Sweden | B25: 32
A26: Puerto Rico | B26: 14 | C26: PWC website (average for middle income value)
A27: Lebanon | B27: 5
A28: South Africa | B28: 18
A29: Portugal | B29: 16
A30: Panama | B30: 15 | C30: PWC website (average for middle income value)
A31: Latvia | B31: 8.9659381
A32: Slovenia | B32: 8.9973502
A33: Lithuania | B33: 5
A34: Estonia | B34: 20
A35: Croatia | B35: 5.9794112
A36: Russian Federation | B36: 13
A37: Japan | B37: 5
A38: Chile | B38: 8
A39: Jordan | B39: 7
A40: Dominican Republic | B40: 15 | C40: PWC website (average for middle income value)
A41: Qatar | B41: 10
A42: Argentina | B42: 10
A43: Hong Kong SAR, China | B43: 5
A44: Korea, Rep. | B44: 10
A45: Romania | B45: 10
A46: Hungary | B46: 15
A47: Belarus | B47: 13
A48: Azerbaijan | B48: 10
A49: Iraq | B49: 4.8049249
A50: Bulgaria | B50: 10
A51: Slovak Republic | B51: 18.789696
A52: Montenegro | B52: 9
A53: Georgia | B53: 20 | C53: PWC website (average for middle income value)
A54: Albania | B54: 5
A55: United Arab Emirates | B55: 9 | C55: PWC website (average for middle income value)
A56: Kazakhstan | B56: 10
A57: Saudi Arabia | B57: 0 | C57: PWC website (average for middle income value)
A58: Poland | B58: 12.311549
A59: Czech Republic | B59: 14.807413
A60: Brazil | B60: 5
A61: Singapore | B61: 2
A62: Mexico | B62: 8
A63: Moldova | B63: 12
A64: Serbia | B64: 7.5957857
A65: Iran, Islamic Rep. | B65: 9.6738526
A66: Macedonia, FYR | B66: 10
A67: Ukraine | B67: 18
A68: Bosnia And Herzegovina | B68: 10
A69: Turkey | B69: 17
A70: Ecuador | B70: 15 | C70: PWC website (average for middle income value)
A71: Taiwan | B71: 5
A72: Morocco | B72: 5
A73: Kosovo | B73: 4
A74: Colombia | B74: 5
A75: Venezuela, RB | B75: 6
A76: Peru | B76: 10
A77: China | B77: 6
A78: Philippines | B78: 10
A79: Egypt, Arab Rep. | B79: 10
A80: Algeria | B80: 15
A81: Malaysia | B81: 2
A82: Nepal | B82: 10
... A87: Tunisia | B87: 13
A88: Pakistan | B88: 12.5 | C88: PWC website (average for middle income value)
A89: Sri Lanka | B89: 6
A90: Croatia | B90: 7
A91: Brazil | B91: 8
A92: Romania | B92: 9
A93: Serbia | B93: 10
A94: Albania | B94: 11
A95: China | B95: 12
A96: India | B96: 2.5
A97: Switzerland | B97: 9.88
A98: Iceland | B98: 21.041793
A99: Norway | B99: 21.131082
A100: Denmark | B100: 44.444554
... A357: Colombo, Sri Lanka | B357: 6

Sheet WB 2022 ExRates
A1: Data Source | B1: World Development Indicators
A2: Last Updated Date | B2: 45343
A3: Vlookup | B3: 1 | C3: 2 | D3: 3 | E3: 4 | F3: 5 | G3: 6 | H3: 7 | I3: 8 | J3: 9 | K3: 10 | L3: 11 | M3: 12 | N3: 13 | O3: 14 | P3: 15 | Q3: 16 | R3: 17 | S3: 18 | T3: 19 | U3: 20 | V3: 21 | W3: 22 | X3: 23 | Y3: 24 | Z3: 25 | AA3: 26 | AB3: 27 | AC3: 28 | AD3: 29 | AE3: 30 | AF3: 31 | AG3: 32 | AH3: 33 | AI3: 34 | AJ3: 35 | AK3: 36 | AL3: 37 | AM3: 38 | AN3: 39 | AO3: 40 | AP3: 41 | AQ3: 42 | AR3: 43 | AS3: 44 | AT3: 45 | AU3: 46 | AV3: 47 | AW3: 48 | AX3: 49 | AY3: 50 | AZ3: 51 | BA3: 52 | BB3: 53 | BC3: 54 | BD3: 55 | BE3: 56 | BF3: 57 | BG3: 58 | BH3: 59 | BI3: 60 | BJ3: 61 | BK3: 62 | BL3: 63 | BM3: 64 | BN3: 65 | BO3: 66
A4: Country Name | B4: Country Code | C4: Indicator Name | D4: Indicator Code | E4: 1960 | F4: 1961 | G4: 1962 | H4: 1963 | I4: 1964 | J4: 1965 | K4: 1966 | L4: 1967 | M4: 1968 | N4: 1969 | O4: 1970 | P4: 1971 | Q4: 1972 | R4: 1973 | S4: 1974 | T4: 1975 | U4: 1976 | V4: 1977 | W4: 1978 | X4: 1979 | Y4: 1980 | Z4: 1981 | AA4: 1982 | AB4: 1983 | AC4: 1984 | AD4: 1985 | AE4: 1986 | AF4: 1987 | AG4: 1988 | AH4: 1989 | AI4: 1990 | AJ4: 1991 | AK4: 1992 | AL4: 1993 | AM4: 1994 | AN4: 1995 | AO4: 1996 | AP4: 1997 | AQ4: 1998 | AR4: 1999 | AS4: 2000 | AT4: 2001 | AU4: 2002 | AV4: 2003 | AW4: 2004 | AX4: 2005 | AY4: 2006 | AZ4: 2007 | BA4: 2008 | BB4: 2009 | BC4: 2010 | BD4: 2011 | BE4: 2012 | BF4: 2013 | BG4: 2014 | BH4: 2015 | BI4: 2016 | BJ4: 2017 | BK4: 2018 | BL4: 2019 | BM4: 2020 | BN4: 2021 | BO4: 2022
